Workbook
Name Type: '[1]Service Marketing Plan'!#REF!
Name Type: '[2]Business Meeting Agenda'!#REF!

Sheet EXAMPLE Multi Project Dashboard
B2: Multiple Project Dashboard Tracking Template Example
B3: DELIVERY TIMELINE & RESOURCES
B7: PROJECT FINANCIALS
B10: RISK ANALYSIS
B15: OPEN & PENDING ACTIONS
B20: PROJECT REPORT
B22: PROJECT NAME | C22: SCHEDULE | D22: BUDGET | E22: RESOURCES | F22: RISKS | G22: ISSUES | H22: COMMENTS
B23: Project A
B24: Project B
B25: Project C
B26: Project D
B27: Project E
B28: Project F
B29: Project G
B30: Project H
B31: Project J
B32: Project K
B33: Project L
B34: Project M
... B38: DASHBOARD DATA
B39: PROJECT NAME | C39: TIMELINE | G39: NUMBER OF TEAM MEMBERS | H39: BUDGET | K39: RISKS | N39: OPEN | P39: PENDING ACTIONS
C40: CALENDAR | D40: BEGIN | E40: FINISH | F40: # of DAYS | H40: PROJECTED | I40: ACTUAL | J40: REMAINDER | K40: HIGH | L40: MEDIUM | M40: LOW | N40: ISSUES | O40: REVISIONS
B41: Project A | C41: 45778 | D41: 45782 | E41: 45839 | F41: =E41-D41 -> 57 | G41: 10 | H41: 1000000 | I41: 880000 | J41: =(H41-I41) -> 120000 | K41: 1 | L41: 0 | M41: 4 | N41: 2 | O41: 0 | P41: 4
B42: Project B | C42: 45809 | D42: 45787 | E42: 45879 | F42: =E42-D42 -> 92 | G42: 5 | H42: 900000 | I42: 920000 | J42: =(H42-I42) -> -20000 | K42: 2 | L42: 3 | M42: 5 | N42: 1 | O42: 2 | P42: 3
B43: Project C | C43: 45839 | D43: 45818 | E43: 46082 | F43: =E43-D43 -> 264 | G43: 10 | H43: 860000 | I43: 850000 | J43: =(H43-I43) -> 10000 | K43: 3 | L43: 4 | M43: 3 | N43: 2 | O43: 1 | P43: 2
B44: Project D | C44: 45870 | D44: 45830 | E44: 45873 | F44: =E44-D44 -> 43 | G44: 5 | H44: 1000000 | I44: 998050 | J44: =(H44-I44) -> 1950 | K44: 5 | L44: 8 | M44: 1 | N44: 1 | O44: 0 | P44: 0
B45: Project E | C45: 45901 | D45: 45852 | E45: 45962 | F45: =E45-D45 -> 110 | G45: 10 | H45: 294000 | I45: 280000 | J45: =(H45-I45) -> 14000 | K45: 8 | L45: 6 | M45: 4 | N45: 0 | O45: 3 | P45: 1
B46: Project F | C46: 45931 | D46: 45852 | E46: 46042 | F46: =E46-D46 -> 190 | G46: 5 | H46: 123400 | I46: 125000 | J46: =(H46-I46) -> -1600 | K46: 5 | L46: 0 | M46: 0 | N46: 2 | O46: 0 | P46: 2
B47: Project G | C47: 45962 | D47: 45870 | E47: 45931 | F47: =E47-D47 -> 61 | G47: 10 | H47: 250500 | I47: 246000 | J47: =(H47-I47) -> 4500 | K47: 6 | L47: 4 | M47: 0 | N47: 1 | O47: 2 | P47: 3
B48: Project H | C48: 45992 | D48: 45883 | E48: 45899 | F48: =E48-D48 -> 16 | G48: 5 | H48: 127200 | I48: 126000 | J48: =(H48-I48) -> 1200 | K48: 7 | L48: 3 | M48: 3 | N48: 0 | O48: 1 | P48: 4
B49: Project J | C49: 46023 | D49: 45901 | E49: 46001 | F49: =E49-D49 -> 100 | G49: 10 | H49: 80000 | I49: 79900 | J49: =(H49-I49) -> 100 | K49: 0 | L49: 2 | M49: 4 | N49: 1 | O49: 3 | P49: 2
B50: Project K | C50: 46054 | D50: 45931 | E50: 45976 | F50: =E50-D50 -> 45 | G50: 5 | H50: 77000 | I50: 77000 | J50: =(H50-I50) -> 0 | K50: 4 | L50: 4 | M50: 5 | N50: 2 | O50: 0 | P50: 0
B51: Project L | C51: 46082 | D51: 45931 | E51: 45992 | F51: =E51-D51 -> 61 | G51: 10 | H51: 65000 | I51: 65000 | J51: =(H51-I51) -> 0 | K51: 3 | L51: 6 | M51: 4 | N51: 3 | O51: 2 | P51: 0
B52: Project M | C52: 46113 | D52: 45962 | E52: 45992 | F52: =E52-D52 -> 30 | G52: 5 | H52: 550000 | I52: 551000 | J52: =(H52-I52) -> -1000 | K52: 2 | L52: 3 | M52: 6 | N52: 0 | O52: 1 | P52: 1
... B54: Project P | C54: 46174 | D54: 45992 | E54: 46063 | F54: =E54-D54 -> 71 | G54: 5 | H54: 32500 | I54: 33000 | J54: =(H54-I54) -> -500 | K54: 5 | L54: 0 | M54: 2 | N54: 2 | O54: 1 | P54: 3
H55: =SUM(H41:H54) -> 5404600 | I55: =SUM(I41:I54) -> 5272950 | J55: =SUM(J41:J54) -> 131650 | K55: =SUM(K41:K54) -> 52 | L55: =SUM(L41:L54) -> 44 | M55: =SUM(M41:M54) -> 48 | N55: =SUM(N41:N54) -> 18 | O55: =SUM(O41:O54) -> 16 | P55: =SUM(P41:P54) -> 27
B57: CLICK HERE TO CREATE IN SMARTSHEET

Sheet – Disclaimer –
B2: Any articles, templates, or information provided by Smartsheet on the website are for reference only. While we strive to keep the information up to date and correct, we make no representations or warranties of any kind, express or implied, about the completeness, accuracy, reliability, suitability, or availability with respect to the website or the information, articles, templates, or related graphics contained on the website. Any reliance you place on such information is therefore strictly at your own risk.

Sheet Ticket Issue Client Dashboard
B1: Maintenance Client Issue Dashboard Tracking 30/06/2026
B3: CONTRACT PERIOD
B6: Issue by Clients
B11: SLA EXCEED BY CLIENTS
B17: DASHBOARD DATA | G17: **Delete unused rows to correctly populate charts and graphs, above.
B18: PROJECT NAME | C18: CONTRACT DATE | G18: TOTAL TICKETS | H18: FAILED SLA | K18: OPEN | M18: COMPLETED / CLOSED
C19: CALENDAR | D19: BEGIN | E19: FINISH | F19: # of DAYS | H19: 1-30 DAYS | I19: 31-60 DAYS | J19: > 60 DAYS | K19: INPROGRESS | L19: PENDING
B20: FRIM | C20: 46023 | D20: 46023 | E20: 46387 | F20: =E20-D20+1 -> 365 | G20: =FRIM!C1 -> 104 | H20: =FRIM!T9 -> 7 | I20: =FRIM!U9 -> 6 | J20: =FRIM!V9 -> 17 | K20: =FRIM!T4 -> 0 | L20: =FRIM!T3 -> 30 | M20: =FRIM!G1 -> 74
B21: MTIB | C21: 46023 | D21: 45962 | E21: 46326 | F21: =E21-D21+1 -> 365 | G21: =MTIB!C1 -> 52 | H21: =MTIB!T9 -> 2 | I21: =MTIB!U9 -> 6 | J21: =MTIB!V9 -> 7 | K21: =MTIB!T4 -> 1 | L21: =MTIB!T3 -> 15 | M21: =MTIB!G1 -> 36
B22: MPOB | C22: 46023 | D22: 46023 | E22: 46387 | F22: =E22-D22+1 -> 365 | G22: =MPOB!C1 -> 206 | H22: =MPOB!T9 -> 0 | I22: =MPOB!U9 -> 11 | J22: =MPOB!V9 -> 26 | K22: =MPOB!T4 -> 9 | L22: =MPOB!T3 -> 29 | M22: =MPOB!G1 -> 168
B23: LKTN | C23: 46023 | D23: 46023 | E23: 46387 | F23: =E23-D23+1 -> 365 | G23: =LKTN!C1 -> 15 | H23: =LKTN!T9 -> 2 | I23: =LKTN!U9 -> 2 | J23: =LKTN!V9 -> 0 | K23: =LKTN!T4 -> 0 | L23: =LKTN!T3 -> 4 | M23: =LKTN!G1 -> 11
B24: LAM | C24: 45931 | D24: 45931 | E24: 46295 | F24: =E24-D24+1 -> 365 | G24: =LAM!C1 -> 21 | H24: =LAM!T9 -> 1 | I24: =LAM!U9 -> 2 | J24: =LAM!V9 -> 1 | K24: =LAM!T4 -> 0 | L24: =LAM!T3 -> 4 | M24: =LAM!G1 -> 17
B25: ISN | C25: 46023 | D25: 46023 | E25: 46387 | F25: =E25-D25+1 -> 365 | G25: =ISN!C1 -> 25 | H25: =ISN!T9 -> 6 | I25: =ISN!U9 -> 1 | J25: =ISN!V9 -> 2 | K25: =ISN!T4 -> 2 | L25: =ISN!T3 -> 7 | M25: =ISN!G1 -> 16
B26: MSN | C26: 46023 | D26: 45809 | E26: 46173 | F26: =E26-D26+1 -> 365 | G26: =MSN!C1 -> 9 | H26: =MSN!T9 -> 0 | I26: =MSN!U9 -> 0 | J26: =MSN!V9 -> 3 | K26: =MSN!T4 -> 1 | L26: =MSN!T3 -> 2 | M26: =MSN!G1 -> 6
C27: 46023 | D27: 46023 | E27: 46387 | F27: =E27-D27+1 -> 365 | G27: 0 | H27: 0 | I27: 0 | J27: 0 | K27: 0 | L27: 0 | M27: 0
B28: KHTP (KTPC) | C28: 46023 | D28: 45927 | E28: 46291 | F28: =E28-D28+1 -> 365 | G28: =KTPC!C1 -> 9 | H28: =KTPC!T9 -> 0 | I28: =KTPC!U9 -> 0 | J28: =KTPC!V9 -> 0 | K28: =KTPC!T4 -> 0 | L28: =KTPC!T3 -> 0 | M28: =KTPC!G1 -> 9
B29: KUIPS (Warranty) | C29: 46023 | D29: 46023 | E29: 46752 | F29: =E29-D29+1 -> 730 | G29: =KUIPS!C1 -> 32 | H29: =KUIPS!T9 -> 23 | I29: =KUIPS!U9 -> 0 | J29: =KUIPS!V9 -> 0 | K29: =KUIPS!T4 -> 0 | L29: =KUIPS!T3 -> 23 | M29: =KUIPS!G1 -> 9
F30: =E30-D30+1 -> 1
F31: =E31-D31+1 -> 1
F32: =E32-D32+1 -> 1
F33: =E33-D33+1 -> 1
H34: =SUM(H20:H33) -> 41 | I34: =SUM(I20:I33) -> 28 | J34: =SUM(J20:J33) -> 56 | K34: =SUM(K20:K33) -> 13 | L34: =SUM(L20:L33) -> 114 | M34: =SUM(M20:M33) -> 346
B63: **Enter data in the table beginning on Row 41

Sheet Ageing Issue
A1: No | B1: Company | C1: Ticket No | D1: Project | E1: Ticket Detail | F1: Ageing | H1: No | I1: Company | J1: Ticket No | K1: Project | L1: Ticket Detail | M1: Ageing | O1: No | P1: Company | Q1: Ticket No | R1: Project | S1: Ticket Detail | T1: Ageing | V1: No | W1: Company | X1: Ticket No | Y1: Project | Z1: Ticket Detail | AA1: Ageing | AC1: No | AD1: Company | AE1: Ticket No | AF1: Project | AG1: Ticket Detail | AH1: Ageing | AJ1: No | AK1: Company | AL1: Ticket No | AM1: Project | AN1: Ticket Detail | AO1: Ageing | AQ1: No | AR1: Company | AS1: Ticket No | AT1: Project | AU1: Ticket Detail | AV1: Ageing
A2: 1 | B2: {=IFERROR(INDEX(FRIM!$E$3:$E$1000, SMALL(IF(FRIM!$Q$3:$Q$1000<>"", ROW(FRIM!$Q$3:$Q$1000)-ROW(FRIM!$Q$3)+1), ROWS(A$2:A2))),"")} -> FRIM | C2: {=IFERROR(INDEX(FRIM!$B$3:$B$1000, SMALL(IF(FRIM!$Q$3:$Q$1000<>"", ROW(FRIM!$Q$3:$Q$1000)-ROW(FRIM!$Q$3)+1), ROWS(A$2:A2))),"")} -> T/2026/00060 | D2: {=IFERROR(INDEX(FRIM!$D$3:$D$1000, SMALL(IF(FRIM!$Q$3:$Q$1000<>"", ROW(FRIM!$Q$3:$Q$1000)-ROW(FRIM!$Q$3)+1), ROWS(A$2:A2))),"")} -> MYPROCUREMENT | E2: {=IFERROR(INDEX(FRIM!$G$3:$G$1000, SMALL(IF(FRIM!$Q$3:$Q$1000<>"", ROW(FRIM!$Q$3:$Q$1000)-ROW(FRIM!$Q$3)+1), ROWS(A$2:A2))),"")} -> No Aduan: W2488 Name: NUR SYAQIRAH BINTI MOHAMED FOZI Date: 07/01/2026 Desc: PADA DEFINISI TEMPOH TUTUP RO MOHON UNTUK TUTUP JUGA SISTEM BAGI PELULUS DAN PENYOKONG VOT SEPERTIMANA TEMPOH YANG DITETAPKAN. | F2: {=IFERROR(INDEX(FRIM!$Q$3:$Q$1000, SMALL(IF(FRIM!$Q$3:$Q$1000<>"", ROW(FRIM!$Q$3:$Q$1000)-ROW(FRIM!$Q$3)+1), ROWS(A$2:A2))),"")} -> >60 Days | H2: 1 | I2: {=IFERROR(INDEX(MTIB!$E$3:$E$1000, SMALL( IF((MTIB!$Q$3:$Q$1000<>"")*(MTIB!$Q$3:$Q$1000<>"Not Due"), ROW(MTIB!$Q$3:$Q$1000)-ROW(MTIB!$Q$3)+1), ROWS(A$2:A2))),"")} -> MTIB | J2: {=IFERROR(INDEX(MTIB!$B$3:$B$1000, SMALL( IF((MTIB!$Q$3:$Q$1000<>"")*(MTIB!$Q$3:$Q$1000<>"Not Due"), ROW(MTIB!$Q$3:$Q$1000)-ROW(MTIB!$Q$3)+1), ROWS(A$2:A2))),"")} -> T/2025/00182 | K2: {=IFERROR(INDEX(MTIB!$D$3:$D$1000, SMALL( IF((MTIB!$Q$3:$Q$1000<>"")*(MTIB!$Q$3:$Q$1000<>"Not Due"), ROW(MTIB!$Q$3:$Q$1000)-ROW(MTIB!$Q$3)+1), ROWS(A$2:A2))),"")} -> EFT | L2: {=IFERROR(INDEX(MTIB!$G$3:$G$1000, SMALL( IF((MTIB!$Q$3:$Q$1000<>"")*(MTIB!$Q$3:$Q$1000<>"Not Due"), ROW(MTIB!$Q$3:$Q$1000)-ROW(MTIB!$Q$3)+1), ROWS(A$2:A2))),"")} -> 1. Notifikasi - notis pembayaran melalui EFT tidak diterima oleh pihak pembekal, pegawai projek 2. Notis untuk tuntutan/pendahuluan juga tidak diterima oleh pagawai MTIB Pengadu: Siti Zahrah Senin | M2: {=IFERROR(INDEX(MTIB!$Q$3:$Q$1000, SMALL( IF((MTIB!$Q$3:$Q$1000<>"")*(MTIB!$Q$3:$Q$1000<>"Not Due"), ROW(MTIB!$Q$3:$Q$1000)-ROW(MTIB!$Q$3)+1), ROWS(A$2:A2)) ),"")} -> >60 Days | O2: 1 | P2: {=IFERROR(INDEX(MPOB!$E$3:$E$1000, SMALL( IF((MPOB!$Q$3:$Q$1000<>"")*(MPOB!$Q$3:$Q$1000<>"Not Due"), ROW(MPOB!$Q$3:$Q$1000)-ROW(MPOB!$Q$3)+1), ROWS(A$2:A2))),"")} -> MPOB | Q2: {=IFERROR(INDEX(MPOB!$B$3:$B$1000, SMALL( IF((MPOB!$Q$3:$Q$1000<>"")*(MPOB!$Q$3:$Q$1000<>"Not Due"), ROW(MPOB!$Q$3:$Q$1000)-ROW(MPOB!$Q$3)+1), ROWS(A$2:A2))),"")} -> T/2026/00142 | R2: {=IFERROR(INDEX(MPOB!$D$3:$D$1000, SMALL( IF((MPOB!$Q$3:$Q$1000<>"")*(MPOB!$Q$3:$Q$1000<>"Not Due"), ROW(MPOB!$Q$3:$Q$1000)-ROW(MPOB!$Q$3)+1), ROWS(A$2:A2))),"")} -> MyAsset | S2: {=IFERROR(INDEX(MPOB!$G$3:$G$1000, SMALL( IF((MPOB!$Q$3:$Q$1000<>"")*(MPOB!$Q$3:$Q$1000<>"Not Due"), ROW(MPOB!$Q$3:$Q$1000)-ROW(MPOB!$Q$3)+1), ROWS(A$2:A2))),"")} -> Nama User : Zulaikha Date : 19/1/2026 Isu :Ini berkaitan pendaftaran aset dalam modul MyAsset, PIC sebelum ni Puan Suhana tapi tak sure masih sama atau tidak 👆🏼ni senarai pendaftaran aset yang masih pending peringkat pengesahan dan kelulusan Nak mintak tolong SW semak dan luluskan secara backdoor dan provide kami nombor jurnal AM untuk kami approve Sama seperti tahun lepas, kami terpaksa mintak tolong SW untuk buat backdoor sebab dah terlalu lambat dan pertukaran pegawai aset. | T2: {=IFERROR(INDEX(MPOB!$Q$3:$Q$1000, SMALL( IF((MPOB!$Q$3:$Q$1000<>"")*(MPOB!$Q$3:$Q$1000<>"Not Due"), ROW(MPOB!$Q$3:$Q$1000)-ROW(MPOB!$Q$3)+1), ROWS(A$2:A2)) ),"")} -> >60 Days | V2: 1 | W2: {=IFERROR(INDEX(LKTN!$E$3:$E$1000, SMALL( IF((LKTN!$Q$3:$Q$1000<>"")*(LKTN!$Q$3:$Q$1000<>"Not Due"), ROW(LKTN!$Q$3:$Q$1000)-ROW(LKTN!$Q$3)+1), ROWS(A$2:A2))),"")} -> LKTN | X2: {=IFERROR(INDEX(LKTN!$B$3:$B$1000, SMALL( IF((LKTN!$Q$3:$Q$1000<>"")*(LKTN!$Q$3:$Q$1000<>"Not Due"), ROW(LKTN!$Q$3:$Q$1000)-ROW(LKTN!$Q$3)+1), ROWS(A$2:A2))),"")} -> T/2026/00293 | Y2: {=IFERROR(INDEX(LKTN!$D$3:$D$1000, SMALL( IF((LKTN!$Q$3:$Q$1000<>"")*(LKTN!$Q$3:$Q$1000<>"Not Due"), ROW(LKTN!$Q$3:$Q$1000)-ROW(LKTN!$Q$3)+1), ROWS(A$2:A2))),"")} -> MYPROCUREMENT | Z2: {=IFERROR(INDEX(LKTN!$G$3:$G$1000, SMALL( IF((LKTN!$Q$3:$Q$1000<>"")*(LKTN!$Q$3:$Q$1000<>"Not Due"), ROW(LKTN!$Q$3:$Q$1000)-ROW(LKTN!$Q$3)+1), ROWS(A$2:A2))),"")} -> PEMOHON TIDAK DAPAT MEMBUAT PENGESAHAN PENERIMAAN. RUJUKAN : NO. LO : LO1225/01161 NO. PENERIMAAN : PR005922 | AA2: {=IFERROR(INDEX(LKTN!$Q$3:$Q$1000, SMALL( IF((LKTN!$Q$3:$Q$1000<>"")*(LKTN!$Q$3:$Q$1000<>"Not Due"), ROW(LKTN!$Q$3:$Q$1000)-ROW(LKTN!$Q$3)+1), ROWS(A$2:A2)) ),"")} -> 31-60 Days | AC2: 1 | AD2: {=IFERROR(INDEX(LAM!$E$3:$E$1000, SMALL( IF((LAM!$Q$3:$Q$1000<>"")*(LAM!$Q$3:$Q$1000<>"Not Due"), ROW(LAM!$Q$3:$Q$1000)-ROW(LAM!$Q$3)+1), ROWS(A$2:A2))),"")} -> LAM | AE2: {=IFERROR(INDEX(LAM!$B$3:$B$1000, SMALL( IF((LAM!$Q$3:$Q$1000<>"")*(LAM!$Q$3:$Q$1000<>"Not Due"), ROW(LAM!$Q$3:$Q$1000)-ROW(LAM!$Q$3)+1), ROWS(A$2:A2))),"")} -> T/2026/00245 | AF2: {=IFERROR(INDEX(LAM!$D$3:$D$1000, SMALL( IF((LAM!$Q$3:$Q$1000<>"")*(LAM!$Q$3:$Q$1000<>"Not Due"), ROW(LAM!$Q$3:$Q$1000)-ROW(LAM!$Q$3)+1), ROWS(A$2:A2))),"")} -> MYPANJAR | AG2: {=IFERROR(INDEX(LAM!$G$3:$G$1000, SMALL( IF((LAM!$Q$3:$Q$1000<>"")*(LAM!$Q$3:$Q$1000<>"Not Due"), ROW(LAM!$Q$3:$Q$1000)-ROW(LAM!$Q$3)+1), ROWS(A$2:A2))),"")} -> KELUAR ERROR BILA KLIK BUTANG SIMPAN (PANJAR AM) - SEPERTI DI LAMPIRAN | AH2: {=IFERROR(INDEX(LAM!$Q$3:$Q$1000, SMALL( IF((LAM!$Q$3:$Q$1000<>"")*(LAM!$Q$3:$Q$1000<>"Not Due"), ROW(LAM!$Q$3:$Q$1000)-ROW(LAM!$Q$3)+1), ROWS(A$2:A2)) ),"")} -> >60 Days | AJ2: 1 | AK2: {=IFERROR(INDEX(ISN!$E$3:$E$1000, SMALL( IF((ISN!$Q$3:$Q$1000<>"")*(ISN!$Q$3:$Q$1000<>"Not Due"), ROW(ISN!$Q$3:$Q$1000)-ROW(ISN!$Q$3)+1), ROWS(A$2:A2))),"")} -> ISN | AL2: {=IFERROR(INDEX(ISN!$B$3:$B$1000, SMALL( IF((ISN!$Q$3:$Q$1000<>"")*(ISN!$Q$3:$Q$1000<>"Not Due"), ROW(ISN!$Q$3:$Q$1000)-ROW(ISN!$Q$3)+1), ROWS(A$2:A2))),"")} -> T/2026/00021 | AM2: {=IFERROR(INDEX(ISN!$D$3:$D$1000, SMALL( IF((ISN!$Q$3:$Q$1000<>"")*(ISN!$Q$3:$Q$1000<>"Not Due"), ROW(ISN!$Q$3:$Q$1000)-ROW(ISN!$Q$3)+1), ROWS(A$2:A2))),"")} -> MYFINANCIAL CLIENT | AN2: {=IFERROR(INDEX(ISN!$G$3:$G$1000, SMALL( IF((ISN!$Q$3:$Q$1000<>"")*(ISN!$Q$3:$Q$1000<>"Not Due"), ROW(ISN!$Q$3:$Q$1000)-ROW(ISN!$Q$3)+1), ROWS(A$2:A2))),"")} -> Nama Penerima / Syarikat tak appear dalam Laporan Butiran Lejar Am | AO2: {=IFERROR(INDEX(ISN!$Q$3:$Q$1000, SMALL( IF((ISN!$Q$3:$Q$1000<>"")*(ISN!$Q$3:$Q$1000<>"Not Due"), ROW(ISN!$Q$3:$Q$1000)-ROW(ISN!$Q$3)+1), ROWS(A$2:A2)) ),"")} -> >60 Days | AQ2: 1 | AR2: {=IFERROR(INDEX(MSN!$E$3:$E$1000, SMALL( IF((MSN!$Q$3:$Q$1000<>"")*(MSN!$Q$3:$Q$1000<>"Not Due"), ROW(MSN!$Q$3:$Q$1000)-ROW(MSN!$Q$3)+1), ROWS(A$2:A2))),"")} -> MSN | AS2: {=IFERROR(INDEX(MSN!$B$3:$B$1000, SMALL( IF((MSN!$Q$3:$Q$1000<>"")*(MSN!$Q$3:$Q$1000<>"Not Due"), ROW(MSN!$Q$3:$Q$1000)-ROW(MSN!$Q$3)+1), ROWS(A$2:A2))),"")} -> T/2025/00149 | AT2: {=IFERROR(INDEX(MSN!$D$3:$D$1000, SMALL( IF((MSN!$Q$3:$Q$1000<>"")*(MSN!$Q$3:$Q$1000<>"Not Due"), ROW(MSN!$Q$3:$Q$1000)-ROW(MSN!$Q$3)+1), ROWS(A$2:A2))),"")} -> MYSTOR | AU2: {=IFERROR(INDEX(MSN!$G$3:$G$1000, SMALL( IF((MSN!$Q$3:$Q$1000<>"")*(MSN!$Q$3:$Q$1000<>"Not Due"), ROW(MSN!$Q$3:$Q$1000)-ROW(MSN!$Q$3)+1), ROWS(A$2:A2))),"")} -> Mohon untuk membuat beberapa perubahan di dalam sistem stor. A) Borang Permohonan Stok:- 1. Untuk mengemaskini senarai nama kakitangan Majlis dan Bahagian termasuk list venue-venue sukan MSN 2. Untuk buat drop down list sahaja bagi semua ruang kerana Majlis selalu membuat pertukaran tempat bertugas dan terdapat kenaikan pangkat. 3. Tambah ruang catatan dalam permohonan keluaran stok seperti di dalam Borang Kew p.s 8. Pastikan semasa kew p.s8 dijana, keterangan dalam ruang Catatan turut dicetak. 4. Tambah ruang unit dalam butiran permohonan keluaran stok. | AV2: {=IFERROR(INDEX(MSN!$Q$3:$Q$1000, SMALL( IF((MSN!$Q$3:$Q$1000<>"")*(MSN!$Q$3:$Q$1000<>"Not Due"), ROW(MSN!$Q$3:$Q$1000)-ROW(MSN!$Q$3)+1), ROWS(A$2:A2)) ),"")} -> >60 Days
A3: 2 | B3: {=IFERROR(INDEX(FRIM!$E$3:$E$1000, SMALL(IF(FRIM!$Q$3:$Q$1000<>"", ROW(FRIM!$Q$3:$Q$1000)-ROW(FRIM!$Q$3)+1), ROWS(A$2:A3))),"")} -> FRIM | C3: {=IFERROR(INDEX(FRIM!$B$3:$B$1000, SMALL(IF(FRIM!$Q$3:$Q$1000<>"", ROW(FRIM!$Q$3:$Q$1000)-ROW(FRIM!$Q$3)+1), ROWS(A$2:A3))),"")} -> T/2026/00061 | D3: {=IFERROR(INDEX(FRIM!$D$3:$D$1000, SMALL(IF(FRIM!$Q$3:$Q$1000<>"", ROW(FRIM!$Q$3:$Q$1000)-ROW(FRIM!$Q$3)+1), ROWS(A$2:A3))),"")} -> MYPROCUREMENT | E3: {=IFERROR(INDEX(FRIM!$G$3:$G$1000, SMALL(IF(FRIM!$Q$3:$Q$1000<>"", ROW(FRIM!$Q$3:$Q$1000)-ROW(FRIM!$Q$3)+1), ROWS(A$2:A3))),"")} -> No Aduan: W2489 Name: NUR SYAQIRAH BINTI MOHAMED FOZI Date: 13/01/2026 Desc: PEMBEKAL TIDAK BOLEH UPLOAD DOKUMEN PADA PORTAL PENDAFTARAN PEMBEKAL | F3: {=IFERROR(INDEX(FRIM!$Q$3:$Q$1000, SMALL(IF(FRIM!$Q$3:$Q$1000<>"", ROW(FRIM!$Q$3:$Q$1000)-ROW(FRIM!$Q$3)+1), ROWS(A$2:A3))),"")} -> >60 Days | H3: 2 | I3: {=IFERROR(INDEX(MTIB!$E$3:$E$1000, SMALL( IF((MTIB!$Q$3:$Q$1000<>"")*(MTIB!$Q$3:$Q$1000<>"Not Due"), ROW(MTIB!$Q$3:$Q$1000)-ROW(MTIB!$Q$3)+1), ROWS(A$2:A3))),"")} -> MTIB | J3: {=IFERROR(INDEX(MTIB!$B$3:$B$1000, SMALL( IF((MTIB!$Q$3:$Q$1000<>"")*(MTIB!$Q$3:$Q$1000<>"Not Due"), ROW(MTIB!$Q$3:$Q$1000)-ROW(MTIB!$Q$3)+1), ROWS(A$2:A3))),"")} -> T/2025/00183 | K3: {=IFERROR(INDEX(MTIB!$D$3:$D$1000, SMALL( IF((MTIB!$Q$3:$Q$1000<>"")*(MTIB!$Q$3:$Q$1000<>"Not Due"), ROW(MTIB!$Q$3:$Q$1000)-ROW(MTIB!$Q$3)+1), ROWS(A$2:A3))),"")} -> MYFINANCIAL | L3: {=IFERROR(INDEX(MTIB!$G$3:$G$1000, SMALL( IF((MTIB!$Q$3:$Q$1000<>"")*(MTIB!$Q$3:$Q$1000<>"Not Due"), ROW(MTIB!$Q$3:$Q$1000)-ROW(MTIB!$Q$3)+1), ROWS(A$2:A3))),"")} -> Tidak boleh print baucar bayaran BCOWS0725/00181 Pengadu: Mohamad Azrul Azlan | M3: {=IFERROR(INDEX(MTIB!$Q$3:$Q$1000, SMALL( IF((MTIB!$Q$3:$Q$1000<>"")*(MTIB!$Q$3:$Q$1000<>"Not Due"), ROW(MTIB!$Q$3:$Q$1000)-ROW(MTIB!$Q$3)+1), ROWS(A$2:A3)) ),"")} -> >60 Days | O3: 2 | P3: {=IFERROR(INDEX(MPOB!$E$3:$E$1000, SMALL( IF((MPOB!$Q$3:$Q$1000<>"")*(MPOB!$Q$3:$Q$1000<>"Not Due"), ROW(MPOB!$Q$3:$Q$1000)-ROW(MPOB!$Q$3)+1), ROWS(A$2:A3))),"")} -> MPOB | Q3: {=IFERROR(INDEX(MPOB!$B$3:$B$1000, SMALL( IF((MPOB!$Q$3:$Q$1000<>"")*(MPOB!$Q$3:$Q$1000<>"Not Due"), ROW(MPOB!$Q$3:$Q$1000)-ROW(MPOB!$Q$3)+1), ROWS(A$2:A3))),"")} -> T/2026/00144 | R3: {=IFERROR(INDEX(MPOB!$D$3:$D$1000, SMALL( IF((MPOB!$Q$3:$Q$1000<>"")*(MPOB!$Q$3:$Q$1000<>"Not Due"), ROW(MPOB!$Q$3:$Q$1000)-ROW(MPOB!$Q$3)+1), ROWS(A$2:A3))),"")} -> MyDeposit | S3: {=IFERROR(INDEX(MPOB!$G$3:$G$1000, SMALL( IF((MPOB!$Q$3:$Q$1000<>"")*(MPOB!$Q$3:$Q$1000<>"Not Due"), ROW(MPOB!$Q$3:$Q$1000)-ROW(MPOB!$Q$3)+1), ROWS(A$2:A3))),"")} -> Nama User : Norfauzan Date : 20/1/2026 Isu : boleh tgkkn refund nie ...tk boleh Tarik Dekat baucar..dulu dekat baucar hjg tu ade button integrasi utk refund Tk, dulu dekat baucar...lepas sistem upgrde..trs hilang...sebab sy kena integrasi utk baucar msk ke mylesen | T3: {=IFERROR(INDEX(MPOB!$Q$3:$Q$1000, SMALL( IF((MPOB!$Q$3:$Q$1000<>"")*(MPOB!$Q$3:$Q$1000<>"Not Due"), ROW(MPOB!$Q$3:$Q$1000)-ROW(MPOB!$Q$3)+1), ROWS(A$2:A3)) ),"")} -> >60 Days | V3: 2 | W3: {=IFERROR(INDEX(LKTN!$E$3:$E$1000, SMALL( IF((LKTN!$Q$3:$Q$1000<>"")*(LKTN!$Q$3:$Q$1000<>"Not Due"), ROW(LKTN!$Q$3:$Q$1000)-ROW(LKTN!$Q$3)+1), ROWS(A$2:A3))),"")} -> LKTN | X3: {=IFERROR(INDEX(LKTN!$B$3:$B$1000, SMALL( IF((LKTN!$Q$3:$Q$1000<>"")*(LKTN!$Q$3:$Q$1000<>"Not Due"), ROW(LKTN!$Q$3:$Q$1000)-ROW(LKTN!$Q$3)+1), ROWS(A$2:A3))),"")} -> T/2026/00304 | Y3: {=IFERROR(INDEX(LKTN!$D$3:$D$1000, SMALL( IF((LKTN!$Q$3:$Q$1000<>"")*(LKTN!$Q$3:$Q$1000<>"Not Due"), ROW(LKTN!$Q$3:$Q$1000)-ROW(LKTN!$Q$3)+1), ROWS(A$2:A3))),"")} -> MYFINANCIAL | Z3: {=IFERROR(INDEX(LKTN!$G$3:$G$1000, SMALL( IF((LKTN!$Q$3:$Q$1000<>"")*(LKTN!$Q$3:$Q$1000<>"Not Due"), ROW(LKTN!$Q$3:$Q$1000)-ROW(LKTN!$Q$3)+1), ROWS(A$2:A3))),"")} -> JURNAL NO RUJUKAN : JE25/00143 TELAH BERSTATUS POS TIDAK DAPAT DIBATALKAN KERANA KELUAR ERROR SEPERTI DI LAMPIRAN. | AA3: {=IFERROR(INDEX(LKTN!$Q$3:$Q$1000, SMALL( IF((LKTN!$Q$3:$Q$1000<>"")*(LKTN!$Q$3:$Q$1000<>"Not Due"), ROW(LKTN!$Q$3:$Q$1000)-ROW(LKTN!$Q$3)+1), ROWS(A$2:A3)) ),"")} -> 31-60 Days | AC3: 2 | AD3: {=IFERROR(INDEX(LAM!$E$3:$E$1000, SMALL( IF((LAM!$Q$3:$Q$1000<>"")*(LAM!$Q$3:$Q$1000<>"Not Due"), ROW(LAM!$Q$3:$Q$1000)-ROW(LAM!$Q$3)+1), ROWS(A$2:A3))),"")} -> LAM | AE3: {=IFERROR(INDEX(LAM!$B$3:$B$1000, SMALL( IF((LAM!$Q$3:$Q$1000<>"")*(LAM!$Q$3:$Q$1000<>"Not Due"), ROW(LAM!$Q$3:$Q$1000)-ROW(LAM!$Q$3)+1), ROWS(A$2:A3))),"")} -> T/2026/00267 | AF3: {=IFERROR(INDEX(LAM!$D$3:$D$1000, SMALL( IF((LAM!$Q$3:$Q$1000<>"")*(LAM!$Q$3:$Q$1000<>"Not Due"), ROW(LAM!$Q$3:$Q$1000)-ROW(LAM!$Q$3)+1), ROWS(A$2:A3))),"")} -> MYPANJAR | AG3: {=IFERROR(INDEX(LAM!$G$3:$G$1000, SMALL( IF((LAM!$Q$3:$Q$1000<>"")*(LAM!$Q$3:$Q$1000<>"Not Due"), ROW(LAM!$Q$3:$Q$1000)-ROW(LAM!$Q$3)+1), ROWS(A$2:A3))),"")} -> KELUAR 'INTERNAL SERVER ERROR' APABILA BUAT PEMBATALAN TUNTUTAN DI MYPANJAR | AH3: {=IFERROR(INDEX(LAM!$Q$3:$Q$1000, SMALL( IF((LAM!$Q$3:$Q$1000<>"")*(LAM!$Q$3:$Q$1000<>"Not Due"), ROW(LAM!$Q$3:$Q$1000)-ROW(LAM!$Q$3)+1), ROWS(A$2:A3)) ),"")} -> 31-60 Days | AJ3: 2 | AK3: {=IFERROR(INDEX(ISN!$E$3:$E$1000, SMALL( IF((ISN!$Q$3:$Q$1000<>"")*(ISN!$Q$3:$Q$1000<>"Not Due"), ROW(ISN!$Q$3:$Q$1000)-ROW(ISN!$Q$3)+1), ROWS(A$2:A3))),"")} -> ISN | AL3: {=IFERROR(INDEX(ISN!$B$3:$B$1000, SMALL( IF((ISN!$Q$3:$Q$1000<>"")*(ISN!$Q$3:$Q$1000<>"Not Due"), ROW(ISN!$Q$3:$Q$1000)-ROW(ISN!$Q$3)+1), ROWS(A$2:A3))),"")} -> T/2026/00260 | AM3: {=IFERROR(INDEX(ISN!$D$3:$D$1000, SMALL( IF((ISN!$Q$3:$Q$1000<>"")*(ISN!$Q$3:$Q$1000<>"Not Due"), ROW(ISN!$Q$3:$Q$1000)-ROW(ISN!$Q$3)+1), ROWS(A$2:A3))),"")} -> MYSTOR | AN3: {=IFERROR(INDEX(ISN!$G$3:$G$1000, SMALL( IF((ISN!$Q$3:$Q$1000<>"")*(ISN!$Q$3:$Q$1000<>"Not Due"), ROW(ISN!$Q$3:$Q$1000)-ROW(ISN!$Q$3)+1), ROWS(A$2:A3))),"")} -> Jumlah nilai laporan pengeluaran stok stor farmasi (oktober-disember 2025) tidak selaras dengan Laporan Kedudukan Stok Suku Tahun Keempat 2025 (pada column Pengeluaran Suku Tahun Keempat 2025) | AO3: {=IFERROR(INDEX(ISN!$Q$3:$Q$1000, SMALL( IF((ISN!$Q$3:$Q$1000<>"")*(ISN!$Q$3:$Q$1000<>"Not Due"), ROW(ISN!$Q$3:$Q$1000)-ROW(ISN!$Q$3)+1), ROWS(A$2:A3)) ),"")} -> >60 Days | AQ3: 2 | AR3: {=IFERROR(INDEX(MSN!$E$3:$E$1000, SMALL( IF((MSN!$Q$3:$Q$1000<>"")*(MSN!$Q$3:$Q$1000<>"Not Due"), ROW(MSN!$Q$3:$Q$1000)-ROW(MSN!$Q$3)+1), ROWS(A$2:A3))),"")} -> MSN | AS3: {=IFERROR(INDEX(MSN!$B$3:$B$1000, SMALL( IF((MSN!$Q$3:$Q$1000<>"")*(MSN!$Q$3:$Q$1000<>"Not Due"), ROW(MSN!$Q$3:$Q$1000)-ROW(MSN!$Q$3)+1), ROWS(A$2:A3))),"")} -> T/2025/00194 | AT3: {=IFERROR(INDEX(MSN!$D$3:$D$1000, SMALL( IF((MSN!$Q$3:$Q$1000<>"")*(MSN!$Q$3:$Q$1000<>"Not Due"), ROW(MSN!$Q$3:$Q$1000)-ROW(MSN!$Q$3)+1), ROWS(A$2:A3))),"")} -> MYSTOR | AU3: {=IFERROR(INDEX(MSN!$G$3:$G$1000, SMALL( IF((MSN!$Q$3:$Q$1000<>"")*(MSN!$Q$3:$Q$1000<>"Not Due"), ROW(MSN!$Q$3:$Q$1000)-ROW(MSN!$Q$3)+1), ROWS(A$2:A3))),"")} -> 1. Status Aktif / Aktif - access pegawai stor sahaja. 2. Perubahan unit ukuran boleh diubah sehingga 31.12.2025. 3. Tambah kolum JUMLAH di setiap terimaan stok. 4. Laporan JKPAK - Selepas stok diserahkan ke Stor Unit, ianya tidak akan diambil kira dalam laporan JKPAK. 5. Laporan JKPAK - boleh dipaparkan mengikut stor dan mengikut tahun dengan menggabungkan Stor Utama, Stor Kafe dan Stor Peralatan Sukan. | AV3: {=IFERROR(INDEX(MSN!$Q$3:$Q$1000, SMALL( IF((MSN!$Q$3:$Q$1000<>"")*(MSN!$Q$3:$Q$1000<>"Not Due"), ROW(MSN!$Q$3:$Q$1000)-ROW(MSN!$Q$3)+1), ROWS(A$2:A3)) ),"")} -> >60 Days
A4: 3 | B4: {=IFERROR(INDEX(FRIM!$E$3:$E$1000, SMALL(IF(FRIM!$Q$3:$Q$1000<>"", ROW(FRIM!$Q$3:$Q$1000)-ROW(FRIM!$Q$3)+1), ROWS(A$2:A4))),"")} -> FRIM | C4: {=IFERROR(INDEX(FRIM!$B$3:$B$1000, SMALL(IF(FRIM!$Q$3:$Q$1000<>"", ROW(FRIM!$Q$3:$Q$1000)-ROW(FRIM!$Q$3)+1), ROWS(A$2:A4))),"")} -> T/2026/00075 | D4: {=IFERROR(INDEX(FRIM!$D$3:$D$1000, SMALL(IF(FRIM!$Q$3:$Q$1000<>"", ROW(FRIM!$Q$3:$Q$1000)-ROW(FRIM!$Q$3)+1), ROWS(A$2:A4))),"")} -> MYPROCUREMENT | E4: {=IFERROR(INDEX(FRIM!$G$3:$G$1000, SMALL(IF(FRIM!$Q$3:$Q$1000<>"", ROW(FRIM!$Q$3:$Q$1000)-ROW(FRIM!$Q$3)+1), ROWS(A$2:A4))),"")} -> No Aduan: W2508 Name: AZMEI B. MARZUKI Date: 05/02/2026 Desc: ASSALAM, SAYA TELAH BERI ID & PWORD KEPADA SYKT LECO INSTRUMENT (M) SDN BHD. SELEPAS LOGIN, BUTANG UPLOAD TIDAK ADA DALAM SCREEN MAKLUMAT DOKUMEN. SO PIHAK SYARIKAT TIDAK BOLEH UPLOAD SIJIL2 SYARIKAT. TQ | F4: {=IFERROR(INDEX(FRIM!$Q$3:$Q$1000, SMALL(IF(FRIM!$Q$3:$Q$1000<>"", ROW(FRIM!$Q$3:$Q$1000)-ROW(FRIM!$Q$3)+1), ROWS(A$2:A4))),"")} -> >60 Days | H4: 3 | I4: {=IFERROR(INDEX(MTIB!$E$3:$E$1000, SMALL( IF((MTIB!$Q$3:$Q$1000<>"")*(MTIB!$Q$3:$Q$1000<>"Not Due"), ROW(MTIB!$Q$3:$Q$1000)-ROW(MTIB!$Q$3)+1), ROWS(A$2:A4))),"")} -> MTIB | J4: {=IFERROR(INDEX(MTIB!$B$3:$B$1000, SMALL( IF((MTIB!$Q$3:$Q$1000<>"")*(MTIB!$Q$3:$Q$1000<>"Not Due"), ROW(MTIB!$Q$3:$Q$1000)-ROW(MTIB!$Q$3)+1), ROWS(A$2:A4))),"")} -> T/2025/00193 | K4: {=IFERROR(INDEX(MTIB!$D$3:$D$1000, SMALL( IF((MTIB!$Q$3:$Q$1000<>"")*(MTIB!$Q$3:$Q$1000<>"Not Due"), ROW(MTIB!$Q$3:$Q$1000)-ROW(MTIB!$Q$3)+1), ROWS(A$2:A4))),"")} -> MYFINANCIAL | L4: {=IFERROR(INDEX(MTIB!$G$3:$G$1000, SMALL( IF((MTIB!$Q$3:$Q$1000<>"")*(MTIB!$Q$3:$Q$1000<>"Not Due"), ROW(MTIB!$Q$3:$Q$1000)-ROW(MTIB!$Q$3)+1), ROWS(A$2:A4))),"")} -> Tidak dapat 'simpan' untuk kedua-dua MyFinancial web dan client (lampiran) Pengadu: Nor Hafizah Yusoff | M4: {=IFERROR(INDEX(MTIB!$Q$3:$Q$1000, SMALL( IF((MTIB!$Q$3:$Q$1000<>"")*(MTIB!$Q$3:$Q$1000<>"Not Due"), ROW(MTIB!$Q$3:$Q$1000)-ROW(MTIB!$Q$3)+1), ROWS(A$2:A4)) ),"")} -> >60 Days | O4: 3 | P4: {=IFERROR(INDEX(MPOB!$E$3:$E$1000, SMALL( IF((MPOB!$Q$3:$Q$1000<>"")*(MPOB!$Q$3:$Q$1000<>"Not Due"), ROW(MPOB!$Q$3:$Q$1000)-ROW(MPOB!$Q$3)+1), ROWS(A$2:A4))),"")} -> MPOB | Q4: {=IFERROR(INDEX(MPOB!$B$3:$B$1000, SMALL( IF((MPOB!$Q$3:$Q$1000<>"")*(MPOB!$Q$3:$Q$1000<>"Not Due"), ROW(MPOB!$Q$3:$Q$1000)-ROW(MPOB!$Q$3)+1), ROWS(A$2:A4))),"")} -> T/2026/00145 | R4: {=IFERROR(INDEX(MPOB!$D$3:$D$1000, SMALL( IF((MPOB!$Q$3:$Q$1000<>"")*(MPOB!$Q$3:$Q$1000<>"Not Due"), ROW(MPOB!$Q$3:$Q$1000)-ROW(MPOB!$Q$3)+1), ROWS(A$2:A4))),"")} -> MyFinancial | S4: {=IFERROR(INDEX(MPOB!$G$3:$G$1000, SMALL( IF((MPOB!$Q$3:$Q$1000<>"")*(MPOB!$Q$3:$Q$1000<>"Not Due"), ROW(MPOB!$Q$3:$Q$1000)-ROW(MPOB!$Q$3)+1), ROWS(A$2:A4))),"")} -> Nama User : Tyra Date : 20/1/2026 Isu : sy xleh nk cetak resit ini | T4: {=IFERROR(INDEX(MPOB!$Q$3:$Q$1000, SMALL( IF((MPOB!$Q$3:$Q$1000<>"")*(MPOB!$Q$3:$Q$1000<>"Not Due"), ROW(MPOB!$Q$3:$Q$1000)-ROW(MPOB!$Q$3)+1), ROWS(A$2:A4)) ),"")} -> >60 Days | V4: 3 | W4: {=IFERROR(INDEX(LKTN!$E$3:$E$1000, SMALL( IF((LKTN!$Q$3:$Q$1000<>"")*(LKTN!$Q$3:$Q$1000<>"Not Due"), ROW(LKTN!$Q$3:$Q$1000)-ROW(LKTN!$Q$3)+1), ROWS(A$2:A4))),"")} -> LKTN | X4: {=IFERROR(INDEX(LKTN!$B$3:$B$1000, SMALL( IF((LKTN!$Q$3:$Q$1000<>"")*(LKTN!$Q$3:$Q$1000<>"Not Due"), ROW(LKTN!$Q$3:$Q$1000)-ROW(LKTN!$Q$3)+1), ROWS(A$2:A4))),"")} -> T/2026/00419 | Y4: {=IFERROR(INDEX(LKTN!$D$3:$D$1000, SMALL( IF((LKTN!$Q$3:$Q$1000<>"")*(LKTN!$Q$3:$Q$1000<>"Not Due"), ROW(LKTN!$Q$3:$Q$1000)-ROW(LKTN!$Q$3)+1), ROWS(A$2:A4))),"")} -> MYFINANCIAL | Z4: {=IFERROR(INDEX(LKTN!$G$3:$G$1000, SMALL( IF((LKTN!$Q$3:$Q$1000<>"")*(LKTN!$Q$3:$Q$1000<>"Not Due"), ROW(LKTN!$Q$3:$Q$1000)-ROW(LKTN!$Q$3)+1), ROWS(A$2:A4))),"")} -> TERDAPAT PERBEZAAN AMAUN TUNAI (A11101) PADA LEJAR AM DAN KUNCI KIRA-KIRA SEPERTI BERIKUT : PERBEZAAN AMAUN TUNAI (A11101) DI LEJAR AM DAN KUNCI KIRA-KIRA ADALAH SEBANYAK RM46,279.84. MINTA SEMAK DAN PERBETULKAN AMAUN YANG SEBENAR. | AA4: {=IFERROR(INDEX(LKTN!$Q$3:$Q$1000, SMALL( IF((LKTN!$Q$3:$Q$1000<>"")*(LKTN!$Q$3:$Q$1000<>"Not Due"), ROW(LKTN!$Q$3:$Q$1000)-ROW(LKTN!$Q$3)+1), ROWS(A$2:A4)) ),"")} -> 1-30 Days | AC4: 3 | AD4: {=IFERROR(INDEX(LAM!$E$3:$E$1000, SMALL( IF((LAM!$Q$3:$Q$1000<>"")*(LAM!$Q$3:$Q$1000<>"Not Due"), ROW(LAM!$Q$3:$Q$1000)-ROW(LAM!$Q$3)+1), ROWS(A$2:A4))),"")} -> LAM | AE4: {=IFERROR(INDEX(LAM!$B$3:$B$1000, SMALL( IF((LAM!$Q$3:$Q$1000<>"")*(LAM!$Q$3:$Q$1000<>"Not Due"), ROW(LAM!$Q$3:$Q$1000)-ROW(LAM!$Q$3)+1), ROWS(A$2:A4))),"")} -> T/2026/00270 | AF4: {=IFERROR(INDEX(LAM!$D$3:$D$1000, SMALL( IF((LAM!$Q$3:$Q$1000<>"")*(LAM!$Q$3:$Q$1000<>"Not Due"), ROW(LAM!$Q$3:$Q$1000)-ROW(LAM!$Q$3)+1), ROWS(A$2:A4))),"")} -> MYFINANCIAL | AG4: {=IFERROR(INDEX(LAM!$G$3:$G$1000, SMALL( IF((LAM!$Q$3:$Q$1000<>"")*(LAM!$Q$3:$Q$1000<>"Not Due"), ROW(LAM!$Q$3:$Q$1000)-ROW(LAM!$Q$3)+1), ROWS(A$2:A4))),"")} -> TUKAR NAMA 'PENERIMA' DI BAUCAR MYFINANCIAL SEMASA INTEGRASI DARI MYPANJAR, DARI NAMA AZURA BINTI GHAZALI KE FARAH IZWAH BINTI ALI | AH4: {=IFERROR(INDEX(LAM!$Q$3:$Q$1000, SMALL( IF((LAM!$Q$3:$Q$1000<>"")*(LAM!$Q$3:$Q$1000<>"Not Due"), ROW(LAM!$Q$3:$Q$1000)-ROW(LAM!$Q$3)+1), ROWS(A$2:A4)) ),"")} -> 31-60 Days | AJ4: 3 | AK4: {=IFERROR(INDEX(ISN!$E$3:$E$1000, SMALL( IF((ISN!$Q$3:$Q$1000<>"")*(ISN!$Q$3:$Q$1000<>"Not Due"), ROW(ISN!$Q$3:$Q$1000)-ROW(ISN!$Q$3)+1), ROWS(A$2:A4))),"")} -> ISN | AL4: {=IFERROR(INDEX(ISN!$B$3:$B$1000, SMALL( IF((ISN!$Q$3:$Q$1000<>"")*(ISN!$Q$3:$Q$1000<>"Not Due"), ROW(ISN!$Q$3:$Q$1000)-ROW(ISN!$Q$3)+1), ROWS(A$2:A4))),"")} -> T/2026/00325 | AM4: {=IFERROR(INDEX(ISN!$D$3:$D$1000, SMALL( IF((ISN!$Q$3:$Q$1000<>"")*(ISN!$Q$3:$Q$1000<>"Not Due"), ROW(ISN!$Q$3:$Q$1000)-ROW(ISN!$Q$3)+1), ROWS(A$2:A4))),"")} -> MYFINANCIAL CLIENT | AN4: {=IFERROR(INDEX(ISN!$G$3:$G$1000, SMALL( IF((ISN!$Q$3:$Q$1000<>"")*(ISN!$Q$3:$Q$1000<>"Not Due"), ROW(ISN!$Q$3:$Q$1000)-ROW(ISN!$Q$3)+1), ROWS(A$2:A4))),"")} -> Mohon tambah row bagi keterangan dalam cetakan baucar. tq | AO4: {=IFERROR(INDEX(ISN!$Q$3:$Q$1000, SMALL( IF((ISN!$Q$3:$Q$1000<>"")*(ISN!$Q$3:$Q$1000<>"Not Due"), ROW(ISN!$Q$3:$Q$1000)-ROW(ISN!$Q$3)+1), ROWS(A$2:A4)) ),"")} -> 31-60 Days | AQ4: 3 | AR4: {=IFERROR(INDEX(MSN!$E$3:$E$1000, SMALL( IF((MSN!$Q$3:$Q$1000<>"")*(MSN!$Q$3:$Q$1000<>"Not Due"), ROW(MSN!$Q$3:$Q$1000)-ROW(MSN!$Q$3)+1), ROWS(A$2:A4))),"")} -> MSN | AS4: {=IFERROR(INDEX(MSN!$B$3:$B$1000, SMALL( IF((MSN!$Q$3:$Q$1000<>"")*(MSN!$Q$3:$Q$1000<>"Not Due"), ROW(MSN!$Q$3:$Q$1000)-ROW(MSN!$Q$3)+1), ROWS(A$2:A4))),"")} -> T/2026/00238 | AT4: {=IFERROR(INDEX(MSN!$D$3:$D$1000, SMALL( IF((MSN!$Q$3:$Q$1000<>"")*(MSN!$Q$3:$Q$1000<>"Not Due"), ROW(MSN!$Q$3:$Q$1000)-ROW(MSN!$Q$3)+1), ROWS(A$2:A4))),"")} -> ATK | AU4: {=IFERROR(INDEX(MSN!$G$3:$G$1000, SMALL( IF((MSN!$Q$3:$Q$1000<>"")*(MSN!$Q$3:$Q$1000<>"Not Due"), ROW(MSN!$Q$3:$Q$1000)-ROW(MSN!$Q$3)+1), ROWS(A$2:A4))),"")} -> 1. Urus setia telah memeriksa rekod pengeluaran sehingga rekod awal. Terdapat stok yang tiada penerimaan (pertambahan baki) tapi pengeluaran melebihi baki menyebabkan rekod stok menjadi negatif. 2. Pengeluaran dibuat, tiada penolakan baki tetapi ada rekod pengeluaran. 3. Rekod pengeluaran tidak dibuat mengikut pekeliling iaitu 'Masuk Dahulu, Keluar Dahulu' kerana urus setia dapati terdapat 2 rekod bagi suatu 1 item dengan harga yang berlainan dan setiap harga mempunyai baki. Contoh : Sampul surat saiz 6x9 09/05/2023 = 20 kotak x rm 158.80 16/07/2025 = 2 kotak x rm 78.00 | AV4: {=IFERROR(INDEX(MSN!$Q$3:$Q$1000, SMALL( IF((MSN!$Q$3:$Q$1000<>"")*(MSN!$Q$3:$Q$1000<>"Not Due"), ROW(MSN!$Q$3:$Q$1000)-ROW(MSN!$Q$3)+1), ROWS(A$2:A4)) ),"")} -> >60 Days
A5: 4 | B5: {=IFERROR(INDEX(FRIM!$E$3:$E$1000, SMALL(IF(FRIM!$Q$3:$Q$1000<>"", ROW(FRIM!$Q$3:$Q$1000)-ROW(FRIM!$Q$3)+1), ROWS(A$2:A5))),"")} -> FRIM | C5: {=IFERROR(INDEX(FRIM!$B$3:$B$1000, SMALL(IF(FRIM!$Q$3:$Q$1000<>"", ROW(FRIM!$Q$3:$Q$1000)-ROW(FRIM!$Q$3)+1), ROWS(A$2:A5))),"")} -> T/2026/00076 | D5: {=IFERROR(INDEX(FRIM!$D$3:$D$1000, SMALL(IF(FRIM!$Q$3:$Q$1000<>"", ROW(FRIM!$Q$3:$Q$1000)-ROW(FRIM!$Q$3)+1), ROWS(A$2:A5))),"")} -> MYFINANCIAL CLIENT | E5: {=IFERROR(INDEX(FRIM!$G$3:$G$1000, SMALL(IF(FRIM!$Q$3:$Q$1000<>"", ROW(FRIM!$Q$3:$Q$1000)-ROW(FRIM!$Q$3)+1), ROWS(A$2:A5))),"")} -> No Aduan: W2509 Name: HASRINA HASNOR BT. KAMARUZAMAN Date: 06/02/2026 Desc: CETAKAN RESIT & LAPORAN 7260182 - SETTING LARI | F5: {=IFERROR(INDEX(FRIM!$Q$3:$Q$1000, SMALL(IF(FRIM!$Q$3:$Q$1000<>"", ROW(FRIM!$Q$3:$Q$1000)-ROW(FRIM!$Q$3)+1), ROWS(A$2:A5))),"")} -> >60 Days | H5: 4 | I5: {=IFERROR(INDEX(MTIB!$E$3:$E$1000, SMALL( IF((MTIB!$Q$3:$Q$1000<>"")*(MTIB!$Q$3:$Q$1000<>"Not Due"), ROW(MTIB!$Q$3:$Q$1000)-ROW(MTIB!$Q$3)+1), ROWS(A$2:A5))),"")} -> MTIB | J5: {=IFERROR(INDEX(MTIB!$B$3:$B$1000, SMALL( IF((MTIB!$Q$3:$Q$1000<>"")*(MTIB!$Q$3:$Q$1000<>"Not Due"), ROW(MTIB!$Q$3:$Q$1000)-ROW(MTIB!$Q$3)+1), ROWS(A$2:A5))),"")} -> T/2025/00198 | K5: {=IFERROR(INDEX(MTIB!$D$3:$D$1000, SMALL( IF((MTIB!$Q$3:$Q$1000<>"")*(MTIB!$Q$3:$Q$1000<>"Not Due"), ROW(MTIB!$Q$3:$Q$1000)-ROW(MTIB!$Q$3)+1), ROWS(A$2:A5))),"")} -> MYLOAN | L5: {=IFERROR(INDEX(MTIB!$G$3:$G$1000, SMALL( IF((MTIB!$Q$3:$Q$1000<>"")*(MTIB!$Q$3:$Q$1000<>"Not Due"), ROW(MTIB!$Q$3:$Q$1000)-ROW(MTIB!$Q$3)+1), ROWS(A$2:A5))),"")} -> Tiada fungsi hapus atau roles dibenarkan kepada Nor Atikah (PSM) untuk hapus permohonan/rekod Nurul Iman seperti di lampiran kerana pemohon tak jadi mohon pinjaman. | M5: {=IFERROR(INDEX(MTIB!$Q$3:$Q$1000, SMALL( IF((MTIB!$Q$3:$Q$1000<>"")*(MTIB!$Q$3:$Q$1000<>"Not Due"), ROW(MTIB!$Q$3:$Q$1000)-ROW(MTIB!$Q$3)+1), ROWS(A$2:A5)) ),"")} -> >60 Days | O5: 4 | P5: {=IFERROR(INDEX(MPOB!$E$3:$E$1000, SMALL( IF((MPOB!$Q$3:$Q$1000<>"")*(MPOB!$Q$3:$Q$1000<>"Not Due"), ROW(MPOB!$Q$3:$Q$1000)-ROW(MPOB!$Q$3)+1), ROWS(A$2:A5))),"")} -> MPOB | Q5: {=IFERROR(INDEX(MPOB!$B$3:$B$1000, SMALL( IF((MPOB!$Q$3:$Q$1000<>"")*(MPOB!$Q$3:$Q$1000<>"Not Due"), ROW(MPOB!$Q$3:$Q$1000)-ROW(MPOB!$Q$3)+1), ROWS(A$2:A5))),"")} -> T/2026/00146 | R5: {=IFERROR(INDEX(MPOB!$D$3:$D$1000, SMALL( IF((MPOB!$Q$3:$Q$1000<>"")*(MPOB!$Q$3:$Q$1000<>"Not Due"), ROW(MPOB!$Q$3:$Q$1000)-ROW(MPOB!$Q$3)+1), ROWS(A$2:A5))),"")} -> Projek Kos | S5: {=IFERROR(INDEX(MPOB!$G$3:$G$1000, SMALL( IF((MPOB!$Q$3:$Q$1000<>"")*(MPOB!$Q$3:$Q$1000<>"Not Due"), ROW(MPOB!$Q$3:$Q$1000)-ROW(MPOB!$Q$3)+1), ROWS(A$2:A5))),"")} -> Nama User : Khairun nisa Date : 20/1/2026 Isu : Ada amaun negatif. | T5: {=IFERROR(INDEX(MPOB!$Q$3:$Q$1000, SMALL( IF((MPOB!$Q$3:$Q$1000<>"")*(MPOB!$Q$3:$Q$1000<>"Not Due"), ROW(MPOB!$Q$3:$Q$1000)-ROW(MPOB!$Q$3)+1), ROWS(A$2:A5)) ),"")} -> >60 Days | V5: 4 | W5: {=IFERROR(INDEX(LKTN!$E$3:$E$1000, SMALL( IF((LKTN!$Q$3:$Q$1000<>"")*(LKTN!$Q$3:$Q$1000<>"Not Due"), ROW(LKTN!$Q$3:$Q$1000)-ROW(LKTN!$Q$3)+1), ROWS(A$2:A5))),"")} -> LKTN | X5: {=IFERROR(INDEX(LKTN!$B$3:$B$1000, SMALL( IF((LKTN!$Q$3:$Q$1000<>"")*(LKTN!$Q$3:$Q$1000<>"Not Due"), ROW(LKTN!$Q$3:$Q$1000)-ROW(LKTN!$Q$3)+1), ROWS(A$2:A5))),"")} -> T/2026/00455 | Y5: {=IFERROR(INDEX(LKTN!$D$3:$D$1000, SMALL( IF((LKTN!$Q$3:$Q$1000<>"")*(LKTN!$Q$3:$Q$1000<>"Not Due"), ROW(LKTN!$Q$3:$Q$1000)-ROW(LKTN!$Q$3)+1), ROWS(A$2:A5))),"")} -> MYSTOR | Z5: {=IFERROR(INDEX(LKTN!$G$3:$G$1000, SMALL( IF((LKTN!$Q$3:$Q$1000<>"")*(LKTN!$Q$3:$Q$1000<>"Not Due"), ROW(LKTN!$Q$3:$Q$1000)-ROW(LKTN!$Q$3)+1), ROWS(A$2:A5))),"")} -> Staf Yang Tidak Dapat Membuat Permohonan Dalam Mystore 1. Muhamad Najib Bin Daud 2. Hafizi Bin Hashim 3. Muhamad Rozaidi Bin Shafie 4. Muhamad Zaini Bin Abdul Ghani 5. Ahmad Syahmi Bin Ismail Nasharuddin Berikan Akses sebagai Pegawai Stor 1. Mohd Khairi Bin Yusoff | AA5: {=IFERROR(INDEX(LKTN!$Q$3:$Q$1000, SMALL( IF((LKTN!$Q$3:$Q$1000<>"")*(LKTN!$Q$3:$Q$1000<>"Not Due"), ROW(LKTN!$Q$3:$Q$1000)-ROW(LKTN!$Q$3)+1), ROWS(A$2:A5)) ),"")} -> 1-30 Days | AC5: 4 | AD5: {=IFERROR(INDEX(LAM!$E$3:$E$1000, SMALL( IF((LAM!$Q$3:$Q$1000<>"")*(LAM!$Q$3:$Q$1000<>"Not Due"), ROW(LAM!$Q$3:$Q$1000)-ROW(LAM!$Q$3)+1), ROWS(A$2:A5))),"")} -> LAM | AE5: {=IFERROR(INDEX(LAM!$B$3:$B$1000, SMALL( IF((LAM!$Q$3:$Q$1000<>"")*(LAM!$Q$3:$Q$1000<>"Not Due"), ROW(LAM!$Q$3:$Q$1000)-ROW(LAM!$Q$3)+1), ROWS(A$2:A5))),"")} -> T/2026/00452 | AF5: {=IFERROR(INDEX(LAM!$D$3:$D$1000, SMALL( IF((LAM!$Q$3:$Q$1000<>"")*(LAM!$Q$3:$Q$1000<>"Not Due"), ROW(LAM!$Q$3:$Q$1000)-ROW(LAM!$Q$3)+1), ROWS(A$2:A5))),"")} -> MYFINANCIAL | AG5: {=IFERROR(INDEX(LAM!$G$3:$G$1000, SMALL( IF((LAM!$Q$3:$Q$1000<>"")*(LAM!$Q$3:$Q$1000<>"Not Due"), ROW(LAM!$Q$3:$Q$1000)-ROW(LAM!$Q$3)+1), ROWS(A$2:A5))),"")} -> Tiada amaun keluar di Penyata Aliran Tunai bagi tahun 2025 Laporan MPSAS --> Laporan Aliran Tunai --> 2025 | AH5: {=IFERROR(INDEX(LAM!$Q$3:$Q$1000, SMALL( IF((LAM!$Q$3:$Q$1000<>"")*(LAM!$Q$3:$Q$1000<>"Not Due"), ROW(LAM!$Q$3:$Q$1000)-ROW(LAM!$Q$3)+1), ROWS(A$2:A5)) ),"")} -> 1-30 Days | AJ5: 4 | AK5: {=IFERROR(INDEX(ISN!$E$3:$E$1000, SMALL( IF((ISN!$Q$3:$Q$1000<>"")*(ISN!$Q$3:$Q$1000<>"Not Due"), ROW(ISN!$Q$3:$Q$1000)-ROW(ISN!$Q$3)+1), ROWS(A$2:A5))),"")} -> ISN | AL5: {=IFERROR(INDEX(ISN!$B$3:$B$1000, SMALL( IF((ISN!$Q$3:$Q$1000<>"")*(ISN!$Q$3:$Q$1000<>"Not Due"), ROW(ISN!$Q$3:$Q$1000)-ROW(ISN!$Q$3)+1), ROWS(A$2:A5))),"")} -> T/2026/00370 | AM5: {=IFERROR(INDEX(ISN!$D$3:$D$1000, SMALL( IF((ISN!$Q$3:$Q$1000<>"")*(ISN!$Q$3:$Q$1000<>"Not Due"), ROW(ISN!$Q$3:$Q$1000)-ROW(ISN!$Q$3)+1), ROWS(A$2:A5))),"")} -> MYSTOR | AN5: {=IFERROR(INDEX(ISN!$G$3:$G$1000, SMALL( IF((ISN!$Q$3:$Q$1000<>"")*(ISN!$Q$3:$Q$1000<>"Not Due"), ROW(ISN!$Q$3:$Q$1000)-ROW(ISN!$Q$3)+1), ROWS(A$2:A5))),"")} -> MOHON KEMASKINI CHECK & FOUND (PEN MERAH) DI KEWPS.3 SISTEM MYSTORE DALAM STOR FARMASI UNTUK BULAN JUN 2026. | AO5: {=IFERROR(INDEX(ISN!$Q$3:$Q$1000, SMALL( IF((ISN!$Q$3:$Q$1000<>"")*(ISN!$Q$3:$Q$1000<>"Not Due"), ROW(ISN!$Q$3:$Q$1000)-ROW(ISN!$Q$3)+1), ROWS(A$2:A5)) ),"")} -> 1-30 Days | AQ5: 4 | AR5: {=IFERROR(INDEX(MSN!$E$3:$E$1000, SMALL( IF((MSN!$Q$3:$Q$1000<>"")*(MSN!$Q$3:$Q$1000<>"Not Due"), ROW(MSN!$Q$3:$Q$1000)-ROW(MSN!$Q$3)+1), ROWS(A$2:A5))),"")} | AS5: {=IFERROR(INDEX(MSN!$B$3:$B$1000, SMALL( IF((MSN!$Q$3:$Q$1000<>"")*(MSN!$Q$3:$Q$1000<>"Not Due"), ROW(MSN!$Q$3:$Q$1000)-ROW(MSN!$Q$3)+1), ROWS(A$2:A5))),"")} | AT5: {=IFERROR(INDEX(MSN!$D$3:$D$1000, SMALL( IF((MSN!$Q$3:$Q$1000<>"")*(MSN!$Q$3:$Q$1000<>"Not Due"), ROW(MSN!$Q$3:$Q$1000)-ROW(MSN!$Q$3)+1), ROWS(A$2:A5))),"")} | AU5: {=IFERROR(INDEX(MSN!$G$3:$G$1000, SMALL( IF((MSN!$Q$3:$Q$1000<>"")*(MSN!$Q$3:$Q$1000<>"Not Due"), ROW(MSN!$Q$3:$Q$1000)-ROW(MSN!$Q$3)+1), ROWS(A$2:A5))),"")} | AV5: {=IFERROR(INDEX(MSN!$Q$3:$Q$1000, SMALL( IF((MSN!$Q$3:$Q$1000<>"")*(MSN!$Q$3:$Q$1000<>"Not Due"), ROW(MSN!$Q$3:$Q$1000)-ROW(MSN!$Q$3)+1), ROWS(A$2:A5)) ),"")}
A6: 5 | B6: {=IFERROR(INDEX(FRIM!$E$3:$E$1000, SMALL(IF(FRIM!$Q$3:$Q$1000<>"", ROW(FRIM!$Q$3:$Q$1000)-ROW(FRIM!$Q$3)+1), ROWS(A$2:A6))),"")} -> FRIM | C6: {=IFERROR(INDEX(FRIM!$B$3:$B$1000, SMALL(IF(FRIM!$Q$3:$Q$1000<>"", ROW(FRIM!$Q$3:$Q$1000)-ROW(FRIM!$Q$3)+1), ROWS(A$2:A6))),"")} -> T/2026/00078 | D6: {=IFERROR(INDEX(FRIM!$D$3:$D$1000, SMALL(IF(FRIM!$Q$3:$Q$1000<>"", ROW(FRIM!$Q$3:$Q$1000)-ROW(FRIM!$Q$3)+1), ROWS(A$2:A6))),"")} -> QUERY | E6: {=IFERROR(INDEX(FRIM!$G$3:$G$1000, SMALL(IF(FRIM!$Q$3:$Q$1000<>"", ROW(FRIM!$Q$3:$Q$1000)-ROW(FRIM!$Q$3)+1), ROWS(A$2:A6))),"")} -> No Aduan: W2511 Name: NAJWA NAFIAH BINTI FAUZI Date: 12/02/2026 Desc: MOHON BANTUAN SEMAKAN BAGI PEROLEHAN SEPERTI BERIKUT KERANA BERBAKI DEFISIT : 1- AG23017 (TK ELEVATOR MALAYSIA SDN BHD) RM-11.00 2- SHB23002(4/4) (AIRCARBONIC SDN BHD) RM-188.00 3- SHB24004(3)(ALPHA GAS SOLUTION SDN. BHD.) RM- 924.00 4- SH22051 (ABROTECH ENTERPRISE) RM-8,789.40 5- SH24017 (SINAR MESRA SERVICES SDN. BHD.) RM- 30,132.00 | F6: {=IFERROR(INDEX(FRIM!$Q$3:$Q$1000, SMALL(IF(FRIM!$Q$3:$Q$1000<>"", ROW(FRIM!$Q$3:$Q$1000)-ROW(FRIM!$Q$3)+1), ROWS(A$2:A6))),"")} -> >60 Days | H6: 5 | I6: {=IFERROR(INDEX(MTIB!$E$3:$E$1000, SMALL( IF((MTIB!$Q$3:$Q$1000<>"")*(MTIB!$Q$3:$Q$1000<>"Not Due"), ROW(MTIB!$Q$3:$Q$1000)-ROW(MTIB!$Q$3)+1), ROWS(A$2:A6))),"")} -> MTIB | J6: {=IFERROR(INDEX(MTIB!$B$3:$B$1000, SMALL( IF((MTIB!$Q$3:$Q$1000<>"")*(MTIB!$Q$3:$Q$1000<>"Not Due"), ROW(MTIB!$Q$3:$Q$1000)-ROW(MTIB!$Q$3)+1), ROWS(A$2:A6))),"")} -> T/2025/00202 | K6: {=IFERROR(INDEX(MTIB!$D$3:$D$1000, SMALL( IF((MTIB!$Q$3:$Q$1000<>"")*(MTIB!$Q$3:$Q$1000<>"Not Due"), ROW(MTIB!$Q$3:$Q$1000)-ROW(MTIB!$Q$3)+1), ROWS(A$2:A6))),"")} -> MYFINANCIAL | L6: {=IFERROR(INDEX(MTIB!$G$3:$G$1000, SMALL( IF((MTIB!$Q$3:$Q$1000<>"")*(MTIB!$Q$3:$Q$1000<>"Not Due"), ROW(MTIB!$Q$3:$Q$1000)-ROW(MTIB!$Q$3)+1), ROWS(A$2:A6))),"")} -> Tidak dapat membuat cetakan terus dari sistem MyFinancial tetapi boleh melalui 'text view'. Namun butiran baucar akan terputus ke baucar seterusnya. Untuk itu setiap baucar perlu diperbetul margin sebelum membuat cetakan. Pengadu: Suhani Hassan | M6: {=IFERROR(INDEX(MTIB!$Q$3:$Q$1000, SMALL( IF((MTIB!$Q$3:$Q$1000<>"")*(MTIB!$Q$3:$Q$1000<>"Not Due"), ROW(MTIB!$Q$3:$Q$1000)-ROW(MTIB!$Q$3)+1), ROWS(A$2:A6)) ),"")} -> >60 Days | O6: 5 | P6: {=IFERROR(INDEX(MPOB!$E$3:$E$1000, SMALL( IF((MPOB!$Q$3:$Q$1000<>"")*(MPOB!$Q$3:$Q$1000<>"Not Due"), ROW(MPOB!$Q$3:$Q$1000)-ROW(MPOB!$Q$3)+1), ROWS(A$2:A6))),"")} -> MPOB | Q6: {=IFERROR(INDEX(MPOB!$B$3:$B$1000, SMALL( IF((MPOB!$Q$3:$Q$1000<>"")*(MPOB!$Q$3:$Q$1000<>"Not Due"), ROW(MPOB!$Q$3:$Q$1000)-ROW(MPOB!$Q$3)+1), ROWS(A$2:A6))),"")} -> T/2026/00147 | R6: {=IFERROR(INDEX(MPOB!$D$3:$D$1000, SMALL( IF((MPOB!$Q$3:$Q$1000<>"")*(MPOB!$Q$3:$Q$1000<>"Not Due"), ROW(MPOB!$Q$3:$Q$1000)-ROW(MPOB!$Q$3)+1), ROWS(A$2:A6))),"")} -> MyFinancial | S6: {=IFERROR(INDEX(MPOB!$G$3:$G$1000, SMALL( IF((MPOB!$Q$3:$Q$1000<>"")*(MPOB!$Q$3:$Q$1000<>"Not Due"), ROW(MPOB!$Q$3:$Q$1000)-ROW(MPOB!$Q$3)+1), ROWS(A$2:A6))),"")} -> Nama User : Dalillah Date : 20/1/2026 Isu : Sistem error message | T6: {=IFERROR(INDEX(MPOB!$Q$3:$Q$1000, SMALL( IF((MPOB!$Q$3:$Q$1000<>"")*(MPOB!$Q$3:$Q$1000<>"Not Due"), ROW(MPOB!$Q$3:$Q$1000)-ROW(MPOB!$Q$3)+1), ROWS(A$2:A6)) ),"")} -> >60 Days | V6: 5 | W6: {=IFERROR(INDEX(LKTN!$E$3:$E$1000, SMALL( IF((LKTN!$Q$3:$Q$1000<>"")*(LKTN!$Q$3:$Q$1000<>"Not Due"), ROW(LKTN!$Q$3:$Q$1000)-ROW(LKTN!$Q$3)+1), ROWS(A$2:A6))),"")} | X6: {=IFERROR(INDEX(LKTN!$B$3:$B$1000, SMALL( IF((LKTN!$Q$3:$Q$1000<>"")*(LKTN!$Q$3:$Q$1000<>"Not Due"), ROW(LKTN!$Q$3:$Q$1000)-ROW(LKTN!$Q$3)+1), ROWS(A$2:A6))),"")} | Y6: {=IFERROR(INDEX(LKTN!$D$3:$D$1000, SMALL( IF((LKTN!$Q$3:$Q$1000<>"")*(LKTN!$Q$3:$Q$1000<>"Not Due"), ROW(LKTN!$Q$3:$Q$1000)-ROW(LKTN!$Q$3)+1), ROWS(A$2:A6))),"")} | Z6: {=IFERROR(INDEX(LKTN!$G$3:$G$1000, SMALL( IF((LKTN!$Q$3:$Q$1000<>"")*(LKTN!$Q$3:$Q$1000<>"Not Due"), ROW(LKTN!$Q$3:$Q$1000)-ROW(LKTN!$Q$3)+1), ROWS(A$2:A6))),"")} | AA6: {=IFERROR(INDEX(LKTN!$Q$3:$Q$1000, SMALL( IF((LKTN!$Q$3:$Q$1000<>"")*(LKTN!$Q$3:$Q$1000<>"Not Due"), ROW(LKTN!$Q$3:$Q$1000)-ROW(LKTN!$Q$3)+1), ROWS(A$2:A6)) ),"")} | AC6: 5 | AD6: {=IFERROR(INDEX(LAM!$E$3:$E$1000, SMALL( IF((LAM!$Q$3:$Q$1000<>"")*(LAM!$Q$3:$Q$1000<>"Not Due"), ROW(LAM!$Q$3:$Q$1000)-ROW(LAM!$Q$3)+1), ROWS(A$2:A6))),"")} | AE6: {=IFERROR(INDEX(LAM!$B$3:$B$1000, SMALL( IF((LAM!$Q$3:$Q$1000<>"")*(LAM!$Q$3:$Q$1000<>"Not Due"), ROW(LAM!$Q$3:$Q$1000)-ROW(LAM!$Q$3)+1), ROWS(A$2:A6))),"")} | AF6: {=IFERROR(INDEX(LAM!$D$3:$D$1000, SMALL( IF((LAM!$Q$3:$Q$1000<>"")*(LAM!$Q$3:$Q$1000<>"Not Due"), ROW(LAM!$Q$3:$Q$1000)-ROW(LAM!$Q$3)+1), ROWS(A$2:A6))),"")} | AG6: {=IFERROR(INDEX(LAM!$G$3:$G$1000, SMALL( IF((LAM!$Q$3:$Q$1000<>"")*(LAM!$Q$3:$Q$1000<>"Not Due"), ROW(LAM!$Q$3:$Q$1000)-ROW(LAM!$Q$3)+1), ROWS(A$2:A6))),"")} | AH6: {=IFERROR(INDEX(LAM!$Q$3:$Q$1000, SMALL( IF((LAM!$Q$3:$Q$1000<>"")*(LAM!$Q$3:$Q$1000<>"Not Due"), ROW(LAM!$Q$3:$Q$1000)-ROW(LAM!$Q$3)+1), ROWS(A$2:A6)) ),"")} | AJ6: 5 | AK6: {=IFERROR(INDEX(ISN!$E$3:$E$1000, SMALL( IF((ISN!$Q$3:$Q$1000<>"")*(ISN!$Q$3:$Q$1000<>"Not Due"), ROW(ISN!$Q$3:$Q$1000)-ROW(ISN!$Q$3)+1), ROWS(A$2:A6))),"")} -> ISN | AL6: {=IFERROR(INDEX(ISN!$B$3:$B$1000, SMALL( IF((ISN!$Q$3:$Q$1000<>"")*(ISN!$Q$3:$Q$1000<>"Not Due"), ROW(ISN!$Q$3:$Q$1000)-ROW(ISN!$Q$3)+1), ROWS(A$2:A6))),"")} -> T/2026/00428 | AM6: {=IFERROR(INDEX(ISN!$D$3:$D$1000, SMALL( IF((ISN!$Q$3:$Q$1000<>"")*(ISN!$Q$3:$Q$1000<>"Not Due"), ROW(ISN!$Q$3:$Q$1000)-ROW(ISN!$Q$3)+1), ROWS(A$2:A6))),"")} -> MYASSET | AN6: {=IFERROR(INDEX(ISN!$G$3:$G$1000, SMALL( IF((ISN!$Q$3:$Q$1000<>"")*(ISN!$Q$3:$Q$1000<>"Not Due"), ROW(ISN!$Q$3:$Q$1000)-ROW(ISN!$Q$3)+1), ROWS(A$2:A6))),"")} -> 1) Selepas daftar pemeriksaan aset, pada sub modul_Cetak Pemeriksaan Aset, tiada maklumat dan tidak dapat pos data. 2) Bila cetak dokumen yang dah siap, pada Bahagian, maklumat tidak keluar/tidak lengkap. | AO6: {=IFERROR(INDEX(ISN!$Q$3:$Q$1000, SMALL( IF((ISN!$Q$3:$Q$1000<>"")*(ISN!$Q$3:$Q$1000<>"Not Due"), ROW(ISN!$Q$3:$Q$1000)-ROW(ISN!$Q$3)+1), ROWS(A$2:A6)) ),"")} -> 1-30 Days | AQ6: 5 | AR6: {=IFERROR(INDEX(MSN!$E$3:$E$1000, SMALL( IF((MSN!$Q$3:$Q$1000<>"")*(MSN!$Q$3:$Q$1000<>"Not Due"), ROW(MSN!$Q$3:$Q$1000)-ROW(MSN!$Q$3)+1), ROWS(A$2:A6))),"")} | AS6: {=IFERROR(INDEX(MSN!$B$3:$B$1000, SMALL( IF((MSN!$Q$3:$Q$1000<>"")*(MSN!$Q$3:$Q$1000<>"Not Due"), ROW(MSN!$Q$3:$Q$1000)-ROW(MSN!$Q$3)+1), ROWS(A$2:A6))),"")} | AT6: {=IFERROR(INDEX(MSN!$D$3:$D$1000, SMALL( IF((MSN!$Q$3:$Q$1000<>"")*(MSN!$Q$3:$Q$1000<>"Not Due"), ROW(MSN!$Q$3:$Q$1000)-ROW(MSN!$Q$3)+1), ROWS(A$2:A6))),"")} | AU6: {=IFERROR(INDEX(MSN!$G$3:$G$1000, SMALL( IF((MSN!$Q$3:$Q$1000<>"")*(MSN!$Q$3:$Q$1000<>"Not Due"), ROW(MSN!$Q$3:$Q$1000)-ROW(MSN!$Q$3)+1), ROWS(A$2:A6))),"")} | AV6: {=IFERROR(INDEX(MSN!$Q$3:$Q$1000, SMALL( IF((MSN!$Q$3:$Q$1000<>"")*(MSN!$Q$3:$Q$1000<>"Not Due"), ROW(MSN!$Q$3:$Q$1000)-ROW(MSN!$Q$3)+1), ROWS(A$2:A6)) ),"")}
A7: 6 | B7: {=IFERROR(INDEX(FRIM!$E$3:$E$1000, SMALL(IF(FRIM!$Q$3:$Q$1000<>"", ROW(FRIM!$Q$3:$Q$1000)-ROW(FRIM!$Q$3)+1), ROWS(A$2:A7))),"")} -> FRIM | C7: {=IFERROR(INDEX(FRIM!$B$3:$B$1000, SMALL(IF(FRIM!$Q$3:$Q$1000<>"", ROW(FRIM!$Q$3:$Q$1000)-ROW(FRIM!$Q$3)+1), ROWS(A$2:A7))),"")} -> T/2026/00087 | D7: {=IFERROR(INDEX(FRIM!$D$3:$D$1000, SMALL(IF(FRIM!$Q$3:$Q$1000<>"", ROW(FRIM!$Q$3:$Q$1000)-ROW(FRIM!$Q$3)+1), ROWS(A$2:A7))),"")} -> MYFINANCIAL CLIENT | E7: {=IFERROR(INDEX(FRIM!$G$3:$G$1000, SMALL(IF(FRIM!$Q$3:$Q$1000<>"", ROW(FRIM!$Q$3:$Q$1000)-ROW(FRIM!$Q$3)+1), ROWS(A$2:A7))),"")} -> NO ADUAN : W2516 TARIKH : 23/02/2026 NAMA : HASRINA HASNOR BT. KAMARUZAMAN UNTUK MAKLUMAN, FRIM AKAN MENGGUNAKAN VIRTUAL ACCOUNT (VA) DARIPADA CIMB BANK, DI MANA NOMBOR AKAUN ADALAH UNIK BAGI SETIAP BAHAGIAN/MAKMAL BAGI MEMUDAHKAN PENGECAMAN TERIMAAN. OLEH ITU, MOHON BANTUAN UNTUK KEMASKINI PILIHAN NOMBOR BANK DALAM INVOICE TERSEBUT. | F7: {=IFERROR(INDEX(FRIM!$Q$3:$Q$1000, SMALL(IF(FRIM!$Q$3:$Q$1000<>"", ROW(FRIM!$Q$3:$Q$1000)-ROW(FRIM!$Q$3)+1), ROWS(A$2:A7))),"")} -> >60 Days | H7: 6 | I7: {=IFERROR(INDEX(MTIB!$E$3:$E$1000, SMALL( IF((MTIB!$Q$3:$Q$1000<>"")*(MTIB!$Q$3:$Q$1000<>"Not Due"), ROW(MTIB!$Q$3:$Q$1000)-ROW(MTIB!$Q$3)+1), ROWS(A$2:A7))),"")} -> MTIB | J7: {=IFERROR(INDEX(MTIB!$B$3:$B$1000, SMALL( IF((MTIB!$Q$3:$Q$1000<>"")*(MTIB!$Q$3:$Q$1000<>"Not Due"), ROW(MTIB!$Q$3:$Q$1000)-ROW(MTIB!$Q$3)+1), ROWS(A$2:A7))),"")} -> T/2026/00020 | K7: {=IFERROR(INDEX(MTIB!$D$3:$D$1000, SMALL( IF((MTIB!$Q$3:$Q$1000<>"")*(MTIB!$Q$3:$Q$1000<>"Not Due"), ROW(MTIB!$Q$3:$Q$1000)-ROW(MTIB!$Q$3)+1), ROWS(A$2:A7))),"")} -> MYFINANCIAL | L7: {=IFERROR(INDEX(MTIB!$G$3:$G$1000, SMALL( IF((MTIB!$Q$3:$Q$1000<>"")*(MTIB!$Q$3:$Q$1000<>"Not Due"), ROW(MTIB!$Q$3:$Q$1000)-ROW(MTIB!$Q$3)+1), ROWS(A$2:A7))),"")} -> Tidak dapat notifikasi emel bagi MyFinancial | M7: {=IFERROR(INDEX(MTIB!$Q$3:$Q$1000, SMALL( IF((MTIB!$Q$3:$Q$1000<>"")*(MTIB!$Q$3:$Q$1000<>"Not Due"), ROW(MTIB!$Q$3:$Q$1000)-ROW(MTIB!$Q$3)+1), ROWS(A$2:A7)) ),"")} -> >60 Days | O7: 6 | P7: {=IFERROR(INDEX(MPOB!$E$3:$E$1000, SMALL( IF((MPOB!$Q$3:$Q$1000<>"")*(MPOB!$Q$3:$Q$1000<>"Not Due"), ROW(MPOB!$Q$3:$Q$1000)-ROW(MPOB!$Q$3)+1), ROWS(A$2:A7))),"")} -> MPOB | Q7: {=IFERROR(INDEX(MPOB!$B$3:$B$1000, SMALL( IF((MPOB!$Q$3:$Q$1000<>"")*(MPOB!$Q$3:$Q$1000<>"Not Due"), ROW(MPOB!$Q$3:$Q$1000)-ROW(MPOB!$Q$3)+1), ROWS(A$2:A7))),"")} -> T/2026/00148 | R7: {=IFERROR(INDEX(MPOB!$D$3:$D$1000, SMALL( IF((MPOB!$Q$3:$Q$1000<>"")*(MPOB!$Q$3:$Q$1000<>"Not Due"), ROW(MPOB!$Q$3:$Q$1000)-ROW(MPOB!$Q$3)+1), ROWS(A$2:A7))),"")} -> MyProcurement | S7: {=IFERROR(INDEX(MPOB!$G$3:$G$1000, SMALL( IF((MPOB!$Q$3:$Q$1000<>"")*(MPOB!$Q$3:$Q$1000<>"Not Due"), ROW(MPOB!$Q$3:$Q$1000)-ROW(MPOB!$Q$3)+1), ROWS(A$2:A7))),"")} -> Nama User : Nabila Date :21/1/2026 Isu : boleh ke nak mintak hapuskan pr ni, 008475? Sebab user salah letak nama utk penyokong dan penyemak. | T7: {=IFERROR(INDEX(MPOB!$Q$3:$Q$1000, SMALL( IF((MPOB!$Q$3:$Q$1000<>"")*(MPOB!$Q$3:$Q$1000<>"Not Due"), ROW(MPOB!$Q$3:$Q$1000)-ROW(MPOB!$Q$3)+1), ROWS(A$2:A7)) ),"")} -> >60 Days | V7: 6 | W7: {=IFERROR(INDEX(LKTN!$E$3:$E$1000, SMALL( IF((LKTN!$Q$3:$Q$1000<>"")*(LKTN!$Q$3:$Q$1000<>"Not Due"), ROW(LKTN!$Q$3:$Q$1000)-ROW(LKTN!$Q$3)+1), ROWS(A$2:A7))),"")} | X7: {=IFERROR(INDEX(LKTN!$B$3:$B$1000, SMALL( IF((LKTN!$Q$3:$Q$1000<>"")*(LKTN!$Q$3:$Q$1000<>"Not Due"), ROW(LKTN!$Q$3:$Q$1000)-ROW(LKTN!$Q$3)+1), ROWS(A$2:A7))),"")} | Y7: {=IFERROR(INDEX(LKTN!$D$3:$D$1000, SMALL( IF((LKTN!$Q$3:$Q$1000<>"")*(LKTN!$Q$3:$Q$1000<>"Not Due"), ROW(LKTN!$Q$3:$Q$1000)-ROW(LKTN!$Q$3)+1), ROWS(A$2:A7))),"")} | Z7: {=IFERROR(INDEX(LKTN!$G$3:$G$1000, SMALL( IF((LKTN!$Q$3:$Q$1000<>"")*(LKTN!$Q$3:$Q$1000<>"Not Due"), ROW(LKTN!$Q$3:$Q$1000)-ROW(LKTN!$Q$3)+1), ROWS(A$2:A7))),"")} | AA7: {=IFERROR(INDEX(LKTN!$Q$3:$Q$1000, SMALL( IF((LKTN!$Q$3:$Q$1000<>"")*(LKTN!$Q$3:$Q$1000<>"Not Due"), ROW(LKTN!$Q$3:$Q$1000)-ROW(LKTN!$Q$3)+1), ROWS(A$2:A7)) ),"")} | AC7: 6 | AD7: {=IFERROR(INDEX(LAM!$E$3:$E$1000, SMALL( IF((LAM!$Q$3:$Q$1000<>"")*(LAM!$Q$3:$Q$1000<>"Not Due"), ROW(LAM!$Q$3:$Q$1000)-ROW(LAM!$Q$3)+1), ROWS(A$2:A7))),"")} | AE7: {=IFERROR(INDEX(LAM!$B$3:$B$1000, SMALL( IF((LAM!$Q$3:$Q$1000<>"")*(LAM!$Q$3:$Q$1000<>"Not Due"), ROW(LAM!$Q$3:$Q$1000)-ROW(LAM!$Q$3)+1), ROWS(A$2:A7))),"")} | AF7: {=IFERROR(INDEX(LAM!$D$3:$D$1000, SMALL( IF((LAM!$Q$3:$Q$1000<>"")*(LAM!$Q$3:$Q$1000<>"Not Due"), ROW(LAM!$Q$3:$Q$1000)-ROW(LAM!$Q$3)+1), ROWS(A$2:A7))),"")} | AG7: {=IFERROR(INDEX(LAM!$G$3:$G$1000, SMALL( IF((LAM!$Q$3:$Q$1000<>"")*(LAM!$Q$3:$Q$1000<>"Not Due"), ROW(LAM!$Q$3:$Q$1000)-ROW(LAM!$Q$3)+1), ROWS(A$2:A7))),"")} | AH7: {=IFERROR(INDEX(LAM!$Q$3:$Q$1000, SMALL( IF((LAM!$Q$3:$Q$1000<>"")*(LAM!$Q$3:$Q$1000<>"Not Due"), ROW(LAM!$Q$3:$Q$1000)-ROW(LAM!$Q$3)+1), ROWS(A$2:A7)) ),"")} | AJ7: 6 | AK7: {=IFERROR(INDEX(ISN!$E$3:$E$1000, SMALL( IF((ISN!$Q$3:$Q$1000<>"")*(ISN!$Q$3:$Q$1000<>"Not Due"), ROW(ISN!$Q$3:$Q$1000)-ROW(ISN!$Q$3)+1), ROWS(A$2:A7))),"")} -> ISN | AL7: {=IFERROR(INDEX(ISN!$B$3:$B$1000, SMALL( IF((ISN!$Q$3:$Q$1000<>"")*(ISN!$Q$3:$Q$1000<>"Not Due"), ROW(ISN!$Q$3:$Q$1000)-ROW(ISN!$Q$3)+1), ROWS(A$2:A7))),"")} -> T/2026/00432 | AM7: {=IFERROR(INDEX(ISN!$D$3:$D$1000, SMALL( IF((ISN!$Q$3:$Q$1000<>"")*(ISN!$Q$3:$Q$1000<>"Not Due"), ROW(ISN!$Q$3:$Q$1000)-ROW(ISN!$Q$3)+1), ROWS(A$2:A7))),"")} -> MYSTOR | AN7: {=IFERROR(INDEX(ISN!$G$3:$G$1000, SMALL( IF((ISN!$Q$3:$Q$1000<>"")*(ISN!$Q$3:$Q$1000<>"Not Due"), ROW(ISN!$Q$3:$Q$1000)-ROW(ISN!$Q$3)+1), ROWS(A$2:A7))),"")} -> KEMASKINI BAKI KEW-PS 3 BAGI TAHUN 2026 UNTUK 155 ITEM YANG TERLIBAT SEPERTI DIBINCANGKAN ANTARA EN. MUHAIMIN DAN EN.NIK TERIMA KASIH. -MUHAIMIN (ISN) | AO7: {=IFERROR(INDEX(ISN!$Q$3:$Q$1000, SMALL( IF((ISN!$Q$3:$Q$1000<>"")*(ISN!$Q$3:$Q$1000<>"Not Due"), ROW(ISN!$Q$3:$Q$1000)-ROW(ISN!$Q$3)+1), ROWS(A$2:A7)) ),"")} -> 1-30 Days | AQ7: 6 | AR7: {=IFERROR(INDEX(MSN!$E$3:$E$1000, SMALL( IF((MSN!$Q$3:$Q$1000<>"")*(MSN!$Q$3:$Q$1000<>"Not Due"), ROW(MSN!$Q$3:$Q$1000)-ROW(MSN!$Q$3)+1), ROWS(A$2:A7))),"")} | AS7: {=IFERROR(INDEX(MSN!$B$3:$B$1000, SMALL( IF((MSN!$Q$3:$Q$1000<>"")*(MSN!$Q$3:$Q$1000<>"Not Due"), ROW(MSN!$Q$3:$Q$1000)-ROW(MSN!$Q$3)+1), ROWS(A$2:A7))),"")} | AT7: {=IFERROR(INDEX(MSN!$D$3:$D$1000, SMALL( IF((MSN!$Q$3:$Q$1000<>"")*(MSN!$Q$3:$Q$1000<>"Not Due"), ROW(MSN!$Q$3:$Q$1000)-ROW(MSN!$Q$3)+1), ROWS(A$2:A7))),"")} | AU7: {=IFERROR(INDEX(MSN!$G$3:$G$1000, SMALL( IF((MSN!$Q$3:$Q$1000<>"")*(MSN!$Q$3:$Q$1000<>"Not Due"), ROW(MSN!$Q$3:$Q$1000)-ROW(MSN!$Q$3)+1), ROWS(A$2:A7))),"")} | AV7: {=IFERROR(INDEX(MSN!$Q$3:$Q$1000, SMALL( IF((MSN!$Q$3:$Q$1000<>"")*(MSN!$Q$3:$Q$1000<>"Not Due"), ROW(MSN!$Q$3:$Q$1000)-ROW(MSN!$Q$3)+1), ROWS(A$2:A7)) ),"")}
A8: 7 | B8: {=IFERROR(INDEX(FRIM!$E$3:$E$1000, SMALL(IF(FRIM!$Q$3:$Q$1000<>"", ROW(FRIM!$Q$3:$Q$1000)-ROW(FRIM!$Q$3)+1), ROWS(A$2:A8))),"")} -> FRIM | C8: {=IFERROR(INDEX(FRIM!$B$3:$B$1000, SMALL(IF(FRIM!$Q$3:$Q$1000<>"", ROW(FRIM!$Q$3:$Q$1000)-ROW(FRIM!$Q$3)+1), ROWS(A$2:A8))),"")} -> T/2026/00093 | D8: {=IFERROR(INDEX(FRIM!$D$3:$D$1000, SMALL(IF(FRIM!$Q$3:$Q$1000<>"", ROW(FRIM!$Q$3:$Q$1000)-ROW(FRIM!$Q$3)+1), ROWS(A$2:A8))),"")} -> MYFINANCIAL CLIENT | E8: {=IFERROR(INDEX(FRIM!$G$3:$G$1000, SMALL(IF(FRIM!$Q$3:$Q$1000<>"", ROW(FRIM!$Q$3:$Q$1000)-ROW(FRIM!$Q$3)+1), ROWS(A$2:A8))),"")} -> W2315 06/03/2024 NORFAZIRA BINTI MUHAMAD PAUZI LO RFQ19011 - DI SISTEM MYQUERY TERDAPAT LEBIHAN BAYARAN SEBANYAK (RM3,791.30) TETAPI DI SISTEM MYFINANCIAL DAN REKOD BAYARAN ADALAH TIDAK MELEBIHI BAYARAN. | F8: {=IFERROR(INDEX(FRIM!$Q$3:$Q$1000, SMALL(IF(FRIM!$Q$3:$Q$1000<>"", ROW(FRIM!$Q$3:$Q$1000)-ROW(FRIM!$Q$3)+1), ROWS(A$2:A8))),"")} -> >60 Days | H8: 7 | I8: {=IFERROR(INDEX(MTIB!$E$3:$E$1000, SMALL( IF((MTIB!$Q$3:$Q$1000<>"")*(MTIB!$Q$3:$Q$1000<>"Not Due"), ROW(MTIB!$Q$3:$Q$1000)-ROW(MTIB!$Q$3)+1), ROWS(A$2:A8))),"")} -> MTIB | J8: {=IFERROR(INDEX(MTIB!$B$3:$B$1000, SMALL( IF((MTIB!$Q$3:$Q$1000<>"")*(MTIB!$Q$3:$Q$1000<>"Not Due"), ROW(MTIB!$Q$3:$Q$1000)-ROW(MTIB!$Q$3)+1), ROWS(A$2:A8))),"")} -> T/2026/00094 | K8: {=IFERROR(INDEX(MTIB!$D$3:$D$1000, SMALL( IF((MTIB!$Q$3:$Q$1000<>"")*(MTIB!$Q$3:$Q$1000<>"Not Due"), ROW(MTIB!$Q$3:$Q$1000)-ROW(MTIB!$Q$3)+1), ROWS(A$2:A8))),"")} -> MYFINANCIAL | L8: {=IFERROR(INDEX(MTIB!$G$3:$G$1000, SMALL( IF((MTIB!$Q$3:$Q$1000<>"")*(MTIB!$Q$3:$Q$1000<>"Not Due"), ROW(MTIB!$Q$3:$Q$1000)-ROW(MTIB!$Q$3)+1), ROWS(A$2:A8))),"")} -> 1. Jumlah tidak sama pada laporan KIRA-KIRA KENA BAYAR (TELAH POS) 2. Invois/ daftar bil menjadi double Pengadu: Siti Zahrah Senin | M8: {=IFERROR(INDEX(MTIB!$Q$3:$Q$1000, SMALL( IF((MTIB!$Q$3:$Q$1000<>"")*(MTIB!$Q$3:$Q$1000<>"Not Due"), ROW(MTIB!$Q$3:$Q$1000)-ROW(MTIB!$Q$3)+1), ROWS(A$2:A8)) ),"")} -> >60 Days | O8: 7 | P8: {=IFERROR(INDEX(MPOB!$E$3:$E$1000, SMALL( IF((MPOB!$Q$3:$Q$1000<>"")*(MPOB!$Q$3:$Q$1000<>"Not Due"), ROW(MPOB!$Q$3:$Q$1000)-ROW(MPOB!$Q$3)+1), ROWS(A$2:A8))),"")} -> MPOB | Q8: {=IFERROR(INDEX(MPOB!$B$3:$B$1000, SMALL( IF((MPOB!$Q$3:$Q$1000<>"")*(MPOB!$Q$3:$Q$1000<>"Not Due"), ROW(MPOB!$Q$3:$Q$1000)-ROW(MPOB!$Q$3)+1), ROWS(A$2:A8))),"")} -> T/2026/00150 | R8: {=IFERROR(INDEX(MPOB!$D$3:$D$1000, SMALL( IF((MPOB!$Q$3:$Q$1000<>"")*(MPOB!$Q$3:$Q$1000<>"Not Due"), ROW(MPOB!$Q$3:$Q$1000)-ROW(MPOB!$Q$3)+1), ROWS(A$2:A8))),"")} -> MyFinancial | S8: {=IFERROR(INDEX(MPOB!$G$3:$G$1000, SMALL( IF((MPOB!$Q$3:$Q$1000<>"")*(MPOB!$Q$3:$Q$1000<>"Not Due"), ROW(MPOB!$Q$3:$Q$1000)-ROW(MPOB!$Q$3)+1), ROWS(A$2:A8))),"")} -> Nama User : Norlizah Date : 21/1/2026 Isu : saya masih tak boleh sahkan ni👆 yg ni pun tak boleh nk sahkan | T8: {=IFERROR(INDEX(MPOB!$Q$3:$Q$1000, SMALL( IF((MPOB!$Q$3:$Q$1000<>"")*(MPOB!$Q$3:$Q$1000<>"Not Due"), ROW(MPOB!$Q$3:$Q$1000)-ROW(MPOB!$Q$3)+1), ROWS(A$2:A8)) ),"")} -> >60 Days | V8: 7 | W8: {=IFERROR(INDEX(LKTN!$E$3:$E$1000, SMALL( IF((LKTN!$Q$3:$Q$1000<>"")*(LKTN!$Q$3:$Q$1000<>"Not Due"), ROW(LKTN!$Q$3:$Q$1000)-ROW(LKTN!$Q$3)+1), ROWS(A$2:A8))),"")} | X8: {=IFERROR(INDEX(LKTN!$B$3:$B$1000, SMALL( IF((LKTN!$Q$3:$Q$1000<>"")*(LKTN!$Q$3:$Q$1000<>"Not Due"), ROW(LKTN!$Q$3:$Q$1000)-ROW(LKTN!$Q$3)+1), ROWS(A$2:A8))),"")} | Y8: {=IFERROR(INDEX(LKTN!$D$3:$D$1000, SMALL( IF((LKTN!$Q$3:$Q$1000<>"")*(LKTN!$Q$3:$Q$1000<>"Not Due"), ROW(LKTN!$Q$3:$Q$1000)-ROW(LKTN!$Q$3)+1), ROWS(A$2:A8))),"")} | Z8: {=IFERROR(INDEX(LKTN!$G$3:$G$1000, SMALL( IF((LKTN!$Q$3:$Q$1000<>"")*(LKTN!$Q$3:$Q$1000<>"Not Due"), ROW(LKTN!$Q$3:$Q$1000)-ROW(LKTN!$Q$3)+1), ROWS(A$2:A8))),"")} | AA8: {=IFERROR(INDEX(LKTN!$Q$3:$Q$1000, SMALL( IF((LKTN!$Q$3:$Q$1000<>"")*(LKTN!$Q$3:$Q$1000<>"Not Due"), ROW(LKTN!$Q$3:$Q$1000)-ROW(LKTN!$Q$3)+1), ROWS(A$2:A8)) ),"")} | AC8: 7 | AD8: {=IFERROR(INDEX(LAM!$E$3:$E$1000, SMALL( IF((LAM!$Q$3:$Q$1000<>"")*(LAM!$Q$3:$Q$1000<>"Not Due"), ROW(LAM!$Q$3:$Q$1000)-ROW(LAM!$Q$3)+1), ROWS(A$2:A8))),"")} | AE8: {=IFERROR(INDEX(LAM!$B$3:$B$1000, SMALL( IF((LAM!$Q$3:$Q$1000<>"")*(LAM!$Q$3:$Q$1000<>"Not Due"), ROW(LAM!$Q$3:$Q$1000)-ROW(LAM!$Q$3)+1), ROWS(A$2:A8))),"")} | AF8: {=IFERROR(INDEX(LAM!$D$3:$D$1000, SMALL( IF((LAM!$Q$3:$Q$1000<>"")*(LAM!$Q$3:$Q$1000<>"Not Due"), ROW(LAM!$Q$3:$Q$1000)-ROW(LAM!$Q$3)+1), ROWS(A$2:A8))),"")} | AG8: {=IFERROR(INDEX(LAM!$G$3:$G$1000, SMALL( IF((LAM!$Q$3:$Q$1000<>"")*(LAM!$Q$3:$Q$1000<>"Not Due"), ROW(LAM!$Q$3:$Q$1000)-ROW(LAM!$Q$3)+1), ROWS(A$2:A8))),"")} | AH8: {=IFERROR(INDEX(LAM!$Q$3:$Q$1000, SMALL( IF((LAM!$Q$3:$Q$1000<>"")*(LAM!$Q$3:$Q$1000<>"Not Due"), ROW(LAM!$Q$3:$Q$1000)-ROW(LAM!$Q$3)+1), ROWS(A$2:A8)) ),"")} | AJ8: 7 | AK8: {=IFERROR(INDEX(ISN!$E$3:$E$1000, SMALL( IF((ISN!$Q$3:$Q$1000<>"")*(ISN!$Q$3:$Q$1000<>"Not Due"), ROW(ISN!$Q$3:$Q$1000)-ROW(ISN!$Q$3)+1), ROWS(A$2:A8))),"")} -> ISN | AL8: {=IFERROR(INDEX(ISN!$B$3:$B$1000, SMALL( IF((ISN!$Q$3:$Q$1000<>"")*(ISN!$Q$3:$Q$1000<>"Not Due"), ROW(ISN!$Q$3:$Q$1000)-ROW(ISN!$Q$3)+1), ROWS(A$2:A8))),"")} -> T/2026/00453 | AM8: {=IFERROR(INDEX(ISN!$D$3:$D$1000, SMALL( IF((ISN!$Q$3:$Q$1000<>"")*(ISN!$Q$3:$Q$1000<>"Not Due"), ROW(ISN!$Q$3:$Q$1000)-ROW(ISN!$Q$3)+1), ROWS(A$2:A8))),"")} -> MYASSET | AN8: {=IFERROR(INDEX(ISN!$G$3:$G$1000, SMALL( IF((ISN!$Q$3:$Q$1000<>"")*(ISN!$Q$3:$Q$1000<>"Not Due"), ROW(ISN!$Q$3:$Q$1000)-ROW(ISN!$Q$3)+1), ROWS(A$2:A8))),"")} -> 1) Pada kad Kew Pa 3 dan 4, Bahagian Pemeriksaan dimohon penambahbaikan seperti berikut:: 1.1) Nama lokasi sama seperi nama pada Bahagian penempatan contoh B-036-Bilik Lily, Psikologi Sukan. 1.2) Status aset dipilih mengikut pekelililing contohnya. sedang digunakan, tidak digunakan, perlu pembaikan dan lain-lain. | AO8: {=IFERROR(INDEX(ISN!$Q$3:$Q$1000, SMALL( IF((ISN!$Q$3:$Q$1000<>"")*(ISN!$Q$3:$Q$1000<>"Not Due"), ROW(ISN!$Q$3:$Q$1000)-ROW(ISN!$Q$3)+1), ROWS(A$2:A8)) ),"")} -> 1-30 Days | AQ8: 7 | AR8: {=IFERROR(INDEX(MSN!$E$3:$E$1000, SMALL( IF((MSN!$Q$3:$Q$1000<>"")*(MSN!$Q$3:$Q$1000<>"Not Due"), ROW(MSN!$Q$3:$Q$1000)-ROW(MSN!$Q$3)+1), ROWS(A$2:A8))),"")} | AS8: {=IFERROR(INDEX(MSN!$B$3:$B$1000, SMALL( IF((MSN!$Q$3:$Q$1000<>"")*(MSN!$Q$3:$Q$1000<>"Not Due"), ROW(MSN!$Q$3:$Q$1000)-ROW(MSN!$Q$3)+1), ROWS(A$2:A8))),"")} | AT8: {=IFERROR(INDEX(MSN!$D$3:$D$1000, SMALL( IF((MSN!$Q$3:$Q$1000<>"")*(MSN!$Q$3:$Q$1000<>"Not Due"), ROW(MSN!$Q$3:$Q$1000)-ROW(MSN!$Q$3)+1), ROWS(A$2:A8))),"")} | AU8: {=IFERROR(INDEX(MSN!$G$3:$G$1000, SMALL( IF((MSN!$Q$3:$Q$1000<>"")*(MSN!$Q$3:$Q$1000<>"Not Due"), ROW(MSN!$Q$3:$Q$1000)-ROW(MSN!$Q$3)+1), ROWS(A$2:A8))),"")} | AV8: {=IFERROR(INDEX(MSN!$Q$3:$Q$1000, SMALL( IF((MSN!$Q$3:$Q$1000<>"")*(MSN!$Q$3:$Q$1000<>"Not Due"), ROW(MSN!$Q$3:$Q$1000)-ROW(MSN!$Q$3)+1), ROWS(A$2:A8)) ),"")}
A9: 8 | B9: {=IFERROR(INDEX(FRIM!$E$3:$E$1000, SMALL(IF(FRIM!$Q$3:$Q$1000<>"", ROW(FRIM!$Q$3:$Q$1000)-ROW(FRIM!$Q$3)+1), ROWS(A$2:A9))),"")} -> FRIM | C9: {=IFERROR(INDEX(FRIM!$B$3:$B$1000, SMALL(IF(FRIM!$Q$3:$Q$1000<>"", ROW(FRIM!$Q$3:$Q$1000)-ROW(FRIM!$Q$3)+1), ROWS(A$2:A9))),"")} -> T/2026/00095 | D9: {=IFERROR(INDEX(FRIM!$D$3:$D$1000, SMALL(IF(FRIM!$Q$3:$Q$1000<>"", ROW(FRIM!$Q$3:$Q$1000)-ROW(FRIM!$Q$3)+1), ROWS(A$2:A9))),"")} -> URUSNIAGA PPS | E9: {=IFERROR(INDEX(FRIM!$G$3:$G$1000, SMALL(IF(FRIM!$Q$3:$Q$1000<>"", ROW(FRIM!$Q$3:$Q$1000)-ROW(FRIM!$Q$3)+1), ROWS(A$2:A9))),"")} -> W2357 03/09/2024 NURFAIEZAH BT. MAZERI KEY IN PEMBELIAN ITEM JENIS BUKU TIDAK BOLEH DILAKUKAN DALAM SISTEM MYURUSNIAGA, SEMAKAN DALAM MYINVENTORY DIDAPATI ITEM MASIH AKTIF. MOHON BANTUAN BERKENAAN BARANGAN JENIS BUKU (KOD BUKU BERMULA BKBK) | F9: {=IFERROR(INDEX(FRIM!$Q$3:$Q$1000, SMALL(IF(FRIM!$Q$3:$Q$1000<>"", ROW(FRIM!$Q$3:$Q$1000)-ROW(FRIM!$Q$3)+1), ROWS(A$2:A9))),"")} -> >60 Days | H9: 8 | I9: {=IFERROR(INDEX(MTIB!$E$3:$E$1000, SMALL( IF((MTIB!$Q$3:$Q$1000<>"")*(MTIB!$Q$3:$Q$1000<>"Not Due"), ROW(MTIB!$Q$3:$Q$1000)-ROW(MTIB!$Q$3)+1), ROWS(A$2:A9))),"")} -> MTIB | J9: {=IFERROR(INDEX(MTIB!$B$3:$B$1000, SMALL( IF((MTIB!$Q$3:$Q$1000<>"")*(MTIB!$Q$3:$Q$1000<>"Not Due"), ROW(MTIB!$Q$3:$Q$1000)-ROW(MTIB!$Q$3)+1), ROWS(A$2:A9))),"")} -> T/2026/00298 | K9: {=IFERROR(INDEX(MTIB!$D$3:$D$1000, SMALL( IF((MTIB!$Q$3:$Q$1000<>"")*(MTIB!$Q$3:$Q$1000<>"Not Due"), ROW(MTIB!$Q$3:$Q$1000)-ROW(MTIB!$Q$3)+1), ROWS(A$2:A9))),"")} -> MYFINANCIAL | L9: {=IFERROR(INDEX(MTIB!$G$3:$G$1000, SMALL( IF((MTIB!$Q$3:$Q$1000<>"")*(MTIB!$Q$3:$Q$1000<>"Not Due"), ROW(MTIB!$Q$3:$Q$1000)-ROW(MTIB!$Q$3)+1), ROWS(A$2:A9))),"")} -> Masukkan nombor akaun Maybank:514404801787 di ruangan nombor akaun dalam Invoice. Pengadu: Marliani | M9: {=IFERROR(INDEX(MTIB!$Q$3:$Q$1000, SMALL( IF((MTIB!$Q$3:$Q$1000<>"")*(MTIB!$Q$3:$Q$1000<>"Not Due"), ROW(MTIB!$Q$3:$Q$1000)-ROW(MTIB!$Q$3)+1), ROWS(A$2:A9)) ),"")} -> 31-60 Days | O9: 8 | P9: {=IFERROR(INDEX(MPOB!$E$3:$E$1000, SMALL( IF((MPOB!$Q$3:$Q$1000<>"")*(MPOB!$Q$3:$Q$1000<>"Not Due"), ROW(MPOB!$Q$3:$Q$1000)-ROW(MPOB!$Q$3)+1), ROWS(A$2:A9))),"")} -> MPOB | Q9: {=IFERROR(INDEX(MPOB!$B$3:$B$1000, SMALL( IF((MPOB!$Q$3:$Q$1000<>"")*(MPOB!$Q$3:$Q$1000<>"Not Due"), ROW(MPOB!$Q$3:$Q$1000)-ROW(MPOB!$Q$3)+1), ROWS(A$2:A9))),"")} -> T/2026/00151 | R9: {=IFERROR(INDEX(MPOB!$D$3:$D$1000, SMALL( IF((MPOB!$Q$3:$Q$1000<>"")*(MPOB!$Q$3:$Q$1000<>"Not Due"), ROW(MPOB!$Q$3:$Q$1000)-ROW(MPOB!$Q$3)+1), ROWS(A$2:A9))),"")} -> MyProcurement | S9: {=IFERROR(INDEX(MPOB!$G$3:$G$1000, SMALL( IF((MPOB!$Q$3:$Q$1000<>"")*(MPOB!$Q$3:$Q$1000<>"Not Due"), ROW(MPOB!$Q$3:$Q$1000)-ROW(MPOB!$Q$3)+1), ROWS(A$2:A9))),"")} -> Nama User : Hazirah Hasnudin Date : 22/1/2026 Isu : Sy nak tny berkenaan myprocurement. Sy buat perolehan menggunakan kod P60SOIL01B1435701, tp utk urusan pendaftaran aset dlm myaset kod ni tiada. Kod ni tiada dlm list diatas | T9: {=IFERROR(INDEX(MPOB!$Q$3:$Q$1000, SMALL( IF((MPOB!$Q$3:$Q$1000<>"")*(MPOB!$Q$3:$Q$1000<>"Not Due"), ROW(MPOB!$Q$3:$Q$1000)-ROW(MPOB!$Q$3)+1), ROWS(A$2:A9)) ),"")} -> >60 Days | V9: 8 | W9: {=IFERROR(INDEX(LKTN!$E$3:$E$1000, SMALL( IF((LKTN!$Q$3:$Q$1000<>"")*(LKTN!$Q$3:$Q$1000<>"Not Due"), ROW(LKTN!$Q$3:$Q$1000)-ROW(LKTN!$Q$3)+1), ROWS(A$2:A9))),"")} | X9: {=IFERROR(INDEX(LKTN!$B$3:$B$1000, SMALL( IF((LKTN!$Q$3:$Q$1000<>"")*(LKTN!$Q$3:$Q$1000<>"Not Due"), ROW(LKTN!$Q$3:$Q$1000)-ROW(LKTN!$Q$3)+1), ROWS(A$2:A9))),"")} | Y9: {=IFERROR(INDEX(LKTN!$D$3:$D$1000, SMALL( IF((LKTN!$Q$3:$Q$1000<>"")*(LKTN!$Q$3:$Q$1000<>"Not Due"), ROW(LKTN!$Q$3:$Q$1000)-ROW(LKTN!$Q$3)+1), ROWS(A$2:A9))),"")} | Z9: {=IFERROR(INDEX(LKTN!$G$3:$G$1000, SMALL( IF((LKTN!$Q$3:$Q$1000<>"")*(LKTN!$Q$3:$Q$1000<>"Not Due"), ROW(LKTN!$Q$3:$Q$1000)-ROW(LKTN!$Q$3)+1), ROWS(A$2:A9))),"")} | AA9: {=IFERROR(INDEX(LKTN!$Q$3:$Q$1000, SMALL( IF((LKTN!$Q$3:$Q$1000<>"")*(LKTN!$Q$3:$Q$1000<>"Not Due"), ROW(LKTN!$Q$3:$Q$1000)-ROW(LKTN!$Q$3)+1), ROWS(A$2:A9)) ),"")} | AC9: 8 | AD9: {=IFERROR(INDEX(LAM!$E$3:$E$1000, SMALL( IF((LAM!$Q$3:$Q$1000<>"")*(LAM!$Q$3:$Q$1000<>"Not Due"), ROW(LAM!$Q$3:$Q$1000)-ROW(LAM!$Q$3)+1), ROWS(A$2:A9))),"")} | AE9: {=IFERROR(INDEX(LAM!$B$3:$B$1000, SMALL( IF((LAM!$Q$3:$Q$1000<>"")*(LAM!$Q$3:$Q$1000<>"Not Due"), ROW(LAM!$Q$3:$Q$1000)-ROW(LAM!$Q$3)+1), ROWS(A$2:A9))),"")} | AF9: {=IFERROR(INDEX(LAM!$D$3:$D$1000, SMALL( IF((LAM!$Q$3:$Q$1000<>"")*(LAM!$Q$3:$Q$1000<>"Not Due"), ROW(LAM!$Q$3:$Q$1000)-ROW(LAM!$Q$3)+1), ROWS(A$2:A9))),"")} | AG9: {=IFERROR(INDEX(LAM!$G$3:$G$1000, SMALL( IF((LAM!$Q$3:$Q$1000<>"")*(LAM!$Q$3:$Q$1000<>"Not Due"), ROW(LAM!$Q$3:$Q$1000)-ROW(LAM!$Q$3)+1), ROWS(A$2:A9))),"")} | AH9: {=IFERROR(INDEX(LAM!$Q$3:$Q$1000, SMALL( IF((LAM!$Q$3:$Q$1000<>"")*(LAM!$Q$3:$Q$1000<>"Not Due"), ROW(LAM!$Q$3:$Q$1000)-ROW(LAM!$Q$3)+1), ROWS(A$2:A9)) ),"")} | AJ9: 8 | AK9: {=IFERROR(INDEX(ISN!$E$3:$E$1000, SMALL( IF((ISN!$Q$3:$Q$1000<>"")*(ISN!$Q$3:$Q$1000<>"Not Due"), ROW(ISN!$Q$3:$Q$1000)-ROW(ISN!$Q$3)+1), ROWS(A$2:A9))),"")} -> ISN | AL9: {=IFERROR(INDEX(ISN!$B$3:$B$1000, SMALL( IF((ISN!$Q$3:$Q$1000<>"")*(ISN!$Q$3:$Q$1000<>"Not Due"), ROW(ISN!$Q$3:$Q$1000)-ROW(ISN!$Q$3)+1), ROWS(A$2:A9))),"")} -> T/2026/00454 | AM9: {=IFERROR(INDEX(ISN!$D$3:$D$1000, SMALL( IF((ISN!$Q$3:$Q$1000<>"")*(ISN!$Q$3:$Q$1000<>"Not Due"), ROW(ISN!$Q$3:$Q$1000)-ROW(ISN!$Q$3)+1), ROWS(A$2:A9))),"")} -> MYASSET | AN9: {=IFERROR(INDEX(ISN!$G$3:$G$1000, SMALL( IF((ISN!$Q$3:$Q$1000<>"")*(ISN!$Q$3:$Q$1000<>"Not Due"), ROW(ISN!$Q$3:$Q$1000)-ROW(ISN!$Q$3)+1), ROWS(A$2:A9))),"")} -> 1) Melalui MyAsset, Submodel: Kemaskini Rekod Pemeriksaan Aset, mohon tambah: 1.1) Filter Nama Pegawai Semasa untuk diklik 1.2) Pada Butiran Aset, mohon tambah column untuk paparan Nama Pegawai Semasa | AO9: {=IFERROR(INDEX(ISN!$Q$3:$Q$1000, SMALL( IF((ISN!$Q$3:$Q$1000<>"")*(ISN!$Q$3:$Q$1000<>"Not Due"), ROW(ISN!$Q$3:$Q$1000)-ROW(ISN!$Q$3)+1), ROWS(A$2:A9)) ),"")} -> 1-30 Days | AQ9: 8 | AR9: {=IFERROR(INDEX(MSN!$E$3:$E$1000, SMALL( IF((MSN!$Q$3:$Q$1000<>"")*(MSN!$Q$3:$Q$1000<>"Not Due"), ROW(MSN!$Q$3:$Q$1000)-ROW(MSN!$Q$3)+1), ROWS(A$2:A9))),"")} | AS9: {=IFERROR(INDEX(MSN!$B$3:$B$1000, SMALL( IF((MSN!$Q$3:$Q$1000<>"")*(MSN!$Q$3:$Q$1000<>"Not Due"), ROW(MSN!$Q$3:$Q$1000)-ROW(MSN!$Q$3)+1), ROWS(A$2:A9))),"")} | AT9: {=IFERROR(INDEX(MSN!$D$3:$D$1000, SMALL( IF((MSN!$Q$3:$Q$1000<>"")*(MSN!$Q$3:$Q$1000<>"Not Due"), ROW(MSN!$Q$3:$Q$1000)-ROW(MSN!$Q$3)+1), ROWS(A$2:A9))),"")} | AU9: {=IFERROR(INDEX(MSN!$G$3:$G$1000, SMALL( IF((MSN!$Q$3:$Q$1000<>"")*(MSN!$Q$3:$Q$1000<>"Not Due"), ROW(MSN!$Q$3:$Q$1000)-ROW(MSN!$Q$3)+1), ROWS(A$2:A9))),"")} | AV9: {=IFERROR(INDEX(MSN!$Q$3:$Q$1000, SMALL( IF((MSN!$Q$3:$Q$1000<>"")*(MSN!$Q$3:$Q$1000<>"Not Due"), ROW(MSN!$Q$3:$Q$1000)-ROW(MSN!$Q$3)+1), ROWS(A$2:A9)) ),"")}
A10: 9 | B10: {=IFERROR(INDEX(FRIM!$E$3:$E$1000, SMALL(IF(FRIM!$Q$3:$Q$1000<>"", ROW(FRIM!$Q$3:$Q$1000)-ROW(FRIM!$Q$3)+1), ROWS(A$2:A10))),"")} -> FRIM | C10: {=IFERROR(INDEX(FRIM!$B$3:$B$1000, SMALL(IF(FRIM!$Q$3:$Q$1000<>"", ROW(FRIM!$Q$3:$Q$1000)-ROW(FRIM!$Q$3)+1), ROWS(A$2:A10))),"")} -> T/2026/00096 | D10: {=IFERROR(INDEX(FRIM!$D$3:$D$1000, SMALL(IF(FRIM!$Q$3:$Q$1000<>"", ROW(FRIM!$Q$3:$Q$1000)-ROW(FRIM!$Q$3)+1), ROWS(A$2:A10))),"")} -> QUERY | E10: {=IFERROR(INDEX(FRIM!$G$3:$G$1000, SMALL(IF(FRIM!$Q$3:$Q$1000<>"", ROW(FRIM!$Q$3:$Q$1000)-ROW(FRIM!$Q$3)+1), ROWS(A$2:A10))),"")} -> W2365 17/10/2024 AHMAD FAREEZ BIN ZAINUDDIN SEMAKAN MENDAPATI NOMBOR VOT 24011501001 BULAN OGOS 2024 PADA LAPORAN PENYATA KEWANGAN MYQUERY. STATUS KOMITMEN MENUJUKKAN MASIH BELUM DIBAYAR,SEDANGKAN BAYARAN TELAH DIBUAT PADA BULAN OGOS 2024 DAN IANYA TELAH DIREKODKAN DIPERBELANJAAN. INI MENJADIKAN DOBULE COUNTING LO TERSEBUT PADA BULAN OGOS 2024 MENYEBABKAN BAKI AKHIR SELEPAS KOMITMEN TIDAK BETUL. MOHON KESELURUHAN SEMAKAN DIBUAT . CONTOH LO ADALAH SH24008 DALAM VOT TERSEBUT. | F10: {=IFERROR(INDEX(FRIM!$Q$3:$Q$1000, SMALL(IF(FRIM!$Q$3:$Q$1000<>"", ROW(FRIM!$Q$3:$Q$1000)-ROW(FRIM!$Q$3)+1), ROWS(A$2:A10))),"")} -> >60 Days | H10: 9 | I10: {=IFERROR(INDEX(MTIB!$E$3:$E$1000, SMALL( IF((MTIB!$Q$3:$Q$1000<>"")*(MTIB!$Q$3:$Q$1000<>"Not Due"), ROW(MTIB!$Q$3:$Q$1000)-ROW(MTIB!$Q$3)+1), ROWS(A$2:A10))),"")} -> MTIB | J10: {=IFERROR(INDEX(MTIB!$B$3:$B$1000, SMALL( IF((MTIB!$Q$3:$Q$1000<>"")*(MTIB!$Q$3:$Q$1000<>"Not Due"), ROW(MTIB!$Q$3:$Q$1000)-ROW(MTIB!$Q$3)+1), ROWS(A$2:A10))),"")} -> T/2026/00309 | K10: {=IFERROR(INDEX(MTIB!$D$3:$D$1000, SMALL( IF((MTIB!$Q$3:$Q$1000<>"")*(MTIB!$Q$3:$Q$1000<>"Not Due"), ROW(MTIB!$Q$3:$Q$1000)-ROW(MTIB!$Q$3)+1), ROWS(A$2:A10))),"")} -> MYFINANCIAL | L10: {=IFERROR(INDEX(MTIB!$G$3:$G$1000, SMALL( IF((MTIB!$Q$3:$Q$1000<>"")*(MTIB!$Q$3:$Q$1000<>"Not Due"), ROW(MTIB!$Q$3:$Q$1000)-ROW(MTIB!$Q$3)+1), ROWS(A$2:A10))),"")} -> Isu yang sama berulang. Sebelum ini telah diadukan pada tahun 2025 dan telah dibaiki. | M10: {=IFERROR(INDEX(MTIB!$Q$3:$Q$1000, SMALL( IF((MTIB!$Q$3:$Q$1000<>"")*(MTIB!$Q$3:$Q$1000<>"Not Due"), ROW(MTIB!$Q$3:$Q$1000)-ROW(MTIB!$Q$3)+1), ROWS(A$2:A10)) ),"")} -> 31-60 Days | O10: 9 | P10: {=IFERROR(INDEX(MPOB!$E$3:$E$1000, SMALL( IF((MPOB!$Q$3:$Q$1000<>"")*(MPOB!$Q$3:$Q$1000<>"Not Due"), ROW(MPOB!$Q$3:$Q$1000)-ROW(MPOB!$Q$3)+1), ROWS(A$2:A10))),"")} -> MPOB | Q10: {=IFERROR(INDEX(MPOB!$B$3:$B$1000, SMALL( IF((MPOB!$Q$3:$Q$1000<>"")*(MPOB!$Q$3:$Q$1000<>"Not Due"), ROW(MPOB!$Q$3:$Q$1000)-ROW(MPOB!$Q$3)+1), ROWS(A$2:A10))),"")} -> T/2026/00152 | R10: {=IFERROR(INDEX(MPOB!$D$3:$D$1000, SMALL( IF((MPOB!$Q$3:$Q$1000<>"")*(MPOB!$Q$3:$Q$1000<>"Not Due"), ROW(MPOB!$Q$3:$Q$1000)-ROW(MPOB!$Q$3)+1), ROWS(A$2:A10))),"")} -> MyFinancial | S10: {=IFERROR(INDEX(MPOB!$G$3:$G$1000, SMALL( IF((MPOB!$Q$3:$Q$1000<>"")*(MPOB!$Q$3:$Q$1000<>"Not Due"), ROW(MPOB!$Q$3:$Q$1000)-ROW(MPOB!$Q$3)+1), ROWS(A$2:A10))),"")} -> Nama User : Hanif Date : 22/1/2026 Isu : boleh minta tolong untuk sorang staff kami ni tak ingat password, dia cuba untuk set kata laluan baru tapi email tu tak dapat dapat..dari semalam dia kata..email dia : norasikin.ulkeply@mpob.gov.my | T10: {=IFERROR(INDEX(MPOB!$Q$3:$Q$1000, SMALL( IF((MPOB!$Q$3:$Q$1000<>"")*(MPOB!$Q$3:$Q$1000<>"Not Due"), ROW(MPOB!$Q$3:$Q$1000)-ROW(MPOB!$Q$3)+1), ROWS(A$2:A10)) ),"")} -> >60 Days | V10: 9 | W10: {=IFERROR(INDEX(LKTN!$E$3:$E$1000, SMALL( IF((LKTN!$Q$3:$Q$1000<>"")*(LKTN!$Q$3:$Q$1000<>"Not Due"), ROW(LKTN!$Q$3:$Q$1000)-ROW(LKTN!$Q$3)+1), ROWS(A$2:A10))),"")} | X10: {=IFERROR(INDEX(LKTN!$B$3:$B$1000, SMALL( IF((LKTN!$Q$3:$Q$1000<>"")*(LKTN!$Q$3:$Q$1000<>"Not Due"), ROW(LKTN!$Q$3:$Q$1000)-ROW(LKTN!$Q$3)+1), ROWS(A$2:A10))),"")} | Y10: {=IFERROR(INDEX(LKTN!$D$3:$D$1000, SMALL( IF((LKTN!$Q$3:$Q$1000<>"")*(LKTN!$Q$3:$Q$1000<>"Not Due"), ROW(LKTN!$Q$3:$Q$1000)-ROW(LKTN!$Q$3)+1), ROWS(A$2:A10))),"")} | Z10: {=IFERROR(INDEX(LKTN!$G$3:$G$1000, SMALL( IF((LKTN!$Q$3:$Q$1000<>"")*(LKTN!$Q$3:$Q$1000<>"Not Due"), ROW(LKTN!$Q$3:$Q$1000)-ROW(LKTN!$Q$3)+1), ROWS(A$2:A10))),"")} | AA10: {=IFERROR(INDEX(LKTN!$Q$3:$Q$1000, SMALL( IF((LKTN!$Q$3:$Q$1000<>"")*(LKTN!$Q$3:$Q$1000<>"Not Due"), ROW(LKTN!$Q$3:$Q$1000)-ROW(LKTN!$Q$3)+1), ROWS(A$2:A10)) ),"")} | AC10: 9 | AD10: {=IFERROR(INDEX(LAM!$E$3:$E$1000, SMALL( IF((LAM!$Q$3:$Q$1000<>"")*(LAM!$Q$3:$Q$1000<>"Not Due"), ROW(LAM!$Q$3:$Q$1000)-ROW(LAM!$Q$3)+1), ROWS(A$2:A10))),"")} | AE10: {=IFERROR(INDEX(LAM!$B$3:$B$1000, SMALL( IF((LAM!$Q$3:$Q$1000<>"")*(LAM!$Q$3:$Q$1000<>"Not Due"), ROW(LAM!$Q$3:$Q$1000)-ROW(LAM!$Q$3)+1), ROWS(A$2:A10))),"")} | AF10: {=IFERROR(INDEX(LAM!$D$3:$D$1000, SMALL( IF((LAM!$Q$3:$Q$1000<>"")*(LAM!$Q$3:$Q$1000<>"Not Due"), ROW(LAM!$Q$3:$Q$1000)-ROW(LAM!$Q$3)+1), ROWS(A$2:A10))),"")} | AG10: {=IFERROR(INDEX(LAM!$G$3:$G$1000, SMALL( IF((LAM!$Q$3:$Q$1000<>"")*(LAM!$Q$3:$Q$1000<>"Not Due"), ROW(LAM!$Q$3:$Q$1000)-ROW(LAM!$Q$3)+1), ROWS(A$2:A10))),"")} | AH10: {=IFERROR(INDEX(LAM!$Q$3:$Q$1000, SMALL( IF((LAM!$Q$3:$Q$1000<>"")*(LAM!$Q$3:$Q$1000<>"Not Due"), ROW(LAM!$Q$3:$Q$1000)-ROW(LAM!$Q$3)+1), ROWS(A$2:A10)) ),"")} | AJ10: 9 | AK10: {=IFERROR(INDEX(ISN!$E$3:$E$1000, SMALL( IF((ISN!$Q$3:$Q$1000<>"")*(ISN!$Q$3:$Q$1000<>"Not Due"), ROW(ISN!$Q$3:$Q$1000)-ROW(ISN!$Q$3)+1), ROWS(A$2:A10))),"")} -> ISN | AL10: {=IFERROR(INDEX(ISN!$B$3:$B$1000, SMALL( IF((ISN!$Q$3:$Q$1000<>"")*(ISN!$Q$3:$Q$1000<>"Not Due"), ROW(ISN!$Q$3:$Q$1000)-ROW(ISN!$Q$3)+1), ROWS(A$2:A10))),"")} -> T/2026/00459 | AM10: {=IFERROR(INDEX(ISN!$D$3:$D$1000, SMALL( IF((ISN!$Q$3:$Q$1000<>"")*(ISN!$Q$3:$Q$1000<>"Not Due"), ROW(ISN!$Q$3:$Q$1000)-ROW(ISN!$Q$3)+1), ROWS(A$2:A10))),"")} -> MYSTOR | AN10: {=IFERROR(INDEX(ISN!$G$3:$G$1000, SMALL( IF((ISN!$Q$3:$Q$1000<>"")*(ISN!$Q$3:$Q$1000<>"Not Due"), ROW(ISN!$Q$3:$Q$1000)-ROW(ISN!$Q$3)+1), ROWS(A$2:A10))),"")} -> PADA 30/6/2026 SAYA TELAH POS TRANSAKSI STOCK OUT DALAM SISTEM MYSTORE UNTUK TRANSAKSI PEMOHON BERTARIKH 29/6/2026 (FLOORSTOCK UNIT FISIOTERAPI) NAMUN TRANSAKSI BERNOMBOR NO. BPSI K07147 ITU TIDAK DAPAT DIPAPARKAN KETIKA SAYA MAHU MENCETAK KEWPS 8. | AO10: {=IFERROR(INDEX(ISN!$Q$3:$Q$1000, SMALL( IF((ISN!$Q$3:$Q$1000<>"")*(ISN!$Q$3:$Q$1000<>"Not Due"), ROW(ISN!$Q$3:$Q$1000)-ROW(ISN!$Q$3)+1), ROWS(A$2:A10)) ),"")} -> 1-30 Days | AQ10: 9 | AR10: {=IFERROR(INDEX(MSN!$E$3:$E$1000, SMALL( IF((MSN!$Q$3:$Q$1000<>"")*(MSN!$Q$3:$Q$1000<>"Not Due"), ROW(MSN!$Q$3:$Q$1000)-ROW(MSN!$Q$3)+1), ROWS(A$2:A10))),"")} | AS10: {=IFERROR(INDEX(MSN!$B$3:$B$1000, SMALL( IF((MSN!$Q$3:$Q$1000<>"")*(MSN!$Q$3:$Q$1000<>"Not Due"), ROW(MSN!$Q$3:$Q$1000)-ROW(MSN!$Q$3)+1), ROWS(A$2:A10))),"")} | AT10: {=IFERROR(INDEX(MSN!$D$3:$D$1000, SMALL( IF((MSN!$Q$3:$Q$1000<>"")*(MSN!$Q$3:$Q$1000<>"Not Due"), ROW(MSN!$Q$3:$Q$1000)-ROW(MSN!$Q$3)+1), ROWS(A$2:A10))),"")} | AU10: {=IFERROR(INDEX(MSN!$G$3:$G$1000, SMALL( IF((MSN!$Q$3:$Q$1000<>"")*(MSN!$Q$3:$Q$1000<>"Not Due"), ROW(MSN!$Q$3:$Q$1000)-ROW(MSN!$Q$3)+1), ROWS(A$2:A10))),"")} | AV10: {=IFERROR(INDEX(MSN!$Q$3:$Q$1000, SMALL( IF((MSN!$Q$3:$Q$1000<>"")*(MSN!$Q$3:$Q$1000<>"Not Due"), ROW(MSN!$Q$3:$Q$1000)-ROW(MSN!$Q$3)+1), ROWS(A$2:A10)) ),"")}
A11: 10 | B11: {=IFERROR(INDEX(FRIM!$E$3:$E$1000, SMALL(IF(FRIM!$Q$3:$Q$1000<>"", ROW(FRIM!$Q$3:$Q$1000)-ROW(FRIM!$Q$3)+1), ROWS(A$2:A11))),"")} -> FRIM | C11: {=IFERROR(INDEX(FRIM!$B$3:$B$1000, SMALL(IF(FRIM!$Q$3:$Q$1000<>"", ROW(FRIM!$Q$3:$Q$1000)-ROW(FRIM!$Q$3)+1), ROWS(A$2:A11))),"")} -> T/2026/00099 | D11: {=IFERROR(INDEX(FRIM!$D$3:$D$1000, SMALL(IF(FRIM!$Q$3:$Q$1000<>"", ROW(FRIM!$Q$3:$Q$1000)-ROW(FRIM!$Q$3)+1), ROWS(A$2:A11))),"")} -> URUSNIAGA PPS | E11: {=IFERROR(INDEX(FRIM!$G$3:$G$1000, SMALL(IF(FRIM!$Q$3:$Q$1000<>"", ROW(FRIM!$Q$3:$Q$1000)-ROW(FRIM!$Q$3)+1), ROWS(A$2:A11))),"")} -> W2401 24/03/2025 NURFAIEZAH BT. MAZERI MOHON PENAMBAIKAN UNTUK ADD ITEM DI MYURUSNIAGA | F11: {=IFERROR(INDEX(FRIM!$Q$3:$Q$1000, SMALL(IF(FRIM!$Q$3:$Q$1000<>"", ROW(FRIM!$Q$3:$Q$1000)-ROW(FRIM!$Q$3)+1), ROWS(A$2:A11))),"")} -> >60 Days | H11: 10 | I11: {=IFERROR(INDEX(MTIB!$E$3:$E$1000, SMALL( IF((MTIB!$Q$3:$Q$1000<>"")*(MTIB!$Q$3:$Q$1000<>"Not Due"), ROW(MTIB!$Q$3:$Q$1000)-ROW(MTIB!$Q$3)+1), ROWS(A$2:A11))),"")} -> MTIB | J11: {=IFERROR(INDEX(MTIB!$B$3:$B$1000, SMALL( IF((MTIB!$Q$3:$Q$1000<>"")*(MTIB!$Q$3:$Q$1000<>"Not Due"), ROW(MTIB!$Q$3:$Q$1000)-ROW(MTIB!$Q$3)+1), ROWS(A$2:A11))),"")} -> T/2026/00332 | K11: {=IFERROR(INDEX(MTIB!$D$3:$D$1000, SMALL( IF((MTIB!$Q$3:$Q$1000<>"")*(MTIB!$Q$3:$Q$1000<>"Not Due"), ROW(MTIB!$Q$3:$Q$1000)-ROW(MTIB!$Q$3)+1), ROWS(A$2:A11))),"")} -> MyPanjar | L11: {=IFERROR(INDEX(MTIB!$G$3:$G$1000, SMALL( IF((MTIB!$Q$3:$Q$1000<>"")*(MTIB!$Q$3:$Q$1000<>"Not Due"), ROW(MTIB!$Q$3:$Q$1000)-ROW(MTIB!$Q$3)+1), ROWS(A$2:A11))),"")} -> Pegawai Pengesah HR (Patmah) tidak dapat membuat pengesahan perubatan dalam sistem MyPanjar. Pengadu: Suhani Hassan | M11: {=IFERROR(INDEX(MTIB!$Q$3:$Q$1000, SMALL( IF((MTIB!$Q$3:$Q$1000<>"")*(MTIB!$Q$3:$Q$1000<>"Not Due"), ROW(MTIB!$Q$3:$Q$1000)-ROW(MTIB!$Q$3)+1), ROWS(A$2:A11)) ),"")} -> 31-60 Days | O11: 10 | P11: {=IFERROR(INDEX(MPOB!$E$3:$E$1000, SMALL( IF((MPOB!$Q$3:$Q$1000<>"")*(MPOB!$Q$3:$Q$1000<>"Not Due"), ROW(MPOB!$Q$3:$Q$1000)-ROW(MPOB!$Q$3)+1), ROWS(A$2:A11))),"")} -> MPOB | Q11: {=IFERROR(INDEX(MPOB!$B$3:$B$1000, SMALL( IF((MPOB!$Q$3:$Q$1000<>"")*(MPOB!$Q$3:$Q$1000<>"Not Due"), ROW(MPOB!$Q$3:$Q$1000)-ROW(MPOB!$Q$3)+1), ROWS(A$2:A11))),"")} -> T/2026/00160 | R11: {=IFERROR(INDEX(MPOB!$D$3:$D$1000, SMALL( IF((MPOB!$Q$3:$Q$1000<>"")*(MPOB!$Q$3:$Q$1000<>"Not Due"), ROW(MPOB!$Q$3:$Q$1000)-ROW(MPOB!$Q$3)+1), ROWS(A$2:A11))),"")} -> MyAsset | S11: {=IFERROR(INDEX(MPOB!$G$3:$G$1000, SMALL( IF((MPOB!$Q$3:$Q$1000<>"")*(MPOB!$Q$3:$Q$1000<>"Not Due"), ROW(MPOB!$Q$3:$Q$1000)-ROW(MPOB!$Q$3)+1), ROWS(A$2:A11))),"")} -> Nama User : Myra Date : 27/1/2026 Isu : Terdapat 40 aset yg telah dihapuskan tetapi GL tak update (reverse) pada 2024. Mohon aktifkan semula aset. | T11: {=IFERROR(INDEX(MPOB!$Q$3:$Q$1000, SMALL( IF((MPOB!$Q$3:$Q$1000<>"")*(MPOB!$Q$3:$Q$1000<>"Not Due"), ROW(MPOB!$Q$3:$Q$1000)-ROW(MPOB!$Q$3)+1), ROWS(A$2:A11)) ),"")} -> >60 Days | V11: 10 | W11: {=IFERROR(INDEX(LKTN!$E$3:$E$1000, SMALL( IF((LKTN!$Q$3:$Q$1000<>"")*(LKTN!$Q$3:$Q$1000<>"Not Due"), ROW(LKTN!$Q$3:$Q$1000)-ROW(LKTN!$Q$3)+1), ROWS(A$2:A11))),"")} | X11: {=IFERROR(INDEX(LKTN!$B$3:$B$1000, SMALL( IF((LKTN!$Q$3:$Q$1000<>"")*(LKTN!$Q$3:$Q$1000<>"Not Due"), ROW(LKTN!$Q$3:$Q$1000)-ROW(LKTN!$Q$3)+1), ROWS(A$2:A11))),"")} | Y11: {=IFERROR(INDEX(LKTN!$D$3:$D$1000, SMALL( IF((LKTN!$Q$3:$Q$1000<>"")*(LKTN!$Q$3:$Q$1000<>"Not Due"), ROW(LKTN!$Q$3:$Q$1000)-ROW(LKTN!$Q$3)+1), ROWS(A$2:A11))),"")} | Z11: {=IFERROR(INDEX(LKTN!$G$3:$G$1000, SMALL( IF((LKTN!$Q$3:$Q$1000<>"")*(LKTN!$Q$3:$Q$1000<>"Not Due"), ROW(LKTN!$Q$3:$Q$1000)-ROW(LKTN!$Q$3)+1), ROWS(A$2:A11))),"")} | AA11: {=IFERROR(INDEX(LKTN!$Q$3:$Q$1000, SMALL( IF((LKTN!$Q$3:$Q$1000<>"")*(LKTN!$Q$3:$Q$1000<>"Not Due"), ROW(LKTN!$Q$3:$Q$1000)-ROW(LKTN!$Q$3)+1), ROWS(A$2:A11)) ),"")} | AJ11: 10 | AK11: {=IFERROR(INDEX(ISN!$E$3:$E$1000, SMALL( IF((ISN!$Q$3:$Q$1000<>"")*(ISN!$Q$3:$Q$1000<>"Not Due"), ROW(ISN!$Q$3:$Q$1000)-ROW(ISN!$Q$3)+1), ROWS(A$2:A11))),"")} | AL11: {=IFERROR(INDEX(ISN!$B$3:$B$1000, SMALL( IF((ISN!$Q$3:$Q$1000<>"")*(ISN!$Q$3:$Q$1000<>"Not Due"), ROW(ISN!$Q$3:$Q$1000)-ROW(ISN!$Q$3)+1), ROWS(A$2:A11))),"")} | AM11: {=IFERROR(INDEX(ISN!$D$3:$D$1000, SMALL( IF((ISN!$Q$3:$Q$1000<>"")*(ISN!$Q$3:$Q$1000<>"Not Due"), ROW(ISN!$Q$3:$Q$1000)-ROW(ISN!$Q$3)+1), ROWS(A$2:A11))),"")} | AN11: {=IFERROR(INDEX(ISN!$G$3:$G$1000, SMALL( IF((ISN!$Q$3:$Q$1000<>"")*(ISN!$Q$3:$Q$1000<>"Not Due"), ROW(ISN!$Q$3:$Q$1000)-ROW(ISN!$Q$3)+1), ROWS(A$2:A11))),"")} | AO11: {=IFERROR(INDEX(ISN!$Q$3:$Q$1000, SMALL( IF((ISN!$Q$3:$Q$1000<>"")*(ISN!$Q$3:$Q$1000<>"Not Due"), ROW(ISN!$Q$3:$Q$1000)-ROW(ISN!$Q$3)+1), ROWS(A$2:A11)) ),"")} | AQ11: 10 | AR11: {=IFERROR(INDEX(MSN!$E$3:$E$1000, SMALL( IF((MSN!$Q$3:$Q$1000<>"")*(MSN!$Q$3:$Q$1000<>"Not Due"), ROW(MSN!$Q$3:$Q$1000)-ROW(MSN!$Q$3)+1), ROWS(A$2:A11))),"")} | AS11: {=IFERROR(INDEX(MSN!$B$3:$B$1000, SMALL( IF((MSN!$Q$3:$Q$1000<>"")*(MSN!$Q$3:$Q$1000<>"Not Due"), ROW(MSN!$Q$3:$Q$1000)-ROW(MSN!$Q$3)+1), ROWS(A$2:A11))),"")} | AT11: {=IFERROR(INDEX(MSN!$D$3:$D$1000, SMALL( IF((MSN!$Q$3:$Q$1000<>"")*(MSN!$Q$3:$Q$1000<>"Not Due"), ROW(MSN!$Q$3:$Q$1000)-ROW(MSN!$Q$3)+1), ROWS(A$2:A11))),"")} | AU11: {=IFERROR(INDEX(MSN!$G$3:$G$1000, SMALL( IF((MSN!$Q$3:$Q$1000<>"")*(MSN!$Q$3:$Q$1000<>"Not Due"), ROW(MSN!$Q$3:$Q$1000)-ROW(MSN!$Q$3)+1), ROWS(A$2:A11))),"")} | AV11: {=IFERROR(INDEX(MSN!$Q$3:$Q$1000, SMALL( IF((MSN!$Q$3:$Q$1000<>"")*(MSN!$Q$3:$Q$1000<>"Not Due"), ROW(MSN!$Q$3:$Q$1000)-ROW(MSN!$Q$3)+1), ROWS(A$2:A11)) ),"")}
A12: 11 | B12: {=IFERROR(INDEX(FRIM!$E$3:$E$1000, SMALL(IF(FRIM!$Q$3:$Q$1000<>"", ROW(FRIM!$Q$3:$Q$1000)-ROW(FRIM!$Q$3)+1), ROWS(A$2:A12))),"")} -> FRIM | C12: {=IFERROR(INDEX(FRIM!$B$3:$B$1000, SMALL(IF(FRIM!$Q$3:$Q$1000<>"", ROW(FRIM!$Q$3:$Q$1000)-ROW(FRIM!$Q$3)+1), ROWS(A$2:A12))),"")} -> T/2026/00102 | D12: {=IFERROR(INDEX(FRIM!$D$3:$D$1000, SMALL(IF(FRIM!$Q$3:$Q$1000<>"", ROW(FRIM!$Q$3:$Q$1000)-ROW(FRIM!$Q$3)+1), ROWS(A$2:A12))),"")} -> QUERY | E12: {=IFERROR(INDEX(FRIM!$G$3:$G$1000, SMALL(IF(FRIM!$Q$3:$Q$1000<>"", ROW(FRIM!$Q$3:$Q$1000)-ROW(FRIM!$Q$3)+1), ROWS(A$2:A12))),"")} -> W2449 28/10/2025 NAJWA NAFIAH BINTI FAUZI MOHON SEMAKAN MODUL PERBELANJAAN IKUT PUSAT KOS DI MYQUERY TIDAK BOLEH DIAKSES. LAPORAN PERUNTUKAN DAN PERBELANJAAN MENGIKUT PUSAT KOS TIDAK KELUAR. SEBELUM NI BOLEH AKSES UNTUK DAPAT KAN LAPORAN. MODUL INI PERLU UNTUK PENYEDIAAN PELAPORAN KEWANGAN PROJEK. CONTOH REPORT SEPERTI LAMPIRAN. | F12: {=IFERROR(INDEX(FRIM!$Q$3:$Q$1000, SMALL(IF(FRIM!$Q$3:$Q$1000<>"", ROW(FRIM!$Q$3:$Q$1000)-ROW(FRIM!$Q$3)+1), ROWS(A$2:A12))),"")} -> >60 Days | H12: 11 | I12: {=IFERROR(INDEX(MTIB!$E$3:$E$1000, SMALL( IF((MTIB!$Q$3:$Q$1000<>"")*(MTIB!$Q$3:$Q$1000<>"Not Due"), ROW(MTIB!$Q$3:$Q$1000)-ROW(MTIB!$Q$3)+1), ROWS(A$2:A12))),"")} -> MTIB | J12: {=IFERROR(INDEX(MTIB!$B$3:$B$1000, SMALL( IF((MTIB!$Q$3:$Q$1000<>"")*(MTIB!$Q$3:$Q$1000<>"Not Due"), ROW(MTIB!$Q$3:$Q$1000)-ROW(MTIB!$Q$3)+1), ROWS(A$2:A12))),"")} -> T/2026/00337 | K12: {=IFERROR(INDEX(MTIB!$D$3:$D$1000, SMALL( IF((MTIB!$Q$3:$Q$1000<>"")*(MTIB!$Q$3:$Q$1000<>"Not Due"), ROW(MTIB!$Q$3:$Q$1000)-ROW(MTIB!$Q$3)+1), ROWS(A$2:A12))),"")} -> MYFINANCIAL | L12: {=IFERROR(INDEX(MTIB!$G$3:$G$1000, SMALL( IF((MTIB!$Q$3:$Q$1000<>"")*(MTIB!$Q$3:$Q$1000<>"Not Due"), ROW(MTIB!$Q$3:$Q$1000)-ROW(MTIB!$Q$3)+1), ROWS(A$2:A12))),"")} -> Mohon laksanakan MyFinancial Client Nama: SHARIFAH SUAIRAH BINTI SAYED KAMARUZAMAN No Kad Pengenalan: 950304-08-5330 No Pekerja: 1233 | M12: {=IFERROR(INDEX(MTIB!$Q$3:$Q$1000, SMALL( IF((MTIB!$Q$3:$Q$1000<>"")*(MTIB!$Q$3:$Q$1000<>"Not Due"), ROW(MTIB!$Q$3:$Q$1000)-ROW(MTIB!$Q$3)+1), ROWS(A$2:A12)) ),"")} -> 31-60 Days | O12: 11 | P12: {=IFERROR(INDEX(MPOB!$E$3:$E$1000, SMALL( IF((MPOB!$Q$3:$Q$1000<>"")*(MPOB!$Q$3:$Q$1000<>"Not Due"), ROW(MPOB!$Q$3:$Q$1000)-ROW(MPOB!$Q$3)+1), ROWS(A$2:A12))),"")} -> MPOB | Q12: {=IFERROR(INDEX(MPOB!$B$3:$B$1000, SMALL( IF((MPOB!$Q$3:$Q$1000<>"")*(MPOB!$Q$3:$Q$1000<>"Not Due"), ROW(MPOB!$Q$3:$Q$1000)-ROW(MPOB!$Q$3)+1), ROWS(A$2:A12))),"")} -> T/2026/00161 | R12: {=IFERROR(INDEX(MPOB!$D$3:$D$1000, SMALL( IF((MPOB!$Q$3:$Q$1000<>"")*(MPOB!$Q$3:$Q$1000<>"Not Due"), ROW(MPOB!$Q$3:$Q$1000)-ROW(MPOB!$Q$3)+1), ROWS(A$2:A12))),"")} -> MyFinancial | S12: {=IFERROR(INDEX(MPOB!$G$3:$G$1000, SMALL( IF((MPOB!$Q$3:$Q$1000<>"")*(MPOB!$Q$3:$Q$1000<>"Not Due"), ROW(MPOB!$Q$3:$Q$1000)-ROW(MPOB!$Q$3)+1), ROWS(A$2:A12))),"")} -> Nama User : Fitrah Date : 27/01/2026 Isu : Baucar tidak dijumpai. No Baucar VOPOB/0126/02611 baucar tu dh wujud dekat baucar yg tlah dipos tpi dekat kelulusan baucar dye tk kluar en hasrol tk dpt nk lulus kn | T12: {=IFERROR(INDEX(MPOB!$Q$3:$Q$1000, SMALL( IF((MPOB!$Q$3:$Q$1000<>"")*(MPOB!$Q$3:$Q$1000<>"Not Due"), ROW(MPOB!$Q$3:$Q$1000)-ROW(MPOB!$Q$3)+1), ROWS(A$2:A12)) ),"")} -> >60 Days | V12: 11 | W12: {=IFERROR(INDEX(LKTN!$E$3:$E$1000, SMALL( IF((LKTN!$Q$3:$Q$1000<>"")*(LKTN!$Q$3:$Q$1000<>"Not Due"), ROW(LKTN!$Q$3:$Q$1000)-ROW(LKTN!$Q$3)+1), ROWS(A$2:A12))),"")} | X12: {=IFERROR(INDEX(LKTN!$B$3:$B$1000, SMALL( IF((LKTN!$Q$3:$Q$1000<>"")*(LKTN!$Q$3:$Q$1000<>"Not Due"), ROW(LKTN!$Q$3:$Q$1000)-ROW(LKTN!$Q$3)+1), ROWS(A$2:A12))),"")} | Y12: {=IFERROR(INDEX(LKTN!$D$3:$D$1000, SMALL( IF((LKTN!$Q$3:$Q$1000<>"")*(LKTN!$Q$3:$Q$1000<>"Not Due"), ROW(LKTN!$Q$3:$Q$1000)-ROW(LKTN!$Q$3)+1), ROWS(A$2:A12))),"")} | Z12: {=IFERROR(INDEX(LKTN!$G$3:$G$1000, SMALL( IF((LKTN!$Q$3:$Q$1000<>"")*(LKTN!$Q$3:$Q$1000<>"Not Due"), ROW(LKTN!$Q$3:$Q$1000)-ROW(LKTN!$Q$3)+1), ROWS(A$2:A12))),"")} | AA12: {=IFERROR(INDEX(LKTN!$Q$3:$Q$1000, SMALL( IF((LKTN!$Q$3:$Q$1000<>"")*(LKTN!$Q$3:$Q$1000<>"Not Due"), ROW(LKTN!$Q$3:$Q$1000)-ROW(LKTN!$Q$3)+1), ROWS(A$2:A12)) ),"")} | AJ12: 11 | AK12: {=IFERROR(INDEX(ISN!$E$3:$E$1000, SMALL( IF((ISN!$Q$3:$Q$1000<>"")*(ISN!$Q$3:$Q$1000<>"Not Due"), ROW(ISN!$Q$3:$Q$1000)-ROW(ISN!$Q$3)+1), ROWS(A$2:A12))),"")} | AL12: {=IFERROR(INDEX(ISN!$B$3:$B$1000, SMALL( IF((ISN!$Q$3:$Q$1000<>"")*(ISN!$Q$3:$Q$1000<>"Not Due"), ROW(ISN!$Q$3:$Q$1000)-ROW(ISN!$Q$3)+1), ROWS(A$2:A12))),"")} | AM12: {=IFERROR(INDEX(ISN!$D$3:$D$1000, SMALL( IF((ISN!$Q$3:$Q$1000<>"")*(ISN!$Q$3:$Q$1000<>"Not Due"), ROW(ISN!$Q$3:$Q$1000)-ROW(ISN!$Q$3)+1), ROWS(A$2:A12))),"")} | AN12: {=IFERROR(INDEX(ISN!$G$3:$G$1000, SMALL( IF((ISN!$Q$3:$Q$1000<>"")*(ISN!$Q$3:$Q$1000<>"Not Due"), ROW(ISN!$Q$3:$Q$1000)-ROW(ISN!$Q$3)+1), ROWS(A$2:A12))),"")} | AO12: {=IFERROR(INDEX(ISN!$Q$3:$Q$1000, SMALL( IF((ISN!$Q$3:$Q$1000<>"")*(ISN!$Q$3:$Q$1000<>"Not Due"), ROW(ISN!$Q$3:$Q$1000)-ROW(ISN!$Q$3)+1), ROWS(A$2:A12)) ),"")} | AQ12: 11 | AR12: {=IFERROR(INDEX(MSN!$E$3:$E$1000, SMALL( IF((MSN!$Q$3:$Q$1000<>"")*(MSN!$Q$3:$Q$1000<>"Not Due"), ROW(MSN!$Q$3:$Q$1000)-ROW(MSN!$Q$3)+1), ROWS(A$2:A12))),"")} | AS12: {=IFERROR(INDEX(MSN!$B$3:$B$1000, SMALL( IF((MSN!$Q$3:$Q$1000<>"")*(MSN!$Q$3:$Q$1000<>"Not Due"), ROW(MSN!$Q$3:$Q$1000)-ROW(MSN!$Q$3)+1), ROWS(A$2:A12))),"")} | AT12: {=IFERROR(INDEX(MSN!$D$3:$D$1000, SMALL( IF((MSN!$Q$3:$Q$1000<>"")*(MSN!$Q$3:$Q$1000<>"Not Due"), ROW(MSN!$Q$3:$Q$1000)-ROW(MSN!$Q$3)+1), ROWS(A$2:A12))),"")} | AU12: {=IFERROR(INDEX(MSN!$G$3:$G$1000, SMALL( IF((MSN!$Q$3:$Q$1000<>"")*(MSN!$Q$3:$Q$1000<>"Not Due"), ROW(MSN!$Q$3:$Q$1000)-ROW(MSN!$Q$3)+1), ROWS(A$2:A12))),"")} | AV12: {=IFERROR(INDEX(MSN!$Q$3:$Q$1000, SMALL( IF((MSN!$Q$3:$Q$1000<>"")*(MSN!$Q$3:$Q$1000<>"Not Due"), ROW(MSN!$Q$3:$Q$1000)-ROW(MSN!$Q$3)+1), ROWS(A$2:A12)) ),"")}
A13: 12 | B13: {=IFERROR(INDEX(FRIM!$E$3:$E$1000, SMALL(IF(FRIM!$Q$3:$Q$1000<>"", ROW(FRIM!$Q$3:$Q$1000)-ROW(FRIM!$Q$3)+1), ROWS(A$2:A13))),"")} -> FRIM | C13: {=IFERROR(INDEX(FRIM!$B$3:$B$1000, SMALL(IF(FRIM!$Q$3:$Q$1000<>"", ROW(FRIM!$Q$3:$Q$1000)-ROW(FRIM!$Q$3)+1), ROWS(A$2:A13))),"")} -> T/2026/00103 | D13: {=IFERROR(INDEX(FRIM!$D$3:$D$1000, SMALL(IF(FRIM!$Q$3:$Q$1000<>"", ROW(FRIM!$Q$3:$Q$1000)-ROW(FRIM!$Q$3)+1), ROWS(A$2:A13))),"")} -> MYFINANCIAL CLIENT | E13: {=IFERROR(INDEX(FRIM!$G$3:$G$1000, SMALL(IF(FRIM!$Q$3:$Q$1000<>"", ROW(FRIM!$Q$3:$Q$1000)-ROW(FRIM!$Q$3)+1), ROWS(A$2:A13))),"")} -> W2453 04/11/2025 NAJWA NAFIAH BINTI FAUZI MOHON SEMAKAN BAGI MODUL PENGELUARAN TUNAI - PENYATA PENYESUAIAN BANK - STATUS TUNAI MASUK - SENARAI CEK BELUM DIKREDITKAN. SEMAKAN MENDAPATI SENARAI CEK BELUM DIKREDITKAN TIDAK SAMA DENGAN CEK-CEK BELUM DIKREDITKAN (NOTA 01) DI DALAM LAPORAN PENYATA PENYESUAIAN BANK. | F13: {=IFERROR(INDEX(FRIM!$Q$3:$Q$1000, SMALL(IF(FRIM!$Q$3:$Q$1000<>"", ROW(FRIM!$Q$3:$Q$1000)-ROW(FRIM!$Q$3)+1), ROWS(A$2:A13))),"")} -> >60 Days | H13: 12 | I13: {=IFERROR(INDEX(MTIB!$E$3:$E$1000, SMALL( IF((MTIB!$Q$3:$Q$1000<>"")*(MTIB!$Q$3:$Q$1000<>"Not Due"), ROW(MTIB!$Q$3:$Q$1000)-ROW(MTIB!$Q$3)+1), ROWS(A$2:A13))),"")} -> MTIB | J13: {=IFERROR(INDEX(MTIB!$B$3:$B$1000, SMALL( IF((MTIB!$Q$3:$Q$1000<>"")*(MTIB!$Q$3:$Q$1000<>"Not Due"), ROW(MTIB!$Q$3:$Q$1000)-ROW(MTIB!$Q$3)+1), ROWS(A$2:A13))),"")} -> T/2026/00354 | K13: {=IFERROR(INDEX(MTIB!$D$3:$D$1000, SMALL( IF((MTIB!$Q$3:$Q$1000<>"")*(MTIB!$Q$3:$Q$1000<>"Not Due"), ROW(MTIB!$Q$3:$Q$1000)-ROW(MTIB!$Q$3)+1), ROWS(A$2:A13))),"")} -> MYINVESTMENT | L13: {=IFERROR(INDEX(MTIB!$G$3:$G$1000, SMALL( IF((MTIB!$Q$3:$Q$1000<>"")*(MTIB!$Q$3:$Q$1000<>"Not Due"), ROW(MTIB!$Q$3:$Q$1000)-ROW(MTIB!$Q$3)+1), ROWS(A$2:A13))),"")} -> 1. Data di MYINVESTMENT tidak lengkap. 2. Pengguna pos data dua kali. Pengadu: Norhayati Muhamad | M13: {=IFERROR(INDEX(MTIB!$Q$3:$Q$1000, SMALL( IF((MTIB!$Q$3:$Q$1000<>"")*(MTIB!$Q$3:$Q$1000<>"Not Due"), ROW(MTIB!$Q$3:$Q$1000)-ROW(MTIB!$Q$3)+1), ROWS(A$2:A13)) ),"")} -> 31-60 Days | O13: 12 | P13: {=IFERROR(INDEX(MPOB!$E$3:$E$1000, SMALL( IF((MPOB!$Q$3:$Q$1000<>"")*(MPOB!$Q$3:$Q$1000<>"Not Due"), ROW(MPOB!$Q$3:$Q$1000)-ROW(MPOB!$Q$3)+1), ROWS(A$2:A13))),"")} -> MPOB | Q13: {=IFERROR(INDEX(MPOB!$B$3:$B$1000, SMALL( IF((MPOB!$Q$3:$Q$1000<>"")*(MPOB!$Q$3:$Q$1000<>"Not Due"), ROW(MPOB!$Q$3:$Q$1000)-ROW(MPOB!$Q$3)+1), ROWS(A$2:A13))),"")} -> T/2026/00162 | R13: {=IFERROR(INDEX(MPOB!$D$3:$D$1000, SMALL( IF((MPOB!$Q$3:$Q$1000<>"")*(MPOB!$Q$3:$Q$1000<>"Not Due"), ROW(MPOB!$Q$3:$Q$1000)-ROW(MPOB!$Q$3)+1), ROWS(A$2:A13))),"")} -> MyProcurement | S13: {=IFERROR(INDEX(MPOB!$G$3:$G$1000, SMALL( IF((MPOB!$Q$3:$Q$1000<>"")*(MPOB!$Q$3:$Q$1000<>"Not Due"), ROW(MPOB!$Q$3:$Q$1000)-ROW(MPOB!$Q$3)+1), ROWS(A$2:A13))),"")} -> Nama User : AsAlya Date : 28/01/2026 Isu : sy salah terbatalkan Ro ni boleh reverse ke ye? No. Permohonan : R260202 | T13: {=IFERROR(INDEX(MPOB!$Q$3:$Q$1000, SMALL( IF((MPOB!$Q$3:$Q$1000<>"")*(MPOB!$Q$3:$Q$1000<>"Not Due"), ROW(MPOB!$Q$3:$Q$1000)-ROW(MPOB!$Q$3)+1), ROWS(A$2:A13)) ),"")} -> >60 Days | V13: 12 | W13: {=IFERROR(INDEX(LKTN!$E$3:$E$1000, SMALL( IF((LKTN!$Q$3:$Q$1000<>"")*(LKTN!$Q$3:$Q$1000<>"Not Due"), ROW(LKTN!$Q$3:$Q$1000)-ROW(LKTN!$Q$3)+1), ROWS(A$2:A13))),"")} | X13: {=IFERROR(INDEX(LKTN!$B$3:$B$1000, SMALL( IF((LKTN!$Q$3:$Q$1000<>"")*(LKTN!$Q$3:$Q$1000<>"Not Due"), ROW(LKTN!$Q$3:$Q$1000)-ROW(LKTN!$Q$3)+1), ROWS(A$2:A13))),"")} | Y13: {=IFERROR(INDEX(LKTN!$D$3:$D$1000, SMALL( IF((LKTN!$Q$3:$Q$1000<>"")*(LKTN!$Q$3:$Q$1000<>"Not Due"), ROW(LKTN!$Q$3:$Q$1000)-ROW(LKTN!$Q$3)+1), ROWS(A$2:A13))),"")} | Z13: {=IFERROR(INDEX(LKTN!$G$3:$G$1000, SMALL( IF((LKTN!$Q$3:$Q$1000<>"")*(LKTN!$Q$3:$Q$1000<>"Not Due"), ROW(LKTN!$Q$3:$Q$1000)-ROW(LKTN!$Q$3)+1), ROWS(A$2:A13))),"")} | AA13: {=IFERROR(INDEX(LKTN!$Q$3:$Q$1000, SMALL( IF((LKTN!$Q$3:$Q$1000<>"")*(LKTN!$Q$3:$Q$1000<>"Not Due"), ROW(LKTN!$Q$3:$Q$1000)-ROW(LKTN!$Q$3)+1), ROWS(A$2:A13)) ),"")} | AJ13: 12 | AK13: {=IFERROR(INDEX(ISN!$E$3:$E$1000, SMALL( IF((ISN!$Q$3:$Q$1000<>"")*(ISN!$Q$3:$Q$1000<>"Not Due"), ROW(ISN!$Q$3:$Q$1000)-ROW(ISN!$Q$3)+1), ROWS(A$2:A13))),"")} | AL13: {=IFERROR(INDEX(ISN!$B$3:$B$1000, SMALL( IF((ISN!$Q$3:$Q$1000<>"")*(ISN!$Q$3:$Q$1000<>"Not Due"), ROW(ISN!$Q$3:$Q$1000)-ROW(ISN!$Q$3)+1), ROWS(A$2:A13))),"")} | AM13: {=IFERROR(INDEX(ISN!$D$3:$D$1000, SMALL( IF((ISN!$Q$3:$Q$1000<>"")*(ISN!$Q$3:$Q$1000<>"Not Due"), ROW(ISN!$Q$3:$Q$1000)-ROW(ISN!$Q$3)+1), ROWS(A$2:A13))),"")} | AN13: {=IFERROR(INDEX(ISN!$G$3:$G$1000, SMALL( IF((ISN!$Q$3:$Q$1000<>"")*(ISN!$Q$3:$Q$1000<>"Not Due"), ROW(ISN!$Q$3:$Q$1000)-ROW(ISN!$Q$3)+1), ROWS(A$2:A13))),"")} | AO13: {=IFERROR(INDEX(ISN!$Q$3:$Q$1000, SMALL( IF((ISN!$Q$3:$Q$1000<>"")*(ISN!$Q$3:$Q$1000<>"Not Due"), ROW(ISN!$Q$3:$Q$1000)-ROW(ISN!$Q$3)+1), ROWS(A$2:A13)) ),"")} | AQ13: 12 | AR13: {=IFERROR(INDEX(MSN!$E$3:$E$1000, SMALL( IF((MSN!$Q$3:$Q$1000<>"")*(MSN!$Q$3:$Q$1000<>"Not Due"), ROW(MSN!$Q$3:$Q$1000)-ROW(MSN!$Q$3)+1), ROWS(A$2:A13))),"")} | AS13: {=IFERROR(INDEX(MSN!$B$3:$B$1000, SMALL( IF((MSN!$Q$3:$Q$1000<>"")*(MSN!$Q$3:$Q$1000<>"Not Due"), ROW(MSN!$Q$3:$Q$1000)-ROW(MSN!$Q$3)+1), ROWS(A$2:A13))),"")} | AT13: {=IFERROR(INDEX(MSN!$D$3:$D$1000, SMALL( IF((MSN!$Q$3:$Q$1000<>"")*(MSN!$Q$3:$Q$1000<>"Not Due"), ROW(MSN!$Q$3:$Q$1000)-ROW(MSN!$Q$3)+1), ROWS(A$2:A13))),"")} | AU13: {=IFERROR(INDEX(MSN!$G$3:$G$1000, SMALL( IF((MSN!$Q$3:$Q$1000<>"")*(MSN!$Q$3:$Q$1000<>"Not Due"), ROW(MSN!$Q$3:$Q$1000)-ROW(MSN!$Q$3)+1), ROWS(A$2:A13))),"")} | AV13: {=IFERROR(INDEX(MSN!$Q$3:$Q$1000, SMALL( IF((MSN!$Q$3:$Q$1000<>"")*(MSN!$Q$3:$Q$1000<>"Not Due"), ROW(MSN!$Q$3:$Q$1000)-ROW(MSN!$Q$3)+1), ROWS(A$2:A13)) ),"")}
A14: 13 | B14: {=IFERROR(INDEX(FRIM!$E$3:$E$1000, SMALL(IF(FRIM!$Q$3:$Q$1000<>"", ROW(FRIM!$Q$3:$Q$1000)-ROW(FRIM!$Q$3)+1), ROWS(A$2:A14))),"")} -> FRIM | C14: {=IFERROR(INDEX(FRIM!$B$3:$B$1000, SMALL(IF(FRIM!$Q$3:$Q$1000<>"", ROW(FRIM!$Q$3:$Q$1000)-ROW(FRIM!$Q$3)+1), ROWS(A$2:A14))),"")} -> T/2026/00108 | D14: {=IFERROR(INDEX(FRIM!$D$3:$D$1000, SMALL(IF(FRIM!$Q$3:$Q$1000<>"", ROW(FRIM!$Q$3:$Q$1000)-ROW(FRIM!$Q$3)+1), ROWS(A$2:A14))),"")} -> MYPROCUREMENT | E14: {=IFERROR(INDEX(FRIM!$G$3:$G$1000, SMALL(IF(FRIM!$Q$3:$Q$1000<>"", ROW(FRIM!$Q$3:$Q$1000)-ROW(FRIM!$Q$3)+1), ROWS(A$2:A14))),"")} -> W2470 04/12/2025 AZMEI B. MARZUKI DARI LUAR SYARIKAT TAK BOLEH MASUKKAN KOD BIDANG. KELUAR ERROR. TAPI SAYA BUAT DI PC SAYA BOLEH KEYIN KOD BIDANG TIADA MASALAH. | F14: {=IFERROR(INDEX(FRIM!$Q$3:$Q$1000, SMALL(IF(FRIM!$Q$3:$Q$1000<>"", ROW(FRIM!$Q$3:$Q$1000)-ROW(FRIM!$Q$3)+1), ROWS(A$2:A14))),"")} -> >60 Days | H14: 13 | I14: {=IFERROR(INDEX(MTIB!$E$3:$E$1000, SMALL( IF((MTIB!$Q$3:$Q$1000<>"")*(MTIB!$Q$3:$Q$1000<>"Not Due"), ROW(MTIB!$Q$3:$Q$1000)-ROW(MTIB!$Q$3)+1), ROWS(A$2:A14))),"")} -> MTIB | J14: {=IFERROR(INDEX(MTIB!$B$3:$B$1000, SMALL( IF((MTIB!$Q$3:$Q$1000<>"")*(MTIB!$Q$3:$Q$1000<>"Not Due"), ROW(MTIB!$Q$3:$Q$1000)-ROW(MTIB!$Q$3)+1), ROWS(A$2:A14))),"")} -> T/2026/00355 | K14: {=IFERROR(INDEX(MTIB!$D$3:$D$1000, SMALL( IF((MTIB!$Q$3:$Q$1000<>"")*(MTIB!$Q$3:$Q$1000<>"Not Due"), ROW(MTIB!$Q$3:$Q$1000)-ROW(MTIB!$Q$3)+1), ROWS(A$2:A14))),"")} -> MYFINANCIAL | L14: {=IFERROR(INDEX(MTIB!$G$3:$G$1000, SMALL( IF((MTIB!$Q$3:$Q$1000<>"")*(MTIB!$Q$3:$Q$1000<>"Not Due"), ROW(MTIB!$Q$3:$Q$1000)-ROW(MTIB!$Q$3)+1), ROWS(A$2:A14))),"")} -> Untuk makluman tuan, dua akaun ini perlu akses kepada MyFinancial Client Nama: Shah Badri Mohd Nor IC: 891214015729 Nama: Nur Adila Badrol Hisham IC: 960414085496 Untuk makluman, akses melalui MySecurity telah dibuat. | M14: {=IFERROR(INDEX(MTIB!$Q$3:$Q$1000, SMALL( IF((MTIB!$Q$3:$Q$1000<>"")*(MTIB!$Q$3:$Q$1000<>"Not Due"), ROW(MTIB!$Q$3:$Q$1000)-ROW(MTIB!$Q$3)+1), ROWS(A$2:A14)) ),"")} -> 31-60 Days | O14: 13 | P14: {=IFERROR(INDEX(MPOB!$E$3:$E$1000, SMALL( IF((MPOB!$Q$3:$Q$1000<>"")*(MPOB!$Q$3:$Q$1000<>"Not Due"), ROW(MPOB!$Q$3:$Q$1000)-ROW(MPOB!$Q$3)+1), ROWS(A$2:A14))),"")} -> MPOB | Q14: {=IFERROR(INDEX(MPOB!$B$3:$B$1000, SMALL( IF((MPOB!$Q$3:$Q$1000<>"")*(MPOB!$Q$3:$Q$1000<>"Not Due"), ROW(MPOB!$Q$3:$Q$1000)-ROW(MPOB!$Q$3)+1), ROWS(A$2:A14))),"")} -> T/2026/00167 | R14: {=IFERROR(INDEX(MPOB!$D$3:$D$1000, SMALL( IF((MPOB!$Q$3:$Q$1000<>"")*(MPOB!$Q$3:$Q$1000<>"Not Due"), ROW(MPOB!$Q$3:$Q$1000)-ROW(MPOB!$Q$3)+1), ROWS(A$2:A14))),"")} -> MyAsset | S14: {=IFERROR(INDEX(MPOB!$G$3:$G$1000, SMALL( IF((MPOB!$Q$3:$Q$1000<>"")*(MPOB!$Q$3:$Q$1000<>"Not Due"), ROW(MPOB!$Q$3:$Q$1000)-ROW(MPOB!$Q$3)+1), ROWS(A$2:A14))),"")} -> Nama User : Myra Date : 29/01/2026 Isu : utk pendaftaran aset 2520211253 sepatutnya link kod A1432203..tapi bile kite print GL AM2601-0079 xappear kod merging aset nya..boleh tlg tgk kn x? klo kata xlink, boleh tlg link kn antara kod A2032203 ke A1432203 | T14: {=IFERROR(INDEX(MPOB!$Q$3:$Q$1000, SMALL( IF((MPOB!$Q$3:$Q$1000<>"")*(MPOB!$Q$3:$Q$1000<>"Not Due"), ROW(MPOB!$Q$3:$Q$1000)-ROW(MPOB!$Q$3)+1), ROWS(A$2:A14)) ),"")} -> >60 Days | V14: 13 | W14: {=IFERROR(INDEX(LKTN!$E$3:$E$1000, SMALL( IF((LKTN!$Q$3:$Q$1000<>"")*(LKTN!$Q$3:$Q$1000<>"Not Due"), ROW(LKTN!$Q$3:$Q$1000)-ROW(LKTN!$Q$3)+1), ROWS(A$2:A14))),"")} | X14: {=IFERROR(INDEX(LKTN!$B$3:$B$1000, SMALL( IF((LKTN!$Q$3:$Q$1000<>"")*(LKTN!$Q$3:$Q$1000<>"Not Due"), ROW(LKTN!$Q$3:$Q$1000)-ROW(LKTN!$Q$3)+1), ROWS(A$2:A14))),"")} | Y14: {=IFERROR(INDEX(LKTN!$D$3:$D$1000, SMALL( IF((LKTN!$Q$3:$Q$1000<>"")*(LKTN!$Q$3:$Q$1000<>"Not Due"), ROW(LKTN!$Q$3:$Q$1000)-ROW(LKTN!$Q$3)+1), ROWS(A$2:A14))),"")} | Z14: {=IFERROR(INDEX(LKTN!$G$3:$G$1000, SMALL( IF((LKTN!$Q$3:$Q$1000<>"")*(LKTN!$Q$3:$Q$1000<>"Not Due"), ROW(LKTN!$Q$3:$Q$1000)-ROW(LKTN!$Q$3)+1), ROWS(A$2:A14))),"")} | AA14: {=IFERROR(INDEX(LKTN!$Q$3:$Q$1000, SMALL( IF((LKTN!$Q$3:$Q$1000<>"")*(LKTN!$Q$3:$Q$1000<>"Not Due"), ROW(LKTN!$Q$3:$Q$1000)-ROW(LKTN!$Q$3)+1), ROWS(A$2:A14)) ),"")} | AJ14: 13 | AK14: {=IFERROR(INDEX(ISN!$E$3:$E$1000, SMALL( IF((ISN!$Q$3:$Q$1000<>"")*(ISN!$Q$3:$Q$1000<>"Not Due"), ROW(ISN!$Q$3:$Q$1000)-ROW(ISN!$Q$3)+1), ROWS(A$2:A14))),"")} | AL14: {=IFERROR(INDEX(ISN!$B$3:$B$1000, SMALL( IF((ISN!$Q$3:$Q$1000<>"")*(ISN!$Q$3:$Q$1000<>"Not Due"), ROW(ISN!$Q$3:$Q$1000)-ROW(ISN!$Q$3)+1), ROWS(A$2:A14))),"")} | AM14: {=IFERROR(INDEX(ISN!$D$3:$D$1000, SMALL( IF((ISN!$Q$3:$Q$1000<>"")*(ISN!$Q$3:$Q$1000<>"Not Due"), ROW(ISN!$Q$3:$Q$1000)-ROW(ISN!$Q$3)+1), ROWS(A$2:A14))),"")} | AN14: {=IFERROR(INDEX(ISN!$G$3:$G$1000, SMALL( IF((ISN!$Q$3:$Q$1000<>"")*(ISN!$Q$3:$Q$1000<>"Not Due"), ROW(ISN!$Q$3:$Q$1000)-ROW(ISN!$Q$3)+1), ROWS(A$2:A14))),"")} | AO14: {=IFERROR(INDEX(ISN!$Q$3:$Q$1000, SMALL( IF((ISN!$Q$3:$Q$1000<>"")*(ISN!$Q$3:$Q$1000<>"Not Due"), ROW(ISN!$Q$3:$Q$1000)-ROW(ISN!$Q$3)+1), ROWS(A$2:A14)) ),"")} | AQ14: 13 | AR14: {=IFERROR(INDEX(MSN!$E$3:$E$1000, SMALL( IF((MSN!$Q$3:$Q$1000<>"")*(MSN!$Q$3:$Q$1000<>"Not Due"), ROW(MSN!$Q$3:$Q$1000)-ROW(MSN!$Q$3)+1), ROWS(A$2:A14))),"")} | AS14: {=IFERROR(INDEX(MSN!$B$3:$B$1000, SMALL( IF((MSN!$Q$3:$Q$1000<>"")*(MSN!$Q$3:$Q$1000<>"Not Due"), ROW(MSN!$Q$3:$Q$1000)-ROW(MSN!$Q$3)+1), ROWS(A$2:A14))),"")} | AT14: {=IFERROR(INDEX(MSN!$D$3:$D$1000, SMALL( IF((MSN!$Q$3:$Q$1000<>"")*(MSN!$Q$3:$Q$1000<>"Not Due"), ROW(MSN!$Q$3:$Q$1000)-ROW(MSN!$Q$3)+1), ROWS(A$2:A14))),"")} | AU14: {=IFERROR(INDEX(MSN!$G$3:$G$1000, SMALL( IF((MSN!$Q$3:$Q$1000<>"")*(MSN!$Q$3:$Q$1000<>"Not Due"), ROW(MSN!$Q$3:$Q$1000)-ROW(MSN!$Q$3)+1), ROWS(A$2:A14))),"")} | AV14: {=IFERROR(INDEX(MSN!$Q$3:$Q$1000, SMALL( IF((MSN!$Q$3:$Q$1000<>"")*(MSN!$Q$3:$Q$1000<>"Not Due"), ROW(MSN!$Q$3:$Q$1000)-ROW(MSN!$Q$3)+1), ROWS(A$2:A14)) ),"")}
A15: 14 | B15: {=IFERROR(INDEX(FRIM!$E$3:$E$1000, SMALL(IF(FRIM!$Q$3:$Q$1000<>"", ROW(FRIM!$Q$3:$Q$1000)-ROW(FRIM!$Q$3)+1), ROWS(A$2:A15))),"")} -> FRIM | C15: {=IFERROR(INDEX(FRIM!$B$3:$B$1000, SMALL(IF(FRIM!$Q$3:$Q$1000<>"", ROW(FRIM!$Q$3:$Q$1000)-ROW(FRIM!$Q$3)+1), ROWS(A$2:A15))),"")} -> T/2026/00112 | D15: {=IFERROR(INDEX(FRIM!$D$3:$D$1000, SMALL(IF(FRIM!$Q$3:$Q$1000<>"", ROW(FRIM!$Q$3:$Q$1000)-ROW(FRIM!$Q$3)+1), ROWS(A$2:A15))),"")} -> MYPROCUREMENT | E15: {=IFERROR(INDEX(FRIM!$G$3:$G$1000, SMALL(IF(FRIM!$Q$3:$Q$1000<>"", ROW(FRIM!$Q$3:$Q$1000)-ROW(FRIM!$Q$3)+1), ROWS(A$2:A15))),"")} -> W2477 17/12/2025 AZMEI B. MARZUKI AZTEC SINAR SDN BHD MENGADU. MASALAH TIADA BUTANG UPLOAD SELEPAS KAMI BERI ID & PWORD. SO SYARIKAT TIDAK DAPAT BUAT RENEWAL DI DALAM SISTEM. MOHON TINDAKAN SEGERA SEBAB PROSES PEMBELIAN SEBUTHARGA TERGENDALA. | F15: {=IFERROR(INDEX(FRIM!$Q$3:$Q$1000, SMALL(IF(FRIM!$Q$3:$Q$1000<>"", ROW(FRIM!$Q$3:$Q$1000)-ROW(FRIM!$Q$3)+1), ROWS(A$2:A15))),"")} -> >60 Days | H15: 14 | I15: {=IFERROR(INDEX(MTIB!$E$3:$E$1000, SMALL( IF((MTIB!$Q$3:$Q$1000<>"")*(MTIB!$Q$3:$Q$1000<>"Not Due"), ROW(MTIB!$Q$3:$Q$1000)-ROW(MTIB!$Q$3)+1), ROWS(A$2:A15))),"")} -> MTIB | J15: {=IFERROR(INDEX(MTIB!$B$3:$B$1000, SMALL( IF((MTIB!$Q$3:$Q$1000<>"")*(MTIB!$Q$3:$Q$1000<>"Not Due"), ROW(MTIB!$Q$3:$Q$1000)-ROW(MTIB!$Q$3)+1), ROWS(A$2:A15))),"")} -> T/2026/00445 | K15: {=IFERROR(INDEX(MTIB!$D$3:$D$1000, SMALL( IF((MTIB!$Q$3:$Q$1000<>"")*(MTIB!$Q$3:$Q$1000<>"Not Due"), ROW(MTIB!$Q$3:$Q$1000)-ROW(MTIB!$Q$3)+1), ROWS(A$2:A15))),"")} -> MYFINANCIAL | L15: {=IFERROR(INDEX(MTIB!$G$3:$G$1000, SMALL( IF((MTIB!$Q$3:$Q$1000<>"")*(MTIB!$Q$3:$Q$1000<>"Not Due"), ROW(MTIB!$Q$3:$Q$1000)-ROW(MTIB!$Q$3)+1), ROWS(A$2:A15))),"")} -> Dah banyak kali key-in dan tak boleh nak SIMPAN. Bila click SIMPAN, keluar error "Tambah tidak berjaya". Untuk makluman, bajet mencukupi. | M15: {=IFERROR(INDEX(MTIB!$Q$3:$Q$1000, SMALL( IF((MTIB!$Q$3:$Q$1000<>"")*(MTIB!$Q$3:$Q$1000<>"Not Due"), ROW(MTIB!$Q$3:$Q$1000)-ROW(MTIB!$Q$3)+1), ROWS(A$2:A15)) ),"")} -> 1-30 Days | O15: 14 | P15: {=IFERROR(INDEX(MPOB!$E$3:$E$1000, SMALL( IF((MPOB!$Q$3:$Q$1000<>"")*(MPOB!$Q$3:$Q$1000<>"Not Due"), ROW(MPOB!$Q$3:$Q$1000)-ROW(MPOB!$Q$3)+1), ROWS(A$2:A15))),"")} -> MPOB | Q15: {=IFERROR(INDEX(MPOB!$B$3:$B$1000, SMALL( IF((MPOB!$Q$3:$Q$1000<>"")*(MPOB!$Q$3:$Q$1000<>"Not Due"), ROW(MPOB!$Q$3:$Q$1000)-ROW(MPOB!$Q$3)+1), ROWS(A$2:A15))),"")} -> T/2026/00168 | R15: {=IFERROR(INDEX(MPOB!$D$3:$D$1000, SMALL( IF((MPOB!$Q$3:$Q$1000<>"")*(MPOB!$Q$3:$Q$1000<>"Not Due"), ROW(MPOB!$Q$3:$Q$1000)-ROW(MPOB!$Q$3)+1), ROWS(A$2:A15))),"")} -> MyFinancial | S15: {=IFERROR(INDEX(MPOB!$G$3:$G$1000, SMALL( IF((MPOB!$Q$3:$Q$1000<>"")*(MPOB!$Q$3:$Q$1000<>"Not Due"), ROW(MPOB!$Q$3:$Q$1000)-ROW(MPOB!$Q$3)+1), ROWS(A$2:A15))),"")} -> Nama User : Liyana Date : 30/01/2026 Isu : NO BIL X APPEAR SEMASA BUAT CREDIT NOTE: BILFMDD/1224/01703, BILFMDD/1224/01707, BILFMDD/0624/00283, BILFMDD/0824/002787, BILFMDD/0624/00298, BILFMDD/1124/01470 | T15: {=IFERROR(INDEX(MPOB!$Q$3:$Q$1000, SMALL( IF((MPOB!$Q$3:$Q$1000<>"")*(MPOB!$Q$3:$Q$1000<>"Not Due"), ROW(MPOB!$Q$3:$Q$1000)-ROW(MPOB!$Q$3)+1), ROWS(A$2:A15)) ),"")} -> >60 Days | V15: 14 | W15: {=IFERROR(INDEX(LKTN!$E$3:$E$1000, SMALL( IF((LKTN!$Q$3:$Q$1000<>"")*(LKTN!$Q$3:$Q$1000<>"Not Due"), ROW(LKTN!$Q$3:$Q$1000)-ROW(LKTN!$Q$3)+1), ROWS(A$2:A15))),"")} | X15: {=IFERROR(INDEX(LKTN!$B$3:$B$1000, SMALL( IF((LKTN!$Q$3:$Q$1000<>"")*(LKTN!$Q$3:$Q$1000<>"Not Due"), ROW(LKTN!$Q$3:$Q$1000)-ROW(LKTN!$Q$3)+1), ROWS(A$2:A15))),"")} | Y15: {=IFERROR(INDEX(LKTN!$D$3:$D$1000, SMALL( IF((LKTN!$Q$3:$Q$1000<>"")*(LKTN!$Q$3:$Q$1000<>"Not Due"), ROW(LKTN!$Q$3:$Q$1000)-ROW(LKTN!$Q$3)+1), ROWS(A$2:A15))),"")} | Z15: {=IFERROR(INDEX(LKTN!$G$3:$G$1000, SMALL( IF((LKTN!$Q$3:$Q$1000<>"")*(LKTN!$Q$3:$Q$1000<>"Not Due"), ROW(LKTN!$Q$3:$Q$1000)-ROW(LKTN!$Q$3)+1), ROWS(A$2:A15))),"")} | AA15: {=IFERROR(INDEX(LKTN!$Q$3:$Q$1000, SMALL( IF((LKTN!$Q$3:$Q$1000<>"")*(LKTN!$Q$3:$Q$1000<>"Not Due"), ROW(LKTN!$Q$3:$Q$1000)-ROW(LKTN!$Q$3)+1), ROWS(A$2:A15)) ),"")} | AJ15: 14 | AK15: {=IFERROR(INDEX(ISN!$E$3:$E$1000, SMALL( IF((ISN!$Q$3:$Q$1000<>"")*(ISN!$Q$3:$Q$1000<>"Not Due"), ROW(ISN!$Q$3:$Q$1000)-ROW(ISN!$Q$3)+1), ROWS(A$2:A15))),"")} | AL15: {=IFERROR(INDEX(ISN!$B$3:$B$1000, SMALL( IF((ISN!$Q$3:$Q$1000<>"")*(ISN!$Q$3:$Q$1000<>"Not Due"), ROW(ISN!$Q$3:$Q$1000)-ROW(ISN!$Q$3)+1), ROWS(A$2:A15))),"")} | AM15: {=IFERROR(INDEX(ISN!$D$3:$D$1000, SMALL( IF((ISN!$Q$3:$Q$1000<>"")*(ISN!$Q$3:$Q$1000<>"Not Due"), ROW(ISN!$Q$3:$Q$1000)-ROW(ISN!$Q$3)+1), ROWS(A$2:A15))),"")} | AN15: {=IFERROR(INDEX(ISN!$G$3:$G$1000, SMALL( IF((ISN!$Q$3:$Q$1000<>"")*(ISN!$Q$3:$Q$1000<>"Not Due"), ROW(ISN!$Q$3:$Q$1000)-ROW(ISN!$Q$3)+1), ROWS(A$2:A15))),"")} | AO15: {=IFERROR(INDEX(ISN!$Q$3:$Q$1000, SMALL( IF((ISN!$Q$3:$Q$1000<>"")*(ISN!$Q$3:$Q$1000<>"Not Due"), ROW(ISN!$Q$3:$Q$1000)-ROW(ISN!$Q$3)+1), ROWS(A$2:A15)) ),"")} | AQ15: 14 | AR15: {=IFERROR(INDEX(MSN!$E$3:$E$1000, SMALL( IF((MSN!$Q$3:$Q$1000<>"")*(MSN!$Q$3:$Q$1000<>"Not Due"), ROW(MSN!$Q$3:$Q$1000)-ROW(MSN!$Q$3)+1), ROWS(A$2:A15))),"")} | AS15: {=IFERROR(INDEX(MSN!$B$3:$B$1000, SMALL( IF((MSN!$Q$3:$Q$1000<>"")*(MSN!$Q$3:$Q$1000<>"Not Due"), ROW(MSN!$Q$3:$Q$1000)-ROW(MSN!$Q$3)+1), ROWS(A$2:A15))),"")} | AT15: {=IFERROR(INDEX(MSN!$D$3:$D$1000, SMALL( IF((MSN!$Q$3:$Q$1000<>"")*(MSN!$Q$3:$Q$1000<>"Not Due"), ROW(MSN!$Q$3:$Q$1000)-ROW(MSN!$Q$3)+1), ROWS(A$2:A15))),"")} | AU15: {=IFERROR(INDEX(MSN!$G$3:$G$1000, SMALL( IF((MSN!$Q$3:$Q$1000<>"")*(MSN!$Q$3:$Q$1000<>"Not Due"), ROW(MSN!$Q$3:$Q$1000)-ROW(MSN!$Q$3)+1), ROWS(A$2:A15))),"")} | AV15: {=IFERROR(INDEX(MSN!$Q$3:$Q$1000, SMALL( IF((MSN!$Q$3:$Q$1000<>"")*(MSN!$Q$3:$Q$1000<>"Not Due"), ROW(MSN!$Q$3:$Q$1000)-ROW(MSN!$Q$3)+1), ROWS(A$2:A15)) ),"")}
A16: 15 | B16: {=IFERROR(INDEX(FRIM!$E$3:$E$1000, SMALL(IF(FRIM!$Q$3:$Q$1000<>"", ROW(FRIM!$Q$3:$Q$1000)-ROW(FRIM!$Q$3)+1), ROWS(A$2:A16))),"")} -> FRIM | C16: {=IFERROR(INDEX(FRIM!$B$3:$B$1000, SMALL(IF(FRIM!$Q$3:$Q$1000<>"", ROW(FRIM!$Q$3:$Q$1000)-ROW(FRIM!$Q$3)+1), ROWS(A$2:A16))),"")} -> T/2026/00115 | D16: {=IFERROR(INDEX(FRIM!$D$3:$D$1000, SMALL(IF(FRIM!$Q$3:$Q$1000<>"", ROW(FRIM!$Q$3:$Q$1000)-ROW(FRIM!$Q$3)+1), ROWS(A$2:A16))),"")} -> MYFINANCIAL CLIENT | E16: {=IFERROR(INDEX(FRIM!$G$3:$G$1000, SMALL(IF(FRIM!$Q$3:$Q$1000<>"", ROW(FRIM!$Q$3:$Q$1000)-ROW(FRIM!$Q$3)+1), ROWS(A$2:A16))),"")} -> W2480 29/12/2025 NOR AFIZAH BT. ARSHAD file batch dijana hanya dalam bentuk text document sedangkan mengikut keperluan perlu ada gpg file bagi tujuan upload dalam sistem cimb-bizchannel. perkara ini berlaku pada 8.6.2021 (frimeft210604227) sehingga kini dan maklumbalas terkini oleh En. Helmi pada Mesyuarat Petugas SAGA pada 23.12.2025 akan diselesaikan segera. | F16: {=IFERROR(INDEX(FRIM!$Q$3:$Q$1000, SMALL(IF(FRIM!$Q$3:$Q$1000<>"", ROW(FRIM!$Q$3:$Q$1000)-ROW(FRIM!$Q$3)+1), ROWS(A$2:A16))),"")} -> >60 Days | H16: 15 | I16: {=IFERROR(INDEX(MTIB!$E$3:$E$1000, SMALL( IF((MTIB!$Q$3:$Q$1000<>"")*(MTIB!$Q$3:$Q$1000<>"Not Due"), ROW(MTIB!$Q$3:$Q$1000)-ROW(MTIB!$Q$3)+1), ROWS(A$2:A16))),"")} -> MTIB | J16: {=IFERROR(INDEX(MTIB!$B$3:$B$1000, SMALL( IF((MTIB!$Q$3:$Q$1000<>"")*(MTIB!$Q$3:$Q$1000<>"Not Due"), ROW(MTIB!$Q$3:$Q$1000)-ROW(MTIB!$Q$3)+1), ROWS(A$2:A16))),"")} -> T/2026/00451 | K16: {=IFERROR(INDEX(MTIB!$D$3:$D$1000, SMALL( IF((MTIB!$Q$3:$Q$1000<>"")*(MTIB!$Q$3:$Q$1000<>"Not Due"), ROW(MTIB!$Q$3:$Q$1000)-ROW(MTIB!$Q$3)+1), ROWS(A$2:A16))),"")} -> MYFINANCIAL | L16: {=IFERROR(INDEX(MTIB!$G$3:$G$1000, SMALL( IF((MTIB!$Q$3:$Q$1000<>"")*(MTIB!$Q$3:$Q$1000<>"Not Due"), ROW(MTIB!$Q$3:$Q$1000)-ROW(MTIB!$Q$3)+1), ROWS(A$2:A16))),"")} -> Untuk makluman tuan, dua akaun telah di-create namun terdapat error seperti lampiran. Senarai nama pengguna juga tidak terpapar pada Security Manager for MyFinancial. Akses juga telah diberi melalui MySecurity. Nama: En. Zulhelmi bin Mohd Ali (Wilayah Tengah) Pn. Mimi Adrina binti Nor Hazazi (Wilayah Tengah) | M16: {=IFERROR(INDEX(MTIB!$Q$3:$Q$1000, SMALL( IF((MTIB!$Q$3:$Q$1000<>"")*(MTIB!$Q$3:$Q$1000<>"Not Due"), ROW(MTIB!$Q$3:$Q$1000)-ROW(MTIB!$Q$3)+1), ROWS(A$2:A16)) ),"")} -> 1-30 Days | O16: 15 | P16: {=IFERROR(INDEX(MPOB!$E$3:$E$1000, SMALL( IF((MPOB!$Q$3:$Q$1000<>"")*(MPOB!$Q$3:$Q$1000<>"Not Due"), ROW(MPOB!$Q$3:$Q$1000)-ROW(MPOB!$Q$3)+1), ROWS(A$2:A16))),"")} -> MPOB | Q16: {=IFERROR(INDEX(MPOB!$B$3:$B$1000, SMALL( IF((MPOB!$Q$3:$Q$1000<>"")*(MPOB!$Q$3:$Q$1000<>"Not Due"), ROW(MPOB!$Q$3:$Q$1000)-ROW(MPOB!$Q$3)+1), ROWS(A$2:A16))),"")} -> T/2026/00177 | R16: {=IFERROR(INDEX(MPOB!$D$3:$D$1000, SMALL( IF((MPOB!$Q$3:$Q$1000<>"")*(MPOB!$Q$3:$Q$1000<>"Not Due"), ROW(MPOB!$Q$3:$Q$1000)-ROW(MPOB!$Q$3)+1), ROWS(A$2:A16))),"")} -> MyFinancial | S16: {=IFERROR(INDEX(MPOB!$G$3:$G$1000, SMALL( IF((MPOB!$Q$3:$Q$1000<>"")*(MPOB!$Q$3:$Q$1000<>"Not Due"), ROW(MPOB!$Q$3:$Q$1000)-ROW(MPOB!$Q$3)+1), ROWS(A$2:A16))),"")} -> Nama User : Norlizah Date : 4/2/2026 Isu : bila klik cetak..kenapa resit kosong👆 | T16: {=IFERROR(INDEX(MPOB!$Q$3:$Q$1000, SMALL( IF((MPOB!$Q$3:$Q$1000<>"")*(MPOB!$Q$3:$Q$1000<>"Not Due"), ROW(MPOB!$Q$3:$Q$1000)-ROW(MPOB!$Q$3)+1), ROWS(A$2:A16)) ),"")} -> >60 Days | V16: 15 | W16: {=IFERROR(INDEX(LKTN!$E$3:$E$1000, SMALL( IF((LKTN!$Q$3:$Q$1000<>"")*(LKTN!$Q$3:$Q$1000<>"Not Due"), ROW(LKTN!$Q$3:$Q$1000)-ROW(LKTN!$Q$3)+1), ROWS(A$2:A16))),"")} | X16: {=IFERROR(INDEX(LKTN!$B$3:$B$1000, SMALL( IF((LKTN!$Q$3:$Q$1000<>"")*(LKTN!$Q$3:$Q$1000<>"Not Due"), ROW(LKTN!$Q$3:$Q$1000)-ROW(LKTN!$Q$3)+1), ROWS(A$2:A16))),"")} | Y16: {=IFERROR(INDEX(LKTN!$D$3:$D$1000, SMALL( IF((LKTN!$Q$3:$Q$1000<>"")*(LKTN!$Q$3:$Q$1000<>"Not Due"), ROW(LKTN!$Q$3:$Q$1000)-ROW(LKTN!$Q$3)+1), ROWS(A$2:A16))),"")} | Z16: {=IFERROR(INDEX(LKTN!$G$3:$G$1000, SMALL( IF((LKTN!$Q$3:$Q$1000<>"")*(LKTN!$Q$3:$Q$1000<>"Not Due"), ROW(LKTN!$Q$3:$Q$1000)-ROW(LKTN!$Q$3)+1), ROWS(A$2:A16))),"")} | AA16: {=IFERROR(INDEX(LKTN!$Q$3:$Q$1000, SMALL( IF((LKTN!$Q$3:$Q$1000<>"")*(LKTN!$Q$3:$Q$1000<>"Not Due"), ROW(LKTN!$Q$3:$Q$1000)-ROW(LKTN!$Q$3)+1), ROWS(A$2:A16)) ),"")} | AJ16: 15 | AK16: {=IFERROR(INDEX(ISN!$E$3:$E$1000, SMALL( IF((ISN!$Q$3:$Q$1000<>"")*(ISN!$Q$3:$Q$1000<>"Not Due"), ROW(ISN!$Q$3:$Q$1000)-ROW(ISN!$Q$3)+1), ROWS(A$2:A16))),"")} | AL16: {=IFERROR(INDEX(ISN!$B$3:$B$1000, SMALL( IF((ISN!$Q$3:$Q$1000<>"")*(ISN!$Q$3:$Q$1000<>"Not Due"), ROW(ISN!$Q$3:$Q$1000)-ROW(ISN!$Q$3)+1), ROWS(A$2:A16))),"")} | AM16: {=IFERROR(INDEX(ISN!$D$3:$D$1000, SMALL( IF((ISN!$Q$3:$Q$1000<>"")*(ISN!$Q$3:$Q$1000<>"Not Due"), ROW(ISN!$Q$3:$Q$1000)-ROW(ISN!$Q$3)+1), ROWS(A$2:A16))),"")} | AN16: {=IFERROR(INDEX(ISN!$G$3:$G$1000, SMALL( IF((ISN!$Q$3:$Q$1000<>"")*(ISN!$Q$3:$Q$1000<>"Not Due"), ROW(ISN!$Q$3:$Q$1000)-ROW(ISN!$Q$3)+1), ROWS(A$2:A16))),"")} | AO16: {=IFERROR(INDEX(ISN!$Q$3:$Q$1000, SMALL( IF((ISN!$Q$3:$Q$1000<>"")*(ISN!$Q$3:$Q$1000<>"Not Due"), ROW(ISN!$Q$3:$Q$1000)-ROW(ISN!$Q$3)+1), ROWS(A$2:A16)) ),"")} | AQ16: 15 | AR16: {=IFERROR(INDEX(MSN!$E$3:$E$1000, SMALL( IF((MSN!$Q$3:$Q$1000<>"")*(MSN!$Q$3:$Q$1000<>"Not Due"), ROW(MSN!$Q$3:$Q$1000)-ROW(MSN!$Q$3)+1), ROWS(A$2:A16))),"")} | AS16: {=IFERROR(INDEX(MSN!$B$3:$B$1000, SMALL( IF((MSN!$Q$3:$Q$1000<>"")*(MSN!$Q$3:$Q$1000<>"Not Due"), ROW(MSN!$Q$3:$Q$1000)-ROW(MSN!$Q$3)+1), ROWS(A$2:A16))),"")} | AT16: {=IFERROR(INDEX(MSN!$D$3:$D$1000, SMALL( IF((MSN!$Q$3:$Q$1000<>"")*(MSN!$Q$3:$Q$1000<>"Not Due"), ROW(MSN!$Q$3:$Q$1000)-ROW(MSN!$Q$3)+1), ROWS(A$2:A16))),"")} | AU16: {=IFERROR(INDEX(MSN!$G$3:$G$1000, SMALL( IF((MSN!$Q$3:$Q$1000<>"")*(MSN!$Q$3:$Q$1000<>"Not Due"), ROW(MSN!$Q$3:$Q$1000)-ROW(MSN!$Q$3)+1), ROWS(A$2:A16))),"")} | AV16: {=IFERROR(INDEX(MSN!$Q$3:$Q$1000, SMALL( IF((MSN!$Q$3:$Q$1000<>"")*(MSN!$Q$3:$Q$1000<>"Not Due"), ROW(MSN!$Q$3:$Q$1000)-ROW(MSN!$Q$3)+1), ROWS(A$2:A16)) ),"")}
A17: 16 | B17: {=IFERROR(INDEX(FRIM!$E$3:$E$1000, SMALL(IF(FRIM!$Q$3:$Q$1000<>"", ROW(FRIM!$Q$3:$Q$1000)-ROW(FRIM!$Q$3)+1), ROWS(A$2:A17))),"")} -> FRIM | C17: {=IFERROR(INDEX(FRIM!$B$3:$B$1000, SMALL(IF(FRIM!$Q$3:$Q$1000<>"", ROW(FRIM!$Q$3:$Q$1000)-ROW(FRIM!$Q$3)+1), ROWS(A$2:A17))),"")} -> T/2026/00122 | D17: {=IFERROR(INDEX(FRIM!$D$3:$D$1000, SMALL(IF(FRIM!$Q$3:$Q$1000<>"", ROW(FRIM!$Q$3:$Q$1000)-ROW(FRIM!$Q$3)+1), ROWS(A$2:A17))),"")} -> MYPROCUREMENT | E17: {=IFERROR(INDEX(FRIM!$G$3:$G$1000, SMALL(IF(FRIM!$Q$3:$Q$1000<>"", ROW(FRIM!$Q$3:$Q$1000)-ROW(FRIM!$Q$3)+1), ROWS(A$2:A17))),"")} -> W2525 12/03/2026 NURUL AIN BINTI MOHD HADZIR Sistem kebenaran perolehan bagi permohonan baru. Terdapat masalah sistem di Konfigurasi capaian. | F17: {=IFERROR(INDEX(FRIM!$Q$3:$Q$1000, SMALL(IF(FRIM!$Q$3:$Q$1000<>"", ROW(FRIM!$Q$3:$Q$1000)-ROW(FRIM!$Q$3)+1), ROWS(A$2:A17))),"")} -> >60 Days | H17: 16 | I17: {=IFERROR(INDEX(MTIB!$E$3:$E$1000, SMALL( IF((MTIB!$Q$3:$Q$1000<>"")*(MTIB!$Q$3:$Q$1000<>"Not Due"), ROW(MTIB!$Q$3:$Q$1000)-ROW(MTIB!$Q$3)+1), ROWS(A$2:A17))),"")} | J17: {=IFERROR(INDEX(MTIB!$B$3:$B$1000, SMALL( IF((MTIB!$Q$3:$Q$1000<>"")*(MTIB!$Q$3:$Q$1000<>"Not Due"), ROW(MTIB!$Q$3:$Q$1000)-ROW(MTIB!$Q$3)+1), ROWS(A$2:A17))),"")} | K17: {=IFERROR(INDEX(MTIB!$D$3:$D$1000, SMALL( IF((MTIB!$Q$3:$Q$1000<>"")*(MTIB!$Q$3:$Q$1000<>"Not Due"), ROW(MTIB!$Q$3:$Q$1000)-ROW(MTIB!$Q$3)+1), ROWS(A$2:A17))),"")} | L17: {=IFERROR(INDEX(MTIB!$G$3:$G$1000, SMALL( IF((MTIB!$Q$3:$Q$1000<>"")*(MTIB!$Q$3:$Q$1000<>"Not Due"), ROW(MTIB!$Q$3:$Q$1000)-ROW(MTIB!$Q$3)+1), ROWS(A$2:A17))),"")} | M17: {=IFERROR(INDEX(MTIB!$Q$3:$Q$1000, SMALL( IF((MTIB!$Q$3:$Q$1000<>"")*(MTIB!$Q$3:$Q$1000<>"Not Due"), ROW(MTIB!$Q$3:$Q$1000)-ROW(MTIB!$Q$3)+1), ROWS(A$2:A17)) ),"")} | O17: 16 | P17: {=IFERROR(INDEX(MPOB!$E$3:$E$1000, SMALL( IF((MPOB!$Q$3:$Q$1000<>"")*(MPOB!$Q$3:$Q$1000<>"Not Due"), ROW(MPOB!$Q$3:$Q$1000)-ROW(MPOB!$Q$3)+1), ROWS(A$2:A17))),"")} -> MPOB | Q17: {=IFERROR(INDEX(MPOB!$B$3:$B$1000, SMALL( IF((MPOB!$Q$3:$Q$1000<>"")*(MPOB!$Q$3:$Q$1000<>"Not Due"), ROW(MPOB!$Q$3:$Q$1000)-ROW(MPOB!$Q$3)+1), ROWS(A$2:A17))),"")} -> T/2026/00178 | R17: {=IFERROR(INDEX(MPOB!$D$3:$D$1000, SMALL( IF((MPOB!$Q$3:$Q$1000<>"")*(MPOB!$Q$3:$Q$1000<>"Not Due"), ROW(MPOB!$Q$3:$Q$1000)-ROW(MPOB!$Q$3)+1), ROWS(A$2:A17))),"")} -> MyProcurement | S17: {=IFERROR(INDEX(MPOB!$G$3:$G$1000, SMALL( IF((MPOB!$Q$3:$Q$1000<>"")*(MPOB!$Q$3:$Q$1000<>"Not Due"), ROW(MPOB!$Q$3:$Q$1000)-ROW(MPOB!$Q$3)+1), ROWS(A$2:A17))),"")} -> Nama User : AsAlya Date : 4/2/2026 Isu : user ni xboleh add kat borang prestasi pembekal untk Po ni LPO/BSRD0401/0725/00025 untuk invois yg bayaran berperingkat Mohd Hafiz Mohd Zuki | T17: {=IFERROR(INDEX(MPOB!$Q$3:$Q$1000, SMALL( IF((MPOB!$Q$3:$Q$1000<>"")*(MPOB!$Q$3:$Q$1000<>"Not Due"), ROW(MPOB!$Q$3:$Q$1000)-ROW(MPOB!$Q$3)+1), ROWS(A$2:A17)) ),"")} -> >60 Days | V17: 16 | W17: {=IFERROR(INDEX(LKTN!$E$3:$E$1000, SMALL( IF((LKTN!$Q$3:$Q$1000<>"")*(LKTN!$Q$3:$Q$1000<>"Not Due"), ROW(LKTN!$Q$3:$Q$1000)-ROW(LKTN!$Q$3)+1), ROWS(A$2:A17))),"")} | X17: {=IFERROR(INDEX(LKTN!$B$3:$B$1000, SMALL( IF((LKTN!$Q$3:$Q$1000<>"")*(LKTN!$Q$3:$Q$1000<>"Not Due"), ROW(LKTN!$Q$3:$Q$1000)-ROW(LKTN!$Q$3)+1), ROWS(A$2:A17))),"")} | Y17: {=IFERROR(INDEX(LKTN!$D$3:$D$1000, SMALL( IF((LKTN!$Q$3:$Q$1000<>"")*(LKTN!$Q$3:$Q$1000<>"Not Due"), ROW(LKTN!$Q$3:$Q$1000)-ROW(LKTN!$Q$3)+1), ROWS(A$2:A17))),"")} | Z17: {=IFERROR(INDEX(LKTN!$G$3:$G$1000, SMALL( IF((LKTN!$Q$3:$Q$1000<>"")*(LKTN!$Q$3:$Q$1000<>"Not Due"), ROW(LKTN!$Q$3:$Q$1000)-ROW(LKTN!$Q$3)+1), ROWS(A$2:A17))),"")} | AA17: {=IFERROR(INDEX(LKTN!$Q$3:$Q$1000, SMALL( IF((LKTN!$Q$3:$Q$1000<>"")*(LKTN!$Q$3:$Q$1000<>"Not Due"), ROW(LKTN!$Q$3:$Q$1000)-ROW(LKTN!$Q$3)+1), ROWS(A$2:A17)) ),"")} | AJ17: 16 | AK17: {=IFERROR(INDEX(ISN!$E$3:$E$1000, SMALL( IF((ISN!$Q$3:$Q$1000<>"")*(ISN!$Q$3:$Q$1000<>"Not Due"), ROW(ISN!$Q$3:$Q$1000)-ROW(ISN!$Q$3)+1), ROWS(A$2:A17))),"")} | AL17: {=IFERROR(INDEX(ISN!$B$3:$B$1000, SMALL( IF((ISN!$Q$3:$Q$1000<>"")*(ISN!$Q$3:$Q$1000<>"Not Due"), ROW(ISN!$Q$3:$Q$1000)-ROW(ISN!$Q$3)+1), ROWS(A$2:A17))),"")} | AM17: {=IFERROR(INDEX(ISN!$D$3:$D$1000, SMALL( IF((ISN!$Q$3:$Q$1000<>"")*(ISN!$Q$3:$Q$1000<>"Not Due"), ROW(ISN!$Q$3:$Q$1000)-ROW(ISN!$Q$3)+1), ROWS(A$2:A17))),"")} | AN17: {=IFERROR(INDEX(ISN!$G$3:$G$1000, SMALL( IF((ISN!$Q$3:$Q$1000<>"")*(ISN!$Q$3:$Q$1000<>"Not Due"), ROW(ISN!$Q$3:$Q$1000)-ROW(ISN!$Q$3)+1), ROWS(A$2:A17))),"")} | AO17: {=IFERROR(INDEX(ISN!$Q$3:$Q$1000, SMALL( IF((ISN!$Q$3:$Q$1000<>"")*(ISN!$Q$3:$Q$1000<>"Not Due"), ROW(ISN!$Q$3:$Q$1000)-ROW(ISN!$Q$3)+1), ROWS(A$2:A17)) ),"")} | AQ17: 16 | AR17: {=IFERROR(INDEX(MSN!$E$3:$E$1000, SMALL( IF((MSN!$Q$3:$Q$1000<>"")*(MSN!$Q$3:$Q$1000<>"Not Due"), ROW(MSN!$Q$3:$Q$1000)-ROW(MSN!$Q$3)+1), ROWS(A$2:A17))),"")} | AS17: {=IFERROR(INDEX(MSN!$B$3:$B$1000, SMALL( IF((MSN!$Q$3:$Q$1000<>"")*(MSN!$Q$3:$Q$1000<>"Not Due"), ROW(MSN!$Q$3:$Q$1000)-ROW(MSN!$Q$3)+1), ROWS(A$2:A17))),"")} | AT17: {=IFERROR(INDEX(MSN!$D$3:$D$1000, SMALL( IF((MSN!$Q$3:$Q$1000<>"")*(MSN!$Q$3:$Q$1000<>"Not Due"), ROW(MSN!$Q$3:$Q$1000)-ROW(MSN!$Q$3)+1), ROWS(A$2:A17))),"")} | AU17: {=IFERROR(INDEX(MSN!$G$3:$G$1000, SMALL( IF((MSN!$Q$3:$Q$1000<>"")*(MSN!$Q$3:$Q$1000<>"Not Due"), ROW(MSN!$Q$3:$Q$1000)-ROW(MSN!$Q$3)+1), ROWS(A$2:A17))),"")} | AV17: {=IFERROR(INDEX(MSN!$Q$3:$Q$1000, SMALL( IF((MSN!$Q$3:$Q$1000<>"")*(MSN!$Q$3:$Q$1000<>"Not Due"), ROW(MSN!$Q$3:$Q$1000)-ROW(MSN!$Q$3)+1), ROWS(A$2:A17)) ),"")}
A18: 17 | B18: {=IFERROR(INDEX(FRIM!$E$3:$E$1000, SMALL(IF(FRIM!$Q$3:$Q$1000<>"", ROW(FRIM!$Q$3:$Q$1000)-ROW(FRIM!$Q$3)+1), ROWS(A$2:A18))),"")} -> FRIM | C18: {=IFERROR(INDEX(FRIM!$B$3:$B$1000, SMALL(IF(FRIM!$Q$3:$Q$1000<>"", ROW(FRIM!$Q$3:$Q$1000)-ROW(FRIM!$Q$3)+1), ROWS(A$2:A18))),"")} -> T/2026/00137 | D18: {=IFERROR(INDEX(FRIM!$D$3:$D$1000, SMALL(IF(FRIM!$Q$3:$Q$1000<>"", ROW(FRIM!$Q$3:$Q$1000)-ROW(FRIM!$Q$3)+1), ROWS(A$2:A18))),"")} -> MYFINANCIAL CLIENT | E18: {=IFERROR(INDEX(FRIM!$G$3:$G$1000, SMALL(IF(FRIM!$Q$3:$Q$1000<>"", ROW(FRIM!$Q$3:$Q$1000)-ROW(FRIM!$Q$3)+1), ROWS(A$2:A18))),"")} -> W2529 17 March 2026 AZROL BIN KAMARUDDIN BAKI AKHIR DISEMBER 2025 KOD PELARASAN GAJI 62510 TIDAK SAMA DENGAN BAKI AWAL JANUARI 2026 | F18: {=IFERROR(INDEX(FRIM!$Q$3:$Q$1000, SMALL(IF(FRIM!$Q$3:$Q$1000<>"", ROW(FRIM!$Q$3:$Q$1000)-ROW(FRIM!$Q$3)+1), ROWS(A$2:A18))),"")} -> >60 Days | H18: 17 | I18: {=IFERROR(INDEX(MTIB!$E$3:$E$1000, SMALL( IF((MTIB!$Q$3:$Q$1000<>"")*(MTIB!$Q$3:$Q$1000<>"Not Due"), ROW(MTIB!$Q$3:$Q$1000)-ROW(MTIB!$Q$3)+1), ROWS(A$2:A18))),"")} | J18: {=IFERROR(INDEX(MTIB!$B$3:$B$1000, SMALL( IF((MTIB!$Q$3:$Q$1000<>"")*(MTIB!$Q$3:$Q$1000<>"Not Due"), ROW(MTIB!$Q$3:$Q$1000)-ROW(MTIB!$Q$3)+1), ROWS(A$2:A18))),"")} | K18: {=IFERROR(INDEX(MTIB!$D$3:$D$1000, SMALL( IF((MTIB!$Q$3:$Q$1000<>"")*(MTIB!$Q$3:$Q$1000<>"Not Due"), ROW(MTIB!$Q$3:$Q$1000)-ROW(MTIB!$Q$3)+1), ROWS(A$2:A18))),"")} | L18: {=IFERROR(INDEX(MTIB!$G$3:$G$1000, SMALL( IF((MTIB!$Q$3:$Q$1000<>"")*(MTIB!$Q$3:$Q$1000<>"Not Due"), ROW(MTIB!$Q$3:$Q$1000)-ROW(MTIB!$Q$3)+1), ROWS(A$2:A18))),"")} | M18: {=IFERROR(INDEX(MTIB!$Q$3:$Q$1000, SMALL( IF((MTIB!$Q$3:$Q$1000<>"")*(MTIB!$Q$3:$Q$1000<>"Not Due"), ROW(MTIB!$Q$3:$Q$1000)-ROW(MTIB!$Q$3)+1), ROWS(A$2:A18)) ),"")} | O18: 17 | P18: {=IFERROR(INDEX(MPOB!$E$3:$E$1000, SMALL( IF((MPOB!$Q$3:$Q$1000<>"")*(MPOB!$Q$3:$Q$1000<>"Not Due"), ROW(MPOB!$Q$3:$Q$1000)-ROW(MPOB!$Q$3)+1), ROWS(A$2:A18))),"")} -> MPOB | Q18: {=IFERROR(INDEX(MPOB!$B$3:$B$1000, SMALL( IF((MPOB!$Q$3:$Q$1000<>"")*(MPOB!$Q$3:$Q$1000<>"Not Due"), ROW(MPOB!$Q$3:$Q$1000)-ROW(MPOB!$Q$3)+1), ROWS(A$2:A18))),"")} -> T/2026/00186 | R18: {=IFERROR(INDEX(MPOB!$D$3:$D$1000, SMALL( IF((MPOB!$Q$3:$Q$1000<>"")*(MPOB!$Q$3:$Q$1000<>"Not Due"), ROW(MPOB!$Q$3:$Q$1000)-ROW(MPOB!$Q$3)+1), ROWS(A$2:A18))),"")} -> MyFinancial | S18: {=IFERROR(INDEX(MPOB!$G$3:$G$1000, SMALL( IF((MPOB!$Q$3:$Q$1000<>"")*(MPOB!$Q$3:$Q$1000<>"Not Due"), ROW(MPOB!$Q$3:$Q$1000)-ROW(MPOB!$Q$3)+1), ROWS(A$2:A18))),"")} -> Nama User : Irda 60182066610 Date : 5/2/2026 Isu : bukan sepatutnya amaun in RM after converted ke? | T18: {=IFERROR(INDEX(MPOB!$Q$3:$Q$1000, SMALL( IF((MPOB!$Q$3:$Q$1000<>"")*(MPOB!$Q$3:$Q$1000<>"Not Due"), ROW(MPOB!$Q$3:$Q$1000)-ROW(MPOB!$Q$3)+1), ROWS(A$2:A18)) ),"")} -> >60 Days | V18: 17 | W18: {=IFERROR(INDEX(LKTN!$E$3:$E$1000, SMALL( IF((LKTN!$Q$3:$Q$1000<>"")*(LKTN!$Q$3:$Q$1000<>"Not Due"), ROW(LKTN!$Q$3:$Q$1000)-ROW(LKTN!$Q$3)+1), ROWS(A$2:A18))),"")} | X18: {=IFERROR(INDEX(LKTN!$B$3:$B$1000, SMALL( IF((LKTN!$Q$3:$Q$1000<>"")*(LKTN!$Q$3:$Q$1000<>"Not Due"), ROW(LKTN!$Q$3:$Q$1000)-ROW(LKTN!$Q$3)+1), ROWS(A$2:A18))),"")} | Y18: {=IFERROR(INDEX(LKTN!$D$3:$D$1000, SMALL( IF((LKTN!$Q$3:$Q$1000<>"")*(LKTN!$Q$3:$Q$1000<>"Not Due"), ROW(LKTN!$Q$3:$Q$1000)-ROW(LKTN!$Q$3)+1), ROWS(A$2:A18))),"")} | Z18: {=IFERROR(INDEX(LKTN!$G$3:$G$1000, SMALL( IF((LKTN!$Q$3:$Q$1000<>"")*(LKTN!$Q$3:$Q$1000<>"Not Due"), ROW(LKTN!$Q$3:$Q$1000)-ROW(LKTN!$Q$3)+1), ROWS(A$2:A18))),"")} | AA18: {=IFERROR(INDEX(LKTN!$Q$3:$Q$1000, SMALL( IF((LKTN!$Q$3:$Q$1000<>"")*(LKTN!$Q$3:$Q$1000<>"Not Due"), ROW(LKTN!$Q$3:$Q$1000)-ROW(LKTN!$Q$3)+1), ROWS(A$2:A18)) ),"")} | AJ18: 17 | AK18: {=IFERROR(INDEX(ISN!$E$3:$E$1000, SMALL( IF((ISN!$Q$3:$Q$1000<>"")*(ISN!$Q$3:$Q$1000<>"Not Due"), ROW(ISN!$Q$3:$Q$1000)-ROW(ISN!$Q$3)+1), ROWS(A$2:A18))),"")} | AL18: {=IFERROR(INDEX(ISN!$B$3:$B$1000, SMALL( IF((ISN!$Q$3:$Q$1000<>"")*(ISN!$Q$3:$Q$1000<>"Not Due"), ROW(ISN!$Q$3:$Q$1000)-ROW(ISN!$Q$3)+1), ROWS(A$2:A18))),"")} | AM18: {=IFERROR(INDEX(ISN!$D$3:$D$1000, SMALL( IF((ISN!$Q$3:$Q$1000<>"")*(ISN!$Q$3:$Q$1000<>"Not Due"), ROW(ISN!$Q$3:$Q$1000)-ROW(ISN!$Q$3)+1), ROWS(A$2:A18))),"")} | AN18: {=IFERROR(INDEX(ISN!$G$3:$G$1000, SMALL( IF((ISN!$Q$3:$Q$1000<>"")*(ISN!$Q$3:$Q$1000<>"Not Due"), ROW(ISN!$Q$3:$Q$1000)-ROW(ISN!$Q$3)+1), ROWS(A$2:A18))),"")} | AO18: {=IFERROR(INDEX(ISN!$Q$3:$Q$1000, SMALL( IF((ISN!$Q$3:$Q$1000<>"")*(ISN!$Q$3:$Q$1000<>"Not Due"), ROW(ISN!$Q$3:$Q$1000)-ROW(ISN!$Q$3)+1), ROWS(A$2:A18)) ),"")} | AQ18: 17 | AR18: {=IFERROR(INDEX(MSN!$E$3:$E$1000, SMALL( IF((MSN!$Q$3:$Q$1000<>"")*(MSN!$Q$3:$Q$1000<>"Not Due"), ROW(MSN!$Q$3:$Q$1000)-ROW(MSN!$Q$3)+1), ROWS(A$2:A18))),"")} | AS18: {=IFERROR(INDEX(MSN!$B$3:$B$1000, SMALL( IF((MSN!$Q$3:$Q$1000<>"")*(MSN!$Q$3:$Q$1000<>"Not Due"), ROW(MSN!$Q$3:$Q$1000)-ROW(MSN!$Q$3)+1), ROWS(A$2:A18))),"")} | AT18: {=IFERROR(INDEX(MSN!$D$3:$D$1000, SMALL( IF((MSN!$Q$3:$Q$1000<>"")*(MSN!$Q$3:$Q$1000<>"Not Due"), ROW(MSN!$Q$3:$Q$1000)-ROW(MSN!$Q$3)+1), ROWS(A$2:A18))),"")} | AU18: {=IFERROR(INDEX(MSN!$G$3:$G$1000, SMALL( IF((MSN!$Q$3:$Q$1000<>"")*(MSN!$Q$3:$Q$1000<>"Not Due"), ROW(MSN!$Q$3:$Q$1000)-ROW(MSN!$Q$3)+1), ROWS(A$2:A18))),"")} | AV18: {=IFERROR(INDEX(MSN!$Q$3:$Q$1000, SMALL( IF((MSN!$Q$3:$Q$1000<>"")*(MSN!$Q$3:$Q$1000<>"Not Due"), ROW(MSN!$Q$3:$Q$1000)-ROW(MSN!$Q$3)+1), ROWS(A$2:A18)) ),"")}
A19: 18 | B19: {=IFERROR(INDEX(FRIM!$E$3:$E$1000, SMALL(IF(FRIM!$Q$3:$Q$1000<>"", ROW(FRIM!$Q$3:$Q$1000)-ROW(FRIM!$Q$3)+1), ROWS(A$2:A19))),"")} -> FRIM | C19: {=IFERROR(INDEX(FRIM!$B$3:$B$1000, SMALL(IF(FRIM!$Q$3:$Q$1000<>"", ROW(FRIM!$Q$3:$Q$1000)-ROW(FRIM!$Q$3)+1), ROWS(A$2:A19))),"")} -> T/2026/00313 | D19: {=IFERROR(INDEX(FRIM!$D$3:$D$1000, SMALL(IF(FRIM!$Q$3:$Q$1000<>"", ROW(FRIM!$Q$3:$Q$1000)-ROW(FRIM!$Q$3)+1), ROWS(A$2:A19))),"")} -> MYFINANCIAL CLIENT | E19: {=IFERROR(INDEX(FRIM!$G$3:$G$1000, SMALL(IF(FRIM!$Q$3:$Q$1000<>"", ROW(FRIM!$Q$3:$Q$1000)-ROW(FRIM!$Q$3)+1), ROWS(A$2:A19))),"")} -> W2548 28 April 2026 NOR AFIZAH BT. ARSHAD mohon semakan bagi baucar per2600678. status baucar dah pos. tarikh cek dan no cek tak update dekat baucar dan baucar tersebut tiada dalam senarai lejar kod bank 65101. | F19: {=IFERROR(INDEX(FRIM!$Q$3:$Q$1000, SMALL(IF(FRIM!$Q$3:$Q$1000<>"", ROW(FRIM!$Q$3:$Q$1000)-ROW(FRIM!$Q$3)+1), ROWS(A$2:A19))),"")} -> 31-60 Days | H19: 18 | I19: {=IFERROR(INDEX(MTIB!$E$3:$E$1000, SMALL( IF((MTIB!$Q$3:$Q$1000<>"")*(MTIB!$Q$3:$Q$1000<>"Not Due"), ROW(MTIB!$Q$3:$Q$1000)-ROW(MTIB!$Q$3)+1), ROWS(A$2:A19))),"")} | J19: {=IFERROR(INDEX(MTIB!$B$3:$B$1000, SMALL( IF((MTIB!$Q$3:$Q$1000<>"")*(MTIB!$Q$3:$Q$1000<>"Not Due"), ROW(MTIB!$Q$3:$Q$1000)-ROW(MTIB!$Q$3)+1), ROWS(A$2:A19))),"")} | K19: {=IFERROR(INDEX(MTIB!$D$3:$D$1000, SMALL( IF((MTIB!$Q$3:$Q$1000<>"")*(MTIB!$Q$3:$Q$1000<>"Not Due"), ROW(MTIB!$Q$3:$Q$1000)-ROW(MTIB!$Q$3)+1), ROWS(A$2:A19))),"")} | L19: {=IFERROR(INDEX(MTIB!$G$3:$G$1000, SMALL( IF((MTIB!$Q$3:$Q$1000<>"")*(MTIB!$Q$3:$Q$1000<>"Not Due"), ROW(MTIB!$Q$3:$Q$1000)-ROW(MTIB!$Q$3)+1), ROWS(A$2:A19))),"")} | M19: {=IFERROR(INDEX(MTIB!$Q$3:$Q$1000, SMALL( IF((MTIB!$Q$3:$Q$1000<>"")*(MTIB!$Q$3:$Q$1000<>"Not Due"), ROW(MTIB!$Q$3:$Q$1000)-ROW(MTIB!$Q$3)+1), ROWS(A$2:A19)) ),"")} | O19: 18 | P19: {=IFERROR(INDEX(MPOB!$E$3:$E$1000, SMALL( IF((MPOB!$Q$3:$Q$1000<>"")*(MPOB!$Q$3:$Q$1000<>"Not Due"), ROW(MPOB!$Q$3:$Q$1000)-ROW(MPOB!$Q$3)+1), ROWS(A$2:A19))),"")} -> MPOB | Q19: {=IFERROR(INDEX(MPOB!$B$3:$B$1000, SMALL( IF((MPOB!$Q$3:$Q$1000<>"")*(MPOB!$Q$3:$Q$1000<>"Not Due"), ROW(MPOB!$Q$3:$Q$1000)-ROW(MPOB!$Q$3)+1), ROWS(A$2:A19))),"")} -> T/2026/00187 | R19: {=IFERROR(INDEX(MPOB!$D$3:$D$1000, SMALL( IF((MPOB!$Q$3:$Q$1000<>"")*(MPOB!$Q$3:$Q$1000<>"Not Due"), ROW(MPOB!$Q$3:$Q$1000)-ROW(MPOB!$Q$3)+1), ROWS(A$2:A19))),"")} -> MyFinancial | S19: {=IFERROR(INDEX(MPOB!$G$3:$G$1000, SMALL( IF((MPOB!$Q$3:$Q$1000<>"")*(MPOB!$Q$3:$Q$1000<>"Not Due"), ROW(MPOB!$Q$3:$Q$1000)-ROW(MPOB!$Q$3)+1), ROWS(A$2:A19))),"")} -> Nama User : Sabrina 0132241723 Date : 6/2/2026 Isu :Saya nk tanya sikit mengenai system myFas . Utk tab pesanan belian. Saya dh jana sebelum ni dan harini saya perasan butiran nya hilang. Jadi saya edit semula. Bila saya edit dan saya print ia masih ada. Kemudian bila saya tekan button simpan dan cari semula utk tekan POS saya view dia dah hilang 2/3 kali dah jadi LPO/FMDD0301/0126/00005 | T19: {=IFERROR(INDEX(MPOB!$Q$3:$Q$1000, SMALL( IF((MPOB!$Q$3:$Q$1000<>"")*(MPOB!$Q$3:$Q$1000<>"Not Due"), ROW(MPOB!$Q$3:$Q$1000)-ROW(MPOB!$Q$3)+1), ROWS(A$2:A19)) ),"")} -> >60 Days | V19: 18 | W19: {=IFERROR(INDEX(LKTN!$E$3:$E$1000, SMALL( IF((LKTN!$Q$3:$Q$1000<>"")*(LKTN!$Q$3:$Q$1000<>"Not Due"), ROW(LKTN!$Q$3:$Q$1000)-ROW(LKTN!$Q$3)+1), ROWS(A$2:A19))),"")} | X19: {=IFERROR(INDEX(LKTN!$B$3:$B$1000, SMALL( IF((LKTN!$Q$3:$Q$1000<>"")*(LKTN!$Q$3:$Q$1000<>"Not Due"), ROW(LKTN!$Q$3:$Q$1000)-ROW(LKTN!$Q$3)+1), ROWS(A$2:A19))),"")} | Y19: {=IFERROR(INDEX(LKTN!$D$3:$D$1000, SMALL( IF((LKTN!$Q$3:$Q$1000<>"")*(LKTN!$Q$3:$Q$1000<>"Not Due"), ROW(LKTN!$Q$3:$Q$1000)-ROW(LKTN!$Q$3)+1), ROWS(A$2:A19))),"")} | Z19: {=IFERROR(INDEX(LKTN!$G$3:$G$1000, SMALL( IF((LKTN!$Q$3:$Q$1000<>"")*(LKTN!$Q$3:$Q$1000<>"Not Due"), ROW(LKTN!$Q$3:$Q$1000)-ROW(LKTN!$Q$3)+1), ROWS(A$2:A19))),"")} | AA19: {=IFERROR(INDEX(LKTN!$Q$3:$Q$1000, SMALL( IF((LKTN!$Q$3:$Q$1000<>"")*(LKTN!$Q$3:$Q$1000<>"Not Due"), ROW(LKTN!$Q$3:$Q$1000)-ROW(LKTN!$Q$3)+1), ROWS(A$2:A19)) ),"")} | AJ19: 18 | AK19: {=IFERROR(INDEX(ISN!$E$3:$E$1000, SMALL( IF((ISN!$Q$3:$Q$1000<>"")*(ISN!$Q$3:$Q$1000<>"Not Due"), ROW(ISN!$Q$3:$Q$1000)-ROW(ISN!$Q$3)+1), ROWS(A$2:A19))),"")} | AL19: {=IFERROR(INDEX(ISN!$B$3:$B$1000, SMALL( IF((ISN!$Q$3:$Q$1000<>"")*(ISN!$Q$3:$Q$1000<>"Not Due"), ROW(ISN!$Q$3:$Q$1000)-ROW(ISN!$Q$3)+1), ROWS(A$2:A19))),"")} | AM19: {=IFERROR(INDEX(ISN!$D$3:$D$1000, SMALL( IF((ISN!$Q$3:$Q$1000<>"")*(ISN!$Q$3:$Q$1000<>"Not Due"), ROW(ISN!$Q$3:$Q$1000)-ROW(ISN!$Q$3)+1), ROWS(A$2:A19))),"")} | AN19: {=IFERROR(INDEX(ISN!$G$3:$G$1000, SMALL( IF((ISN!$Q$3:$Q$1000<>"")*(ISN!$Q$3:$Q$1000<>"Not Due"), ROW(ISN!$Q$3:$Q$1000)-ROW(ISN!$Q$3)+1), ROWS(A$2:A19))),"")} | AO19: {=IFERROR(INDEX(ISN!$Q$3:$Q$1000, SMALL( IF((ISN!$Q$3:$Q$1000<>"")*(ISN!$Q$3:$Q$1000<>"Not Due"), ROW(ISN!$Q$3:$Q$1000)-ROW(ISN!$Q$3)+1), ROWS(A$2:A19)) ),"")} | AQ19: 18 | AR19: {=IFERROR(INDEX(MSN!$E$3:$E$1000, SMALL( IF((MSN!$Q$3:$Q$1000<>"")*(MSN!$Q$3:$Q$1000<>"Not Due"), ROW(MSN!$Q$3:$Q$1000)-ROW(MSN!$Q$3)+1), ROWS(A$2:A19))),"")} | AS19: {=IFERROR(INDEX(MSN!$B$3:$B$1000, SMALL( IF((MSN!$Q$3:$Q$1000<>"")*(MSN!$Q$3:$Q$1000<>"Not Due"), ROW(MSN!$Q$3:$Q$1000)-ROW(MSN!$Q$3)+1), ROWS(A$2:A19))),"")} | AT19: {=IFERROR(INDEX(MSN!$D$3:$D$1000, SMALL( IF((MSN!$Q$3:$Q$1000<>"")*(MSN!$Q$3:$Q$1000<>"Not Due"), ROW(MSN!$Q$3:$Q$1000)-ROW(MSN!$Q$3)+1), ROWS(A$2:A19))),"")} | AU19: {=IFERROR(INDEX(MSN!$G$3:$G$1000, SMALL( IF((MSN!$Q$3:$Q$1000<>"")*(MSN!$Q$3:$Q$1000<>"Not Due"), ROW(MSN!$Q$3:$Q$1000)-ROW(MSN!$Q$3)+1), ROWS(A$2:A19))),"")} | AV19: {=IFERROR(INDEX(MSN!$Q$3:$Q$1000, SMALL( IF((MSN!$Q$3:$Q$1000<>"")*(MSN!$Q$3:$Q$1000<>"Not Due"), ROW(MSN!$Q$3:$Q$1000)-ROW(MSN!$Q$3)+1), ROWS(A$2:A19)) ),"")}
A20: 19 | B20: {=IFERROR(INDEX(FRIM!$E$3:$E$1000, SMALL(IF(FRIM!$Q$3:$Q$1000<>"", ROW(FRIM!$Q$3:$Q$1000)-ROW(FRIM!$Q$3)+1), ROWS(A$2:A20))),"")} -> FRIM | C20: {=IFERROR(INDEX(FRIM!$B$3:$B$1000, SMALL(IF(FRIM!$Q$3:$Q$1000<>"", ROW(FRIM!$Q$3:$Q$1000)-ROW(FRIM!$Q$3)+1), ROWS(A$2:A20))),"")} -> T/2026/00314 | D20: {=IFERROR(INDEX(FRIM!$D$3:$D$1000, SMALL(IF(FRIM!$Q$3:$Q$1000<>"", ROW(FRIM!$Q$3:$Q$1000)-ROW(FRIM!$Q$3)+1), ROWS(A$2:A20))),"")} -> MYASSET | E20: {=IFERROR(INDEX(FRIM!$G$3:$G$1000, SMALL(IF(FRIM!$Q$3:$Q$1000<>"", ROW(FRIM!$Q$3:$Q$1000)-ROW(FRIM!$Q$3)+1), ROWS(A$2:A20))),"")} -> W2546 27 April 2026 EMYLIA BINTI AYOUB modul konfigurasi capaian pengguna, admin telah membuat pendaftaran baru untuk 2 orang pegawai iaitu: 1. dr mohd faridzuan bin majid [3874] 2. noor amira binti mohd kasim (3858). semakan mendapati paparan capaian modul sistem pegawai berkenaan berjaya dilakukan oleh admin tetapi apabila pegawai cuba untuk melayari portal myasset notifikasi "server error in'/myasset' application" terpapar. mohon untuk dibuat semakan. | F20: {=IFERROR(INDEX(FRIM!$Q$3:$Q$1000, SMALL(IF(FRIM!$Q$3:$Q$1000<>"", ROW(FRIM!$Q$3:$Q$1000)-ROW(FRIM!$Q$3)+1), ROWS(A$2:A20))),"")} -> 31-60 Days | H20: 19 | I20: {=IFERROR(INDEX(MTIB!$E$3:$E$1000, SMALL( IF((MTIB!$Q$3:$Q$1000<>"")*(MTIB!$Q$3:$Q$1000<>"Not Due"), ROW(MTIB!$Q$3:$Q$1000)-ROW(MTIB!$Q$3)+1), ROWS(A$2:A20))),"")} | J20: {=IFERROR(INDEX(MTIB!$B$3:$B$1000, SMALL( IF((MTIB!$Q$3:$Q$1000<>"")*(MTIB!$Q$3:$Q$1000<>"Not Due"), ROW(MTIB!$Q$3:$Q$1000)-ROW(MTIB!$Q$3)+1), ROWS(A$2:A20))),"")} | K20: {=IFERROR(INDEX(MTIB!$D$3:$D$1000, SMALL( IF((MTIB!$Q$3:$Q$1000<>"")*(MTIB!$Q$3:$Q$1000<>"Not Due"), ROW(MTIB!$Q$3:$Q$1000)-ROW(MTIB!$Q$3)+1), ROWS(A$2:A20))),"")} | L20: {=IFERROR(INDEX(MTIB!$G$3:$G$1000, SMALL( IF((MTIB!$Q$3:$Q$1000<>"")*(MTIB!$Q$3:$Q$1000<>"Not Due"), ROW(MTIB!$Q$3:$Q$1000)-ROW(MTIB!$Q$3)+1), ROWS(A$2:A20))),"")} | M20: {=IFERROR(INDEX(MTIB!$Q$3:$Q$1000, SMALL( IF((MTIB!$Q$3:$Q$1000<>"")*(MTIB!$Q$3:$Q$1000<>"Not Due"), ROW(MTIB!$Q$3:$Q$1000)-ROW(MTIB!$Q$3)+1), ROWS(A$2:A20)) ),"")} | O20: 19 | P20: {=IFERROR(INDEX(MPOB!$E$3:$E$1000, SMALL( IF((MPOB!$Q$3:$Q$1000<>"")*(MPOB!$Q$3:$Q$1000<>"Not Due"), ROW(MPOB!$Q$3:$Q$1000)-ROW(MPOB!$Q$3)+1), ROWS(A$2:A20))),"")} -> MPOB | Q20: {=IFERROR(INDEX(MPOB!$B$3:$B$1000, SMALL( IF((MPOB!$Q$3:$Q$1000<>"")*(MPOB!$Q$3:$Q$1000<>"Not Due"), ROW(MPOB!$Q$3:$Q$1000)-ROW(MPOB!$Q$3)+1), ROWS(A$2:A20))),"")} -> T/2026/00198 | R20: {=IFERROR(INDEX(MPOB!$D$3:$D$1000, SMALL( IF((MPOB!$Q$3:$Q$1000<>"")*(MPOB!$Q$3:$Q$1000<>"Not Due"), ROW(MPOB!$Q$3:$Q$1000)-ROW(MPOB!$Q$3)+1), ROWS(A$2:A20))),"")} -> MyAsset | S20: {=IFERROR(INDEX(MPOB!$G$3:$G$1000, SMALL( IF((MPOB!$Q$3:$Q$1000<>"")*(MPOB!$Q$3:$Q$1000<>"Not Due"), ROW(MPOB!$Q$3:$Q$1000)-ROW(MPOB!$Q$3)+1), ROWS(A$2:A20))),"")} -> Nama User : 60182583185 Date : 11/2/2026 Isu : boleh semakkan kenapa syor kaedah pelupusan dari ketua pengarah tak keluar bila nak cetak borang? bila view dari sistem status pemeriksaan ni dah diluluskan oleh ketua pengarah | T20: {=IFERROR(INDEX(MPOB!$Q$3:$Q$1000, SMALL( IF((MPOB!$Q$3:$Q$1000<>"")*(MPOB!$Q$3:$Q$1000<>"Not Due"), ROW(MPOB!$Q$3:$Q$1000)-ROW(MPOB!$Q$3)+1), ROWS(A$2:A20)) ),"")} -> >60 Days | V20: 19 | W20: {=IFERROR(INDEX(LKTN!$E$3:$E$1000, SMALL( IF((LKTN!$Q$3:$Q$1000<>"")*(LKTN!$Q$3:$Q$1000<>"Not Due"), ROW(LKTN!$Q$3:$Q$1000)-ROW(LKTN!$Q$3)+1), ROWS(A$2:A20))),"")} | X20: {=IFERROR(INDEX(LKTN!$B$3:$B$1000, SMALL( IF((LKTN!$Q$3:$Q$1000<>"")*(LKTN!$Q$3:$Q$1000<>"Not Due"), ROW(LKTN!$Q$3:$Q$1000)-ROW(LKTN!$Q$3)+1), ROWS(A$2:A20))),"")} | Y20: {=IFERROR(INDEX(LKTN!$D$3:$D$1000, SMALL( IF((LKTN!$Q$3:$Q$1000<>"")*(LKTN!$Q$3:$Q$1000<>"Not Due"), ROW(LKTN!$Q$3:$Q$1000)-ROW(LKTN!$Q$3)+1), ROWS(A$2:A20))),"")} | Z20: {=IFERROR(INDEX(LKTN!$G$3:$G$1000, SMALL( IF((LKTN!$Q$3:$Q$1000<>"")*(LKTN!$Q$3:$Q$1000<>"Not Due"), ROW(LKTN!$Q$3:$Q$1000)-ROW(LKTN!$Q$3)+1), ROWS(A$2:A20))),"")} | AA20: {=IFERROR(INDEX(LKTN!$Q$3:$Q$1000, SMALL( IF((LKTN!$Q$3:$Q$1000<>"")*(LKTN!$Q$3:$Q$1000<>"Not Due"), ROW(LKTN!$Q$3:$Q$1000)-ROW(LKTN!$Q$3)+1), ROWS(A$2:A20)) ),"")} | AJ20: 19 | AK20: {=IFERROR(INDEX(ISN!$E$3:$E$1000, SMALL( IF((ISN!$Q$3:$Q$1000<>"")*(ISN!$Q$3:$Q$1000<>"Not Due"), ROW(ISN!$Q$3:$Q$1000)-ROW(ISN!$Q$3)+1), ROWS(A$2:A20))),"")} | AL20: {=IFERROR(INDEX(ISN!$B$3:$B$1000, SMALL( IF((ISN!$Q$3:$Q$1000<>"")*(ISN!$Q$3:$Q$1000<>"Not Due"), ROW(ISN!$Q$3:$Q$1000)-ROW(ISN!$Q$3)+1), ROWS(A$2:A20))),"")} | AM20: {=IFERROR(INDEX(ISN!$D$3:$D$1000, SMALL( IF((ISN!$Q$3:$Q$1000<>"")*(ISN!$Q$3:$Q$1000<>"Not Due"), ROW(ISN!$Q$3:$Q$1000)-ROW(ISN!$Q$3)+1), ROWS(A$2:A20))),"")} | AN20: {=IFERROR(INDEX(ISN!$G$3:$G$1000, SMALL( IF((ISN!$Q$3:$Q$1000<>"")*(ISN!$Q$3:$Q$1000<>"Not Due"), ROW(ISN!$Q$3:$Q$1000)-ROW(ISN!$Q$3)+1), ROWS(A$2:A20))),"")} | AO20: {=IFERROR(INDEX(ISN!$Q$3:$Q$1000, SMALL( IF((ISN!$Q$3:$Q$1000<>"")*(ISN!$Q$3:$Q$1000<>"Not Due"), ROW(ISN!$Q$3:$Q$1000)-ROW(ISN!$Q$3)+1), ROWS(A$2:A20)) ),"")} | AQ20: 19 | AR20: {=IFERROR(INDEX(MSN!$E$3:$E$1000, SMALL( IF((MSN!$Q$3:$Q$1000<>"")*(MSN!$Q$3:$Q$1000<>"Not Due"), ROW(MSN!$Q$3:$Q$1000)-ROW(MSN!$Q$3)+1), ROWS(A$2:A20))),"")} | AS20: {=IFERROR(INDEX(MSN!$B$3:$B$1000, SMALL( IF((MSN!$Q$3:$Q$1000<>"")*(MSN!$Q$3:$Q$1000<>"Not Due"), ROW(MSN!$Q$3:$Q$1000)-ROW(MSN!$Q$3)+1), ROWS(A$2:A20))),"")} | AT20: {=IFERROR(INDEX(MSN!$D$3:$D$1000, SMALL( IF((MSN!$Q$3:$Q$1000<>"")*(MSN!$Q$3:$Q$1000<>"Not Due"), ROW(MSN!$Q$3:$Q$1000)-ROW(MSN!$Q$3)+1), ROWS(A$2:A20))),"")} | AU20: {=IFERROR(INDEX(MSN!$G$3:$G$1000, SMALL( IF((MSN!$Q$3:$Q$1000<>"")*(MSN!$Q$3:$Q$1000<>"Not Due"), ROW(MSN!$Q$3:$Q$1000)-ROW(MSN!$Q$3)+1), ROWS(A$2:A20))),"")} | AV20: {=IFERROR(INDEX(MSN!$Q$3:$Q$1000, SMALL( IF((MSN!$Q$3:$Q$1000<>"")*(MSN!$Q$3:$Q$1000<>"Not Due"), ROW(MSN!$Q$3:$Q$1000)-ROW(MSN!$Q$3)+1), ROWS(A$2:A20)) ),"")}
A21: 20 | B21: {=IFERROR(INDEX(FRIM!$E$3:$E$1000, SMALL(IF(FRIM!$Q$3:$Q$1000<>"", ROW(FRIM!$Q$3:$Q$1000)-ROW(FRIM!$Q$3)+1), ROWS(A$2:A21))),"")} -> FRIM | C21: {=IFERROR(INDEX(FRIM!$B$3:$B$1000, SMALL(IF(FRIM!$Q$3:$Q$1000<>"", ROW(FRIM!$Q$3:$Q$1000)-ROW(FRIM!$Q$3)+1), ROWS(A$2:A21))),"")} -> T/2026/00316 | D21: {=IFERROR(INDEX(FRIM!$D$3:$D$1000, SMALL(IF(FRIM!$Q$3:$Q$1000<>"", ROW(FRIM!$Q$3:$Q$1000)-ROW(FRIM!$Q$3)+1), ROWS(A$2:A21))),"")} -> MYINVENTORY | E21: {=IFERROR(INDEX(FRIM!$G$3:$G$1000, SMALL(IF(FRIM!$Q$3:$Q$1000<>"", ROW(FRIM!$Q$3:$Q$1000)-ROW(FRIM!$Q$3)+1), ROWS(A$2:A21))),"")} -> W2533 08 April 2026 NURFAIEZAH BT. MAZERI mohon bantuan untuk email seperti ini myinventory: status permohonan pengeluaran item (26-04031) masuk ke email saya. untuk makluman, saya juga menjawab email enquiry dan feedback yang mencapai lebih dari 100 email. | F21: {=IFERROR(INDEX(FRIM!$Q$3:$Q$1000, SMALL(IF(FRIM!$Q$3:$Q$1000<>"", ROW(FRIM!$Q$3:$Q$1000)-ROW(FRIM!$Q$3)+1), ROWS(A$2:A21))),"")} -> 31-60 Days | H21: 20 | I21: {=IFERROR(INDEX(MTIB!$E$3:$E$1000, SMALL( IF((MTIB!$Q$3:$Q$1000<>"")*(MTIB!$Q$3:$Q$1000<>"Not Due"), ROW(MTIB!$Q$3:$Q$1000)-ROW(MTIB!$Q$3)+1), ROWS(A$2:A21))),"")} | J21: {=IFERROR(INDEX(MTIB!$B$3:$B$1000, SMALL( IF((MTIB!$Q$3:$Q$1000<>"")*(MTIB!$Q$3:$Q$1000<>"Not Due"), ROW(MTIB!$Q$3:$Q$1000)-ROW(MTIB!$Q$3)+1), ROWS(A$2:A21))),"")} | K21: {=IFERROR(INDEX(MTIB!$D$3:$D$1000, SMALL( IF((MTIB!$Q$3:$Q$1000<>"")*(MTIB!$Q$3:$Q$1000<>"Not Due"), ROW(MTIB!$Q$3:$Q$1000)-ROW(MTIB!$Q$3)+1), ROWS(A$2:A21))),"")} | L21: {=IFERROR(INDEX(MTIB!$G$3:$G$1000, SMALL( IF((MTIB!$Q$3:$Q$1000<>"")*(MTIB!$Q$3:$Q$1000<>"Not Due"), ROW(MTIB!$Q$3:$Q$1000)-ROW(MTIB!$Q$3)+1), ROWS(A$2:A21))),"")} | M21: {=IFERROR(INDEX(MTIB!$Q$3:$Q$1000, SMALL( IF((MTIB!$Q$3:$Q$1000<>"")*(MTIB!$Q$3:$Q$1000<>"Not Due"), ROW(MTIB!$Q$3:$Q$1000)-ROW(MTIB!$Q$3)+1), ROWS(A$2:A21)) ),"")} | O21: 20 | P21: {=IFERROR(INDEX(MPOB!$E$3:$E$1000, SMALL( IF((MPOB!$Q$3:$Q$1000<>"")*(MPOB!$Q$3:$Q$1000<>"Not Due"), ROW(MPOB!$Q$3:$Q$1000)-ROW(MPOB!$Q$3)+1), ROWS(A$2:A21))),"")} -> MPOB | Q21: {=IFERROR(INDEX(MPOB!$B$3:$B$1000, SMALL( IF((MPOB!$Q$3:$Q$1000<>"")*(MPOB!$Q$3:$Q$1000<>"Not Due"), ROW(MPOB!$Q$3:$Q$1000)-ROW(MPOB!$Q$3)+1), ROWS(A$2:A21))),"")} -> T/2026/00223 | R21: {=IFERROR(INDEX(MPOB!$D$3:$D$1000, SMALL( IF((MPOB!$Q$3:$Q$1000<>"")*(MPOB!$Q$3:$Q$1000<>"Not Due"), ROW(MPOB!$Q$3:$Q$1000)-ROW(MPOB!$Q$3)+1), ROWS(A$2:A21))),"")} -> MyFinancial | S21: {=IFERROR(INDEX(MPOB!$G$3:$G$1000, SMALL( IF((MPOB!$Q$3:$Q$1000<>"")*(MPOB!$Q$3:$Q$1000<>"Not Due"), ROW(MPOB!$Q$3:$Q$1000)-ROW(MPOB!$Q$3)+1), ROWS(A$2:A21))),"")} -> vocher : 09319 tak boleh post dalam modul kelulusan VOUCHER. | T21: {=IFERROR(INDEX(MPOB!$Q$3:$Q$1000, SMALL( IF((MPOB!$Q$3:$Q$1000<>"")*(MPOB!$Q$3:$Q$1000<>"Not Due"), ROW(MPOB!$Q$3:$Q$1000)-ROW(MPOB!$Q$3)+1), ROWS(A$2:A21)) ),"")} -> >60 Days | V21: 20 | W21: {=IFERROR(INDEX(LKTN!$E$3:$E$1000, SMALL( IF((LKTN!$Q$3:$Q$1000<>"")*(LKTN!$Q$3:$Q$1000<>"Not Due"), ROW(LKTN!$Q$3:$Q$1000)-ROW(LKTN!$Q$3)+1), ROWS(A$2:A21))),"")} | X21: {=IFERROR(INDEX(LKTN!$B$3:$B$1000, SMALL( IF((LKTN!$Q$3:$Q$1000<>"")*(LKTN!$Q$3:$Q$1000<>"Not Due"), ROW(LKTN!$Q$3:$Q$1000)-ROW(LKTN!$Q$3)+1), ROWS(A$2:A21))),"")} | Y21: {=IFERROR(INDEX(LKTN!$D$3:$D$1000, SMALL( IF((LKTN!$Q$3:$Q$1000<>"")*(LKTN!$Q$3:$Q$1000<>"Not Due"), ROW(LKTN!$Q$3:$Q$1000)-ROW(LKTN!$Q$3)+1), ROWS(A$2:A21))),"")} | Z21: {=IFERROR(INDEX(LKTN!$G$3:$G$1000, SMALL( IF((LKTN!$Q$3:$Q$1000<>"")*(LKTN!$Q$3:$Q$1000<>"Not Due"), ROW(LKTN!$Q$3:$Q$1000)-ROW(LKTN!$Q$3)+1), ROWS(A$2:A21))),"")} | AA21: {=IFERROR(INDEX(LKTN!$Q$3:$Q$1000, SMALL( IF((LKTN!$Q$3:$Q$1000<>"")*(LKTN!$Q$3:$Q$1000<>"Not Due"), ROW(LKTN!$Q$3:$Q$1000)-ROW(LKTN!$Q$3)+1), ROWS(A$2:A21)) ),"")} | AJ21: 20 | AK21: {=IFERROR(INDEX(ISN!$E$3:$E$1000, SMALL( IF((ISN!$Q$3:$Q$1000<>"")*(ISN!$Q$3:$Q$1000<>"Not Due"), ROW(ISN!$Q$3:$Q$1000)-ROW(ISN!$Q$3)+1), ROWS(A$2:A21))),"")} | AL21: {=IFERROR(INDEX(ISN!$B$3:$B$1000, SMALL( IF((ISN!$Q$3:$Q$1000<>"")*(ISN!$Q$3:$Q$1000<>"Not Due"), ROW(ISN!$Q$3:$Q$1000)-ROW(ISN!$Q$3)+1), ROWS(A$2:A21))),"")} | AM21: {=IFERROR(INDEX(ISN!$D$3:$D$1000, SMALL( IF((ISN!$Q$3:$Q$1000<>"")*(ISN!$Q$3:$Q$1000<>"Not Due"), ROW(ISN!$Q$3:$Q$1000)-ROW(ISN!$Q$3)+1), ROWS(A$2:A21))),"")} | AN21: {=IFERROR(INDEX(ISN!$G$3:$G$1000, SMALL( IF((ISN!$Q$3:$Q$1000<>"")*(ISN!$Q$3:$Q$1000<>"Not Due"), ROW(ISN!$Q$3:$Q$1000)-ROW(ISN!$Q$3)+1), ROWS(A$2:A21))),"")} | AO21: {=IFERROR(INDEX(ISN!$Q$3:$Q$1000, SMALL( IF((ISN!$Q$3:$Q$1000<>"")*(ISN!$Q$3:$Q$1000<>"Not Due"), ROW(ISN!$Q$3:$Q$1000)-ROW(ISN!$Q$3)+1), ROWS(A$2:A21)) ),"")} | AQ21: 20 | AR21: {=IFERROR(INDEX(MSN!$E$3:$E$1000, SMALL( IF((MSN!$Q$3:$Q$1000<>"")*(MSN!$Q$3:$Q$1000<>"Not Due"), ROW(MSN!$Q$3:$Q$1000)-ROW(MSN!$Q$3)+1), ROWS(A$2:A21))),"")} | AS21: {=IFERROR(INDEX(MSN!$B$3:$B$1000, SMALL( IF((MSN!$Q$3:$Q$1000<>"")*(MSN!$Q$3:$Q$1000<>"Not Due"), ROW(MSN!$Q$3:$Q$1000)-ROW(MSN!$Q$3)+1), ROWS(A$2:A21))),"")} | AT21: {=IFERROR(INDEX(MSN!$D$3:$D$1000, SMALL( IF((MSN!$Q$3:$Q$1000<>"")*(MSN!$Q$3:$Q$1000<>"Not Due"), ROW(MSN!$Q$3:$Q$1000)-ROW(MSN!$Q$3)+1), ROWS(A$2:A21))),"")} | AU21: {=IFERROR(INDEX(MSN!$G$3:$G$1000, SMALL( IF((MSN!$Q$3:$Q$1000<>"")*(MSN!$Q$3:$Q$1000<>"Not Due"), ROW(MSN!$Q$3:$Q$1000)-ROW(MSN!$Q$3)+1), ROWS(A$2:A21))),"")} | AV21: {=IFERROR(INDEX(MSN!$Q$3:$Q$1000, SMALL( IF((MSN!$Q$3:$Q$1000<>"")*(MSN!$Q$3:$Q$1000<>"Not Due"), ROW(MSN!$Q$3:$Q$1000)-ROW(MSN!$Q$3)+1), ROWS(A$2:A21)) ),"")}
A22: 21 | B22: {=IFERROR(INDEX(FRIM!$E$3:$E$1000, SMALL(IF(FRIM!$Q$3:$Q$1000<>"", ROW(FRIM!$Q$3:$Q$1000)-ROW(FRIM!$Q$3)+1), ROWS(A$2:A22))),"")} -> FRIM | C22: {=IFERROR(INDEX(FRIM!$B$3:$B$1000, SMALL(IF(FRIM!$Q$3:$Q$1000<>"", ROW(FRIM!$Q$3:$Q$1000)-ROW(FRIM!$Q$3)+1), ROWS(A$2:A22))),"")} -> T/2026/00328 | D22: {=IFERROR(INDEX(FRIM!$D$3:$D$1000, SMALL(IF(FRIM!$Q$3:$Q$1000<>"", ROW(FRIM!$Q$3:$Q$1000)-ROW(FRIM!$Q$3)+1), ROWS(A$2:A22))),"")} -> MYASSET | E22: {=IFERROR(INDEX(FRIM!$G$3:$G$1000, SMALL(IF(FRIM!$Q$3:$Q$1000<>"", ROW(FRIM!$Q$3:$Q$1000)-ROW(FRIM!$Q$3)+1), ROWS(A$2:A22))),"")} -> W2550 29 April 2026 SAILESUZE BT. MOHD SALIM mohon semak kenapa label aset tidak boleh di print. ada keluar paparan "access to the path 'c:\inetpub\wwwroot\myasset\laporan_myasset\2da2wn x35eig0k1ko0aqea4p.pdf' is denied sama juga dengan penyata laporan ikut kategori, ikut penempatan,ikut dana, ikut kakitangan dan senarai aset juga tidak boleh di print | F22: {=IFERROR(INDEX(FRIM!$Q$3:$Q$1000, SMALL(IF(FRIM!$Q$3:$Q$1000<>"", ROW(FRIM!$Q$3:$Q$1000)-ROW(FRIM!$Q$3)+1), ROWS(A$2:A22))),"")} -> 31-60 Days | H22: 21 | I22: {=IFERROR(INDEX(MTIB!$E$3:$E$1000, SMALL( IF((MTIB!$Q$3:$Q$1000<>"")*(MTIB!$Q$3:$Q$1000<>"Not Due"), ROW(MTIB!$Q$3:$Q$1000)-ROW(MTIB!$Q$3)+1), ROWS(A$2:A22))),"")} | J22: {=IFERROR(INDEX(MTIB!$B$3:$B$1000, SMALL( IF((MTIB!$Q$3:$Q$1000<>"")*(MTIB!$Q$3:$Q$1000<>"Not Due"), ROW(MTIB!$Q$3:$Q$1000)-ROW(MTIB!$Q$3)+1), ROWS(A$2:A22))),"")} | K22: {=IFERROR(INDEX(MTIB!$D$3:$D$1000, SMALL( IF((MTIB!$Q$3:$Q$1000<>"")*(MTIB!$Q$3:$Q$1000<>"Not Due"), ROW(MTIB!$Q$3:$Q$1000)-ROW(MTIB!$Q$3)+1), ROWS(A$2:A22))),"")} | L22: {=IFERROR(INDEX(MTIB!$G$3:$G$1000, SMALL( IF((MTIB!$Q$3:$Q$1000<>"")*(MTIB!$Q$3:$Q$1000<>"Not Due"), ROW(MTIB!$Q$3:$Q$1000)-ROW(MTIB!$Q$3)+1), ROWS(A$2:A22))),"")} | M22: {=IFERROR(INDEX(MTIB!$Q$3:$Q$1000, SMALL( IF((MTIB!$Q$3:$Q$1000<>"")*(MTIB!$Q$3:$Q$1000<>"Not Due"), ROW(MTIB!$Q$3:$Q$1000)-ROW(MTIB!$Q$3)+1), ROWS(A$2:A22)) ),"")} | O22: 21 | P22: {=IFERROR(INDEX(MPOB!$E$3:$E$1000, SMALL( IF((MPOB!$Q$3:$Q$1000<>"")*(MPOB!$Q$3:$Q$1000<>"Not Due"), ROW(MPOB!$Q$3:$Q$1000)-ROW(MPOB!$Q$3)+1), ROWS(A$2:A22))),"")} -> MPOB | Q22: {=IFERROR(INDEX(MPOB!$B$3:$B$1000, SMALL( IF((MPOB!$Q$3:$Q$1000<>"")*(MPOB!$Q$3:$Q$1000<>"Not Due"), ROW(MPOB!$Q$3:$Q$1000)-ROW(MPOB!$Q$3)+1), ROWS(A$2:A22))),"")} -> T/2026/00235 | R22: {=IFERROR(INDEX(MPOB!$D$3:$D$1000, SMALL( IF((MPOB!$Q$3:$Q$1000<>"")*(MPOB!$Q$3:$Q$1000<>"Not Due"), ROW(MPOB!$Q$3:$Q$1000)-ROW(MPOB!$Q$3)+1), ROWS(A$2:A22))),"")} -> MyFinancial | S22: {=IFERROR(INDEX(MPOB!$G$3:$G$1000, SMALL( IF((MPOB!$Q$3:$Q$1000<>"")*(MPOB!$Q$3:$Q$1000<>"Not Due"), ROW(MPOB!$Q$3:$Q$1000)-ROW(MPOB!$Q$3)+1), ROWS(A$2:A22))),"")} -> SEMASA PENGESAHAN RESIT - MAKLUMAT BIL DAN AMAUN BAYARAN TIDAK APPEAR - RUJUK RESIT NO RCPFMDD/0225/10615 | T22: {=IFERROR(INDEX(MPOB!$Q$3:$Q$1000, SMALL( IF((MPOB!$Q$3:$Q$1000<>"")*(MPOB!$Q$3:$Q$1000<>"Not Due"), ROW(MPOB!$Q$3:$Q$1000)-ROW(MPOB!$Q$3)+1), ROWS(A$2:A22)) ),"")} -> >60 Days | V22: 21 | W22: {=IFERROR(INDEX(LKTN!$E$3:$E$1000, SMALL( IF((LKTN!$Q$3:$Q$1000<>"")*(LKTN!$Q$3:$Q$1000<>"Not Due"), ROW(LKTN!$Q$3:$Q$1000)-ROW(LKTN!$Q$3)+1), ROWS(A$2:A22))),"")} | X22: {=IFERROR(INDEX(LKTN!$B$3:$B$1000, SMALL( IF((LKTN!$Q$3:$Q$1000<>"")*(LKTN!$Q$3:$Q$1000<>"Not Due"), ROW(LKTN!$Q$3:$Q$1000)-ROW(LKTN!$Q$3)+1), ROWS(A$2:A22))),"")} | Y22: {=IFERROR(INDEX(LKTN!$D$3:$D$1000, SMALL( IF((LKTN!$Q$3:$Q$1000<>"")*(LKTN!$Q$3:$Q$1000<>"Not Due"), ROW(LKTN!$Q$3:$Q$1000)-ROW(LKTN!$Q$3)+1), ROWS(A$2:A22))),"")} | Z22: {=IFERROR(INDEX(LKTN!$G$3:$G$1000, SMALL( IF((LKTN!$Q$3:$Q$1000<>"")*(LKTN!$Q$3:$Q$1000<>"Not Due"), ROW(LKTN!$Q$3:$Q$1000)-ROW(LKTN!$Q$3)+1), ROWS(A$2:A22))),"")} | AA22: {=IFERROR(INDEX(LKTN!$Q$3:$Q$1000, SMALL( IF((LKTN!$Q$3:$Q$1000<>"")*(LKTN!$Q$3:$Q$1000<>"Not Due"), ROW(LKTN!$Q$3:$Q$1000)-ROW(LKTN!$Q$3)+1), ROWS(A$2:A22)) ),"")} | AJ22: 21 | AK22: {=IFERROR(INDEX(ISN!$E$3:$E$1000, SMALL( IF((ISN!$Q$3:$Q$1000<>"")*(ISN!$Q$3:$Q$1000<>"Not Due"), ROW(ISN!$Q$3:$Q$1000)-ROW(ISN!$Q$3)+1), ROWS(A$2:A22))),"")} | AL22: {=IFERROR(INDEX(ISN!$B$3:$B$1000, SMALL( IF((ISN!$Q$3:$Q$1000<>"")*(ISN!$Q$3:$Q$1000<>"Not Due"), ROW(ISN!$Q$3:$Q$1000)-ROW(ISN!$Q$3)+1), ROWS(A$2:A22))),"")} | AM22: {=IFERROR(INDEX(ISN!$D$3:$D$1000, SMALL( IF((ISN!$Q$3:$Q$1000<>"")*(ISN!$Q$3:$Q$1000<>"Not Due"), ROW(ISN!$Q$3:$Q$1000)-ROW(ISN!$Q$3)+1), ROWS(A$2:A22))),"")} | AN22: {=IFERROR(INDEX(ISN!$G$3:$G$1000, SMALL( IF((ISN!$Q$3:$Q$1000<>"")*(ISN!$Q$3:$Q$1000<>"Not Due"), ROW(ISN!$Q$3:$Q$1000)-ROW(ISN!$Q$3)+1), ROWS(A$2:A22))),"")} | AO22: {=IFERROR(INDEX(ISN!$Q$3:$Q$1000, SMALL( IF((ISN!$Q$3:$Q$1000<>"")*(ISN!$Q$3:$Q$1000<>"Not Due"), ROW(ISN!$Q$3:$Q$1000)-ROW(ISN!$Q$3)+1), ROWS(A$2:A22)) ),"")} | AQ22: 21 | AR22: {=IFERROR(INDEX(MSN!$E$3:$E$1000, SMALL( IF((MSN!$Q$3:$Q$1000<>"")*(MSN!$Q$3:$Q$1000<>"Not Due"), ROW(MSN!$Q$3:$Q$1000)-ROW(MSN!$Q$3)+1), ROWS(A$2:A22))),"")} | AS22: {=IFERROR(INDEX(MSN!$B$3:$B$1000, SMALL( IF((MSN!$Q$3:$Q$1000<>"")*(MSN!$Q$3:$Q$1000<>"Not Due"), ROW(MSN!$Q$3:$Q$1000)-ROW(MSN!$Q$3)+1), ROWS(A$2:A22))),"")} | AT22: {=IFERROR(INDEX(MSN!$D$3:$D$1000, SMALL( IF((MSN!$Q$3:$Q$1000<>"")*(MSN!$Q$3:$Q$1000<>"Not Due"), ROW(MSN!$Q$3:$Q$1000)-ROW(MSN!$Q$3)+1), ROWS(A$2:A22))),"")} | AU22: {=IFERROR(INDEX(MSN!$G$3:$G$1000, SMALL( IF((MSN!$Q$3:$Q$1000<>"")*(MSN!$Q$3:$Q$1000<>"Not Due"), ROW(MSN!$Q$3:$Q$1000)-ROW(MSN!$Q$3)+1), ROWS(A$2:A22))),"")} | AV22: {=IFERROR(INDEX(MSN!$Q$3:$Q$1000, SMALL( IF((MSN!$Q$3:$Q$1000<>"")*(MSN!$Q$3:$Q$1000<>"Not Due"), ROW(MSN!$Q$3:$Q$1000)-ROW(MSN!$Q$3)+1), ROWS(A$2:A22)) ),"")}
... A30: 29 | B30: {=IFERROR(INDEX(FRIM!$E$3:$E$1000, SMALL(IF(FRIM!$Q$3:$Q$1000<>"", ROW(FRIM!$Q$3:$Q$1000)-ROW(FRIM!$Q$3)+1), ROWS(A$2:A30))),"")} -> FRIM | C30: {=IFERROR(INDEX(FRIM!$B$3:$B$1000, SMALL(IF(FRIM!$Q$3:$Q$1000<>"", ROW(FRIM!$Q$3:$Q$1000)-ROW(FRIM!$Q$3)+1), ROWS(A$2:A30))),"")} -> T/2026/00446 | D30: {=IFERROR(INDEX(FRIM!$D$3:$D$1000, SMALL(IF(FRIM!$Q$3:$Q$1000<>"", ROW(FRIM!$Q$3:$Q$1000)-ROW(FRIM!$Q$3)+1), ROWS(A$2:A30))),"")} -> MYASSET | E30: {=IFERROR(INDEX(FRIM!$G$3:$G$1000, SMALL(IF(FRIM!$Q$3:$Q$1000<>"", ROW(FRIM!$Q$3:$Q$1000)-ROW(FRIM!$Q$3)+1), ROWS(A$2:A30))),"")} -> W2411 26/05/2025 ZAINORASRI B. YAHYA MAKLUMAT NO. ASET DIDALAM EMAIL MAKLUMAN SERAHAN ASET TIDAK SAMA DENGAN ASET SEBENAR YANG DISERAHKAN. CONTOH SERAHAN ASET NO. 005053 TETAPI KELUAR NO 005705 DIDALAM EMAIL. ADUAN LAMA T/2026/00100 SW TIDAK MAHU BUKA SEMULA, DAN ADUAN BARU DIBUAT. | F30: {=IFERROR(INDEX(FRIM!$Q$3:$Q$1000, SMALL(IF(FRIM!$Q$3:$Q$1000<>"", ROW(FRIM!$Q$3:$Q$1000)-ROW(FRIM!$Q$3)+1), ROWS(A$2:A30))),"")} -> 1-30 Days | H30: 29 | I30: {=IFERROR(INDEX(MTIB!$E$3:$E$1000, SMALL( IF((MTIB!$Q$3:$Q$1000<>"")*(MTIB!$Q$3:$Q$1000<>"Not Due"), ROW(MTIB!$Q$3:$Q$1000)-ROW(MTIB!$Q$3)+1), ROWS(A$2:A30))),"")} | J30: {=IFERROR(INDEX(MTIB!$B$3:$B$1000, SMALL( IF((MTIB!$Q$3:$Q$1000<>"")*(MTIB!$Q$3:$Q$1000<>"Not Due"), ROW(MTIB!$Q$3:$Q$1000)-ROW(MTIB!$Q$3)+1), ROWS(A$2:A30))),"")} | K30: {=IFERROR(INDEX(MTIB!$D$3:$D$1000, SMALL( IF((MTIB!$Q$3:$Q$1000<>"")*(MTIB!$Q$3:$Q$1000<>"Not Due"), ROW(MTIB!$Q$3:$Q$1000)-ROW(MTIB!$Q$3)+1), ROWS(A$2:A30))),"")} | L30: {=IFERROR(INDEX(MTIB!$G$3:$G$1000, SMALL( IF((MTIB!$Q$3:$Q$1000<>"")*(MTIB!$Q$3:$Q$1000<>"Not Due"), ROW(MTIB!$Q$3:$Q$1000)-ROW(MTIB!$Q$3)+1), ROWS(A$2:A30))),"")} | M30: {=IFERROR(INDEX(MTIB!$Q$3:$Q$1000, SMALL( IF((MTIB!$Q$3:$Q$1000<>"")*(MTIB!$Q$3:$Q$1000<>"Not Due"), ROW(MTIB!$Q$3:$Q$1000)-ROW(MTIB!$Q$3)+1), ROWS(A$2:A30)) ),"")} | O30: 29 | P30: {=IFERROR(INDEX(MPOB!$E$3:$E$1000, SMALL( IF((MPOB!$Q$3:$Q$1000<>"")*(MPOB!$Q$3:$Q$1000<>"Not Due"), ROW(MPOB!$Q$3:$Q$1000)-ROW(MPOB!$Q$3)+1), ROWS(A$2:A30))),"")} -> MPOB | Q30: {=IFERROR(INDEX(MPOB!$B$3:$B$1000, SMALL( IF((MPOB!$Q$3:$Q$1000<>"")*(MPOB!$Q$3:$Q$1000<>"Not Due"), ROW(MPOB!$Q$3:$Q$1000)-ROW(MPOB!$Q$3)+1), ROWS(A$2:A30))),"")} -> T/2026/00289 | R30: {=IFERROR(INDEX(MPOB!$D$3:$D$1000, SMALL( IF((MPOB!$Q$3:$Q$1000<>"")*(MPOB!$Q$3:$Q$1000<>"Not Due"), ROW(MPOB!$Q$3:$Q$1000)-ROW(MPOB!$Q$3)+1), ROWS(A$2:A30))),"")} -> MyFinancial | S30: {=IFERROR(INDEX(MPOB!$G$3:$G$1000, SMALL( IF((MPOB!$Q$3:$Q$1000<>"")*(MPOB!$Q$3:$Q$1000<>"Not Due"), ROW(MPOB!$Q$3:$Q$1000)-ROW(MPOB!$Q$3)+1), ROWS(A$2:A30))),"")} -> Bantuan MuatNaik Dokumen Invois bagi Daftar Bil INPOB/0426/06442 User: Norasma No. Hp: 0125985540 | T30: {=IFERROR(INDEX(MPOB!$Q$3:$Q$1000, SMALL( IF((MPOB!$Q$3:$Q$1000<>"")*(MPOB!$Q$3:$Q$1000<>"Not Due"), ROW(MPOB!$Q$3:$Q$1000)-ROW(MPOB!$Q$3)+1), ROWS(A$2:A30)) ),"")} -> 31-60 Days | V30: 29 | W30: {=IFERROR(INDEX(LKTN!$E$3:$E$1000, SMALL( IF((LKTN!$Q$3:$Q$1000<>"")*(LKTN!$Q$3:$Q$1000<>"Not Due"), ROW(LKTN!$Q$3:$Q$1000)-ROW(LKTN!$Q$3)+1), ROWS(A$2:A30))),"")} | X30: {=IFERROR(INDEX(LKTN!$B$3:$B$1000, SMALL( IF((LKTN!$Q$3:$Q$1000<>"")*(LKTN!$Q$3:$Q$1000<>"Not Due"), ROW(LKTN!$Q$3:$Q$1000)-ROW(LKTN!$Q$3)+1), ROWS(A$2:A30))),"")} | Y30: {=IFERROR(INDEX(LKTN!$D$3:$D$1000, SMALL( IF((LKTN!$Q$3:$Q$1000<>"")*(LKTN!$Q$3:$Q$1000<>"Not Due"), ROW(LKTN!$Q$3:$Q$1000)-ROW(LKTN!$Q$3)+1), ROWS(A$2:A30))),"")} | Z30: {=IFERROR(INDEX(LKTN!$G$3:$G$1000, SMALL( IF((LKTN!$Q$3:$Q$1000<>"")*(LKTN!$Q$3:$Q$1000<>"Not Due"), ROW(LKTN!$Q$3:$Q$1000)-ROW(LKTN!$Q$3)+1), ROWS(A$2:A30))),"")} | AA30: {=IFERROR(INDEX(LKTN!$Q$3:$Q$1000, SMALL( IF((LKTN!$Q$3:$Q$1000<>"")*(LKTN!$Q$3:$Q$1000<>"Not Due"), ROW(LKTN!$Q$3:$Q$1000)-ROW(LKTN!$Q$3)+1), ROWS(A$2:A30)) ),"")} | AJ30: 29 | AK30: {=IFERROR(INDEX(ISN!$E$3:$E$1000, SMALL( IF((ISN!$Q$3:$Q$1000<>"")*(ISN!$Q$3:$Q$1000<>"Not Due"), ROW(ISN!$Q$3:$Q$1000)-ROW(ISN!$Q$3)+1), ROWS(A$2:A30))),"")} | AL30: {=IFERROR(INDEX(ISN!$B$3:$B$1000, SMALL( IF((ISN!$Q$3:$Q$1000<>"")*(ISN!$Q$3:$Q$1000<>"Not Due"), ROW(ISN!$Q$3:$Q$1000)-ROW(ISN!$Q$3)+1), ROWS(A$2:A30))),"")} | AM30: {=IFERROR(INDEX(ISN!$D$3:$D$1000, SMALL( IF((ISN!$Q$3:$Q$1000<>"")*(ISN!$Q$3:$Q$1000<>"Not Due"), ROW(ISN!$Q$3:$Q$1000)-ROW(ISN!$Q$3)+1), ROWS(A$2:A30))),"")} | AN30: {=IFERROR(INDEX(ISN!$G$3:$G$1000, SMALL( IF((ISN!$Q$3:$Q$1000<>"")*(ISN!$Q$3:$Q$1000<>"Not Due"), ROW(ISN!$Q$3:$Q$1000)-ROW(ISN!$Q$3)+1), ROWS(A$2:A30))),"")} | AO30: {=IFERROR(INDEX(ISN!$Q$3:$Q$1000, SMALL( IF((ISN!$Q$3:$Q$1000<>"")*(ISN!$Q$3:$Q$1000<>"Not Due"), ROW(ISN!$Q$3:$Q$1000)-ROW(ISN!$Q$3)+1), ROWS(A$2:A30)) ),"")} | AQ30: 29 | AR30: {=IFERROR(INDEX(MSN!$E$3:$E$1000, SMALL( IF((MSN!$Q$3:$Q$1000<>"")*(MSN!$Q$3:$Q$1000<>"Not Due"), ROW(MSN!$Q$3:$Q$1000)-ROW(MSN!$Q$3)+1), ROWS(A$2:A30))),"")} | AS30: {=IFERROR(INDEX(MSN!$B$3:$B$1000, SMALL( IF((MSN!$Q$3:$Q$1000<>"")*(MSN!$Q$3:$Q$1000<>"Not Due"), ROW(MSN!$Q$3:$Q$1000)-ROW(MSN!$Q$3)+1), ROWS(A$2:A30))),"")} | AT30: {=IFERROR(INDEX(MSN!$D$3:$D$1000, SMALL( IF((MSN!$Q$3:$Q$1000<>"")*(MSN!$Q$3:$Q$1000<>"Not Due"), ROW(MSN!$Q$3:$Q$1000)-ROW(MSN!$Q$3)+1), ROWS(A$2:A30))),"")} | AU30: {=IFERROR(INDEX(MSN!$G$3:$G$1000, SMALL( IF((MSN!$Q$3:$Q$1000<>"")*(MSN!$Q$3:$Q$1000<>"Not Due"), ROW(MSN!$Q$3:$Q$1000)-ROW(MSN!$Q$3)+1), ROWS(A$2:A30))),"")} | AV30: {=IFERROR(INDEX(MSN!$Q$3:$Q$1000, SMALL( IF((MSN!$Q$3:$Q$1000<>"")*(MSN!$Q$3:$Q$1000<>"Not Due"), ROW(MSN!$Q$3:$Q$1000)-ROW(MSN!$Q$3)+1), ROWS(A$2:A30)) ),"")}
A31: 30 | B31: {=IFERROR(INDEX(FRIM!$E$3:$E$1000, SMALL( IF((FRIM!$Q$3:$Q$1000<>"")*(FRIM!$Q$3:$Q$1000<>"Not Due"), ROW(FRIM!$Q$3:$Q$1000)-ROW(FRIM!$Q$3)+1), ROWS(A$2:A31))),"")} -> FRIM | C31: {=IFERROR(INDEX(FRIM!$B$3:$B$1000, SMALL( IF((FRIM!$Q$3:$Q$1000<>"")*(FRIM!$Q$3:$Q$1000<>"Not Due"), ROW(FRIM!$Q$3:$Q$1000)-ROW(FRIM!$Q$3)+1), ROWS(A$2:A31))),"")} -> T/2026/00457 | D31: {=IFERROR(INDEX(FRIM!$D$3:$D$1000, SMALL( IF((FRIM!$Q$3:$Q$1000<>"")*(FRIM!$Q$3:$Q$1000<>"Not Due"), ROW(FRIM!$Q$3:$Q$1000)-ROW(FRIM!$Q$3)+1), ROWS(A$2:A31))),"")} -> MYINVENTORY | E31: {=IFERROR(INDEX(FRIM!$G$3:$G$1000, SMALL( IF((FRIM!$Q$3:$Q$1000<>"")*(FRIM!$Q$3:$Q$1000<>"Not Due"), ROW(FRIM!$Q$3:$Q$1000)-ROW(FRIM!$Q$3)+1), ROWS(A$2:A31))),"")} -> No Aduan: W2397 Name: ZAINORASRI B. YAHYA Date: 03/03/2025 Desc: MODUL KONFIGURASI CAPAIAN PENGGUNA TIDAK BERJAYA. PENDAFTARAN PENGGUNA PUAN EMYLIA (NOGAJI=2013) SEBAGAIMANA PUAN HASRINA TIDAK BERJAYA DIBUAT MELALUI MODUL TERSEBUT. MOHON PENYELESAIAN SEGERA BAGI MEMBOLEHKAN CAPAIAN DIBERI. ADUAN BARU DIBUAT ATAS PERMINTAAN SOFTWARE WIZARDS. ADUAN LAMA T/2026/00081 | F31: {=IFERROR(INDEX(FRIM!$Q$3:$Q$1000, SMALL( IF((FRIM!$Q$3:$Q$1000<>"")*(FRIM!$Q$3:$Q$1000<>"Not Due"), ROW(FRIM!$Q$3:$Q$1000)-ROW(FRIM!$Q$3)+1), ROWS(A$2:A31)) ),"")} -> 1-30 Days | H31: 30 | I31: {=IFERROR(INDEX(MTIB!$E$3:$E$1000, SMALL( IF((MTIB!$Q$3:$Q$1000<>"")*(MTIB!$Q$3:$Q$1000<>"Not Due"), ROW(MTIB!$Q$3:$Q$1000)-ROW(MTIB!$Q$3)+1), ROWS(A$2:A31))),"")} | J31: {=IFERROR(INDEX(MTIB!$B$3:$B$1000, SMALL( IF((MTIB!$Q$3:$Q$1000<>"")*(MTIB!$Q$3:$Q$1000<>"Not Due"), ROW(MTIB!$Q$3:$Q$1000)-ROW(MTIB!$Q$3)+1), ROWS(A$2:A31))),"")} | K31: {=IFERROR(INDEX(MTIB!$D$3:$D$1000, SMALL( IF((MTIB!$Q$3:$Q$1000<>"")*(MTIB!$Q$3:$Q$1000<>"Not Due"), ROW(MTIB!$Q$3:$Q$1000)-ROW(MTIB!$Q$3)+1), ROWS(A$2:A31))),"")} | L31: {=IFERROR(INDEX(MTIB!$G$3:$G$1000, SMALL( IF((MTIB!$Q$3:$Q$1000<>"")*(MTIB!$Q$3:$Q$1000<>"Not Due"), ROW(MTIB!$Q$3:$Q$1000)-ROW(MTIB!$Q$3)+1), ROWS(A$2:A31))),"")} | M31: {=IFERROR(INDEX(MTIB!$Q$3:$Q$1000, SMALL( IF((MTIB!$Q$3:$Q$1000<>"")*(MTIB!$Q$3:$Q$1000<>"Not Due"), ROW(MTIB!$Q$3:$Q$1000)-ROW(MTIB!$Q$3)+1), ROWS(A$2:A31)) ),"")} | O31: 30 | P31: {=IFERROR(INDEX(MPOB!$E$3:$E$1000, SMALL( IF((MPOB!$Q$3:$Q$1000<>"")*(MPOB!$Q$3:$Q$1000<>"Not Due"), ROW(MPOB!$Q$3:$Q$1000)-ROW(MPOB!$Q$3)+1), ROWS(A$2:A31))),"")} -> MPOB | Q31: {=IFERROR(INDEX(MPOB!$B$3:$B$1000, SMALL( IF((MPOB!$Q$3:$Q$1000<>"")*(MPOB!$Q$3:$Q$1000<>"Not Due"), ROW(MPOB!$Q$3:$Q$1000)-ROW(MPOB!$Q$3)+1), ROWS(A$2:A31))),"")} -> T/2026/00308 | R31: {=IFERROR(INDEX(MPOB!$D$3:$D$1000, SMALL( IF((MPOB!$Q$3:$Q$1000<>"")*(MPOB!$Q$3:$Q$1000<>"Not Due"), ROW(MPOB!$Q$3:$Q$1000)-ROW(MPOB!$Q$3)+1), ROWS(A$2:A31))),"")} -> MyAsset | S31: {=IFERROR(INDEX(MPOB!$G$3:$G$1000, SMALL( IF((MPOB!$Q$3:$Q$1000<>"")*(MPOB!$Q$3:$Q$1000<>"Not Due"), ROW(MPOB!$Q$3:$Q$1000)-ROW(MPOB!$Q$3)+1), ROWS(A$2:A31))),"")} -> 1. Permohonan yang telah dilakukan hilang semasa carian. 2. Pegawai pengesah dan pelulus tidak dapat paparan 3. No.ID pemeriksa tidak keluar untuk memilih pemeriksa bagi pelupusan 4. Tidak dapat upload memo disebabkan carian | T31: {=IFERROR(INDEX(MPOB!$Q$3:$Q$1000, SMALL( IF((MPOB!$Q$3:$Q$1000<>"")*(MPOB!$Q$3:$Q$1000<>"Not Due"), ROW(MPOB!$Q$3:$Q$1000)-ROW(MPOB!$Q$3)+1), ROWS(A$2:A31)) ),"")} -> 31-60 Days | V31: 30 | W31: {=IFERROR(INDEX(LKTN!$E$3:$E$1000, SMALL( IF((LKTN!$Q$3:$Q$1000<>"")*(LKTN!$Q$3:$Q$1000<>"Not Due"), ROW(LKTN!$Q$3:$Q$1000)-ROW(LKTN!$Q$3)+1), ROWS(A$2:A31))),"")} | X31: {=IFERROR(INDEX(LKTN!$B$3:$B$1000, SMALL( IF((LKTN!$Q$3:$Q$1000<>"")*(LKTN!$Q$3:$Q$1000<>"Not Due"), ROW(LKTN!$Q$3:$Q$1000)-ROW(LKTN!$Q$3)+1), ROWS(A$2:A31))),"")} | Y31: {=IFERROR(INDEX(LKTN!$D$3:$D$1000, SMALL( IF((LKTN!$Q$3:$Q$1000<>"")*(LKTN!$Q$3:$Q$1000<>"Not Due"), ROW(LKTN!$Q$3:$Q$1000)-ROW(LKTN!$Q$3)+1), ROWS(A$2:A31))),"")} | Z31: {=IFERROR(INDEX(LKTN!$G$3:$G$1000, SMALL( IF((LKTN!$Q$3:$Q$1000<>"")*(LKTN!$Q$3:$Q$1000<>"Not Due"), ROW(LKTN!$Q$3:$Q$1000)-ROW(LKTN!$Q$3)+1), ROWS(A$2:A31))),"")} | AA31: {=IFERROR(INDEX(LKTN!$Q$3:$Q$1000, SMALL( IF((LKTN!$Q$3:$Q$1000<>"")*(LKTN!$Q$3:$Q$1000<>"Not Due"), ROW(LKTN!$Q$3:$Q$1000)-ROW(LKTN!$Q$3)+1), ROWS(A$2:A31)) ),"")} | AJ31: 30 | AK31: {=IFERROR(INDEX(ISN!$E$3:$E$1000, SMALL( IF((ISN!$Q$3:$Q$1000<>"")*(ISN!$Q$3:$Q$1000<>"Not Due"), ROW(ISN!$Q$3:$Q$1000)-ROW(ISN!$Q$3)+1), ROWS(A$2:A31))),"")} | AL31: {=IFERROR(INDEX(ISN!$B$3:$B$1000, SMALL( IF((ISN!$Q$3:$Q$1000<>"")*(ISN!$Q$3:$Q$1000<>"Not Due"), ROW(ISN!$Q$3:$Q$1000)-ROW(ISN!$Q$3)+1), ROWS(A$2:A31))),"")} | AM31: {=IFERROR(INDEX(ISN!$D$3:$D$1000, SMALL( IF((ISN!$Q$3:$Q$1000<>"")*(ISN!$Q$3:$Q$1000<>"Not Due"), ROW(ISN!$Q$3:$Q$1000)-ROW(ISN!$Q$3)+1), ROWS(A$2:A31))),"")} | AN31: {=IFERROR(INDEX(ISN!$G$3:$G$1000, SMALL( IF((ISN!$Q$3:$Q$1000<>"")*(ISN!$Q$3:$Q$1000<>"Not Due"), ROW(ISN!$Q$3:$Q$1000)-ROW(ISN!$Q$3)+1), ROWS(A$2:A31))),"")} | AO31: {=IFERROR(INDEX(ISN!$Q$3:$Q$1000, SMALL( IF((ISN!$Q$3:$Q$1000<>"")*(ISN!$Q$3:$Q$1000<>"Not Due"), ROW(ISN!$Q$3:$Q$1000)-ROW(ISN!$Q$3)+1), ROWS(A$2:A31)) ),"")} | AQ31: 30 | AR31: {=IFERROR(INDEX(MSN!$E$3:$E$1000, SMALL( IF((MSN!$Q$3:$Q$1000<>"")*(MSN!$Q$3:$Q$1000<>"Not Due"), ROW(MSN!$Q$3:$Q$1000)-ROW(MSN!$Q$3)+1), ROWS(A$2:A31))),"")} | AS31: {=IFERROR(INDEX(MSN!$B$3:$B$1000, SMALL( IF((MSN!$Q$3:$Q$1000<>"")*(MSN!$Q$3:$Q$1000<>"Not Due"), ROW(MSN!$Q$3:$Q$1000)-ROW(MSN!$Q$3)+1), ROWS(A$2:A31))),"")} | AT31: {=IFERROR(INDEX(MSN!$D$3:$D$1000, SMALL( IF((MSN!$Q$3:$Q$1000<>"")*(MSN!$Q$3:$Q$1000<>"Not Due"), ROW(MSN!$Q$3:$Q$1000)-ROW(MSN!$Q$3)+1), ROWS(A$2:A31))),"")} | AU31: {=IFERROR(INDEX(MSN!$G$3:$G$1000, SMALL( IF((MSN!$Q$3:$Q$1000<>"")*(MSN!$Q$3:$Q$1000<>"Not Due"), ROW(MSN!$Q$3:$Q$1000)-ROW(MSN!$Q$3)+1), ROWS(A$2:A31))),"")} | AV31: {=IFERROR(INDEX(MSN!$Q$3:$Q$1000, SMALL( IF((MSN!$Q$3:$Q$1000<>"")*(MSN!$Q$3:$Q$1000<>"Not Due"), ROW(MSN!$Q$3:$Q$1000)-ROW(MSN!$Q$3)+1), ROWS(A$2:A31)) ),"")}
A32: 31 | B32: {=IFERROR(INDEX(FRIM!$E$3:$E$1000, SMALL(IF(FRIM!$Q$3:$Q$1000<>"", ROW(FRIM!$Q$3:$Q$1000)-ROW(FRIM!$Q$3)+1), ROWS(A$2:A32))),"")} | C32: {=IFERROR(INDEX(FRIM!$B$3:$B$1000, SMALL(IF(FRIM!$Q$3:$Q$1000<>"", ROW(FRIM!$Q$3:$Q$1000)-ROW(FRIM!$Q$3)+1), ROWS(A$2:A32))),"")} | D32: {=IFERROR(INDEX(FRIM!$D$3:$D$1000, SMALL(IF(FRIM!$Q$3:$Q$1000<>"", ROW(FRIM!$Q$3:$Q$1000)-ROW(FRIM!$Q$3)+1), ROWS(A$2:A32))),"")} | E32: {=IFERROR(INDEX(FRIM!$G$3:$G$1000, SMALL(IF(FRIM!$Q$3:$Q$1000<>"", ROW(FRIM!$Q$3:$Q$1000)-ROW(FRIM!$Q$3)+1), ROWS(A$2:A32))),"")} | F32: {=IFERROR(INDEX(FRIM!$Q$3:$Q$1000, SMALL(IF(FRIM!$Q$3:$Q$1000<>"", ROW(FRIM!$Q$3:$Q$1000)-ROW(FRIM!$Q$3)+1), ROWS(A$2:A32))),"")} | H32: 31 | I32: {=IFERROR(INDEX(MTIB!$E$3:$E$1000, SMALL( IF((MTIB!$Q$3:$Q$1000<>"")*(MTIB!$Q$3:$Q$1000<>"Not Due"), ROW(MTIB!$Q$3:$Q$1000)-ROW(MTIB!$Q$3)+1), ROWS(A$2:A32))),"")} | J32: {=IFERROR(INDEX(MTIB!$B$3:$B$1000, SMALL( IF((MTIB!$Q$3:$Q$1000<>"")*(MTIB!$Q$3:$Q$1000<>"Not Due"), ROW(MTIB!$Q$3:$Q$1000)-ROW(MTIB!$Q$3)+1), ROWS(A$2:A32))),"")} | K32: {=IFERROR(INDEX(MTIB!$D$3:$D$1000, SMALL( IF((MTIB!$Q$3:$Q$1000<>"")*(MTIB!$Q$3:$Q$1000<>"Not Due"), ROW(MTIB!$Q$3:$Q$1000)-ROW(MTIB!$Q$3)+1), ROWS(A$2:A32))),"")} | L32: {=IFERROR(INDEX(MTIB!$G$3:$G$1000, SMALL( IF((MTIB!$Q$3:$Q$1000<>"")*(MTIB!$Q$3:$Q$1000<>"Not Due"), ROW(MTIB!$Q$3:$Q$1000)-ROW(MTIB!$Q$3)+1), ROWS(A$2:A32))),"")} | M32: {=IFERROR(INDEX(MTIB!$Q$3:$Q$1000, SMALL( IF((MTIB!$Q$3:$Q$1000<>"")*(MTIB!$Q$3:$Q$1000<>"Not Due"), ROW(MTIB!$Q$3:$Q$1000)-ROW(MTIB!$Q$3)+1), ROWS(A$2:A32)) ),"")} | O32: 31 | P32: {=IFERROR(INDEX(MPOB!$E$3:$E$1000, SMALL( IF((MPOB!$Q$3:$Q$1000<>"")*(MPOB!$Q$3:$Q$1000<>"Not Due"), ROW(MPOB!$Q$3:$Q$1000)-ROW(MPOB!$Q$3)+1), ROWS(A$2:A32))),"")} -> MPOB | Q32: {=IFERROR(INDEX(MPOB!$B$3:$B$1000, SMALL( IF((MPOB!$Q$3:$Q$1000<>"")*(MPOB!$Q$3:$Q$1000<>"Not Due"), ROW(MPOB!$Q$3:$Q$1000)-ROW(MPOB!$Q$3)+1), ROWS(A$2:A32))),"")} -> T/2026/00322 | R32: {=IFERROR(INDEX(MPOB!$D$3:$D$1000, SMALL( IF((MPOB!$Q$3:$Q$1000<>"")*(MPOB!$Q$3:$Q$1000<>"Not Due"), ROW(MPOB!$Q$3:$Q$1000)-ROW(MPOB!$Q$3)+1), ROWS(A$2:A32))),"")} -> MyProcurement | S32: {=IFERROR(INDEX(MPOB!$G$3:$G$1000, SMALL( IF((MPOB!$Q$3:$Q$1000<>"")*(MPOB!$Q$3:$Q$1000<>"Not Due"), ROW(MPOB!$Q$3:$Q$1000)-ROW(MPOB!$Q$3)+1), ROWS(A$2:A32))),"")} -> SUPPLIER TAK BOLEH UPLOAD DOKUMEN SEBUT HARGA DI MY VENDOR. TIADA BUTTOM UPLOAD Jana - 012-6045704 | T32: {=IFERROR(INDEX(MPOB!$Q$3:$Q$1000, SMALL( IF((MPOB!$Q$3:$Q$1000<>"")*(MPOB!$Q$3:$Q$1000<>"Not Due"), ROW(MPOB!$Q$3:$Q$1000)-ROW(MPOB!$Q$3)+1), ROWS(A$2:A32)) ),"")} -> 31-60 Days | V32: 31 | W32: {=IFERROR(INDEX(LKTN!$E$3:$E$1000, SMALL( IF((LKTN!$Q$3:$Q$1000<>"")*(LKTN!$Q$3:$Q$1000<>"Not Due"), ROW(LKTN!$Q$3:$Q$1000)-ROW(LKTN!$Q$3)+1), ROWS(A$2:A32))),"")} | X32: {=IFERROR(INDEX(LKTN!$B$3:$B$1000, SMALL( IF((LKTN!$Q$3:$Q$1000<>"")*(LKTN!$Q$3:$Q$1000<>"Not Due"), ROW(LKTN!$Q$3:$Q$1000)-ROW(LKTN!$Q$3)+1), ROWS(A$2:A32))),"")} | Y32: {=IFERROR(INDEX(LKTN!$D$3:$D$1000, SMALL( IF((LKTN!$Q$3:$Q$1000<>"")*(LKTN!$Q$3:$Q$1000<>"Not Due"), ROW(LKTN!$Q$3:$Q$1000)-ROW(LKTN!$Q$3)+1), ROWS(A$2:A32))),"")} | Z32: {=IFERROR(INDEX(LKTN!$G$3:$G$1000, SMALL( IF((LKTN!$Q$3:$Q$1000<>"")*(LKTN!$Q$3:$Q$1000<>"Not Due"), ROW(LKTN!$Q$3:$Q$1000)-ROW(LKTN!$Q$3)+1), ROWS(A$2:A32))),"")} | AA32: {=IFERROR(INDEX(LKTN!$Q$3:$Q$1000, SMALL( IF((LKTN!$Q$3:$Q$1000<>"")*(LKTN!$Q$3:$Q$1000<>"Not Due"), ROW(LKTN!$Q$3:$Q$1000)-ROW(LKTN!$Q$3)+1), ROWS(A$2:A32)) ),"")} | AJ32: 31 | AK32: {=IFERROR(INDEX(ISN!$E$3:$E$1000, SMALL( IF((ISN!$Q$3:$Q$1000<>"")*(ISN!$Q$3:$Q$1000<>"Not Due"), ROW(ISN!$Q$3:$Q$1000)-ROW(ISN!$Q$3)+1), ROWS(A$2:A32))),"")} | AL32: {=IFERROR(INDEX(ISN!$B$3:$B$1000, SMALL( IF((ISN!$Q$3:$Q$1000<>"")*(ISN!$Q$3:$Q$1000<>"Not Due"), ROW(ISN!$Q$3:$Q$1000)-ROW(ISN!$Q$3)+1), ROWS(A$2:A32))),"")} | AM32: {=IFERROR(INDEX(ISN!$D$3:$D$1000, SMALL( IF((ISN!$Q$3:$Q$1000<>"")*(ISN!$Q$3:$Q$1000<>"Not Due"), ROW(ISN!$Q$3:$Q$1000)-ROW(ISN!$Q$3)+1), ROWS(A$2:A32))),"")} | AN32: {=IFERROR(INDEX(ISN!$G$3:$G$1000, SMALL( IF((ISN!$Q$3:$Q$1000<>"")*(ISN!$Q$3:$Q$1000<>"Not Due"), ROW(ISN!$Q$3:$Q$1000)-ROW(ISN!$Q$3)+1), ROWS(A$2:A32))),"")} | AO32: {=IFERROR(INDEX(ISN!$Q$3:$Q$1000, SMALL( IF((ISN!$Q$3:$Q$1000<>"")*(ISN!$Q$3:$Q$1000<>"Not Due"), ROW(ISN!$Q$3:$Q$1000)-ROW(ISN!$Q$3)+1), ROWS(A$2:A32)) ),"")} | AQ32: 31 | AR32: {=IFERROR(INDEX(MSN!$E$3:$E$1000, SMALL( IF((MSN!$Q$3:$Q$1000<>"")*(MSN!$Q$3:$Q$1000<>"Not Due"), ROW(MSN!$Q$3:$Q$1000)-ROW(MSN!$Q$3)+1), ROWS(A$2:A32))),"")} | AS32: {=IFERROR(INDEX(MSN!$B$3:$B$1000, SMALL( IF((MSN!$Q$3:$Q$1000<>"")*(MSN!$Q$3:$Q$1000<>"Not Due"), ROW(MSN!$Q$3:$Q$1000)-ROW(MSN!$Q$3)+1), ROWS(A$2:A32))),"")} | AT32: {=IFERROR(INDEX(MSN!$D$3:$D$1000, SMALL( IF((MSN!$Q$3:$Q$1000<>"")*(MSN!$Q$3:$Q$1000<>"Not Due"), ROW(MSN!$Q$3:$Q$1000)-ROW(MSN!$Q$3)+1), ROWS(A$2:A32))),"")} | AU32: {=IFERROR(INDEX(MSN!$G$3:$G$1000, SMALL( IF((MSN!$Q$3:$Q$1000<>"")*(MSN!$Q$3:$Q$1000<>"Not Due"), ROW(MSN!$Q$3:$Q$1000)-ROW(MSN!$Q$3)+1), ROWS(A$2:A32))),"")} | AV32: {=IFERROR(INDEX(MSN!$Q$3:$Q$1000, SMALL( IF((MSN!$Q$3:$Q$1000<>"")*(MSN!$Q$3:$Q$1000<>"Not Due"), ROW(MSN!$Q$3:$Q$1000)-ROW(MSN!$Q$3)+1), ROWS(A$2:A32)) ),"")}
A33: 32 | B33: {=IFERROR(INDEX(FRIM!$E$3:$E$1000, SMALL(IF(FRIM!$Q$3:$Q$1000<>"", ROW(FRIM!$Q$3:$Q$1000)-ROW(FRIM!$Q$3)+1), ROWS(A$2:A33))),"")} | C33: {=IFERROR(INDEX(FRIM!$B$3:$B$1000, SMALL(IF(FRIM!$Q$3:$Q$1000<>"", ROW(FRIM!$Q$3:$Q$1000)-ROW(FRIM!$Q$3)+1), ROWS(A$2:A33))),"")} | D33: {=IFERROR(INDEX(FRIM!$D$3:$D$1000, SMALL(IF(FRIM!$Q$3:$Q$1000<>"", ROW(FRIM!$Q$3:$Q$1000)-ROW(FRIM!$Q$3)+1), ROWS(A$2:A33))),"")} | E33: {=IFERROR(INDEX(FRIM!$G$3:$G$1000, SMALL(IF(FRIM!$Q$3:$Q$1000<>"", ROW(FRIM!$Q$3:$Q$1000)-ROW(FRIM!$Q$3)+1), ROWS(A$2:A33))),"")} | F33: {=IFERROR(INDEX(FRIM!$Q$3:$Q$1000, SMALL(IF(FRIM!$Q$3:$Q$1000<>"", ROW(FRIM!$Q$3:$Q$1000)-ROW(FRIM!$Q$3)+1), ROWS(A$2:A33))),"")} | H33: 32 | I33: {=IFERROR(INDEX(MTIB!$E$3:$E$1000, SMALL( IF((MTIB!$Q$3:$Q$1000<>"")*(MTIB!$Q$3:$Q$1000<>"Not Due"), ROW(MTIB!$Q$3:$Q$1000)-ROW(MTIB!$Q$3)+1), ROWS(A$2:A33))),"")} | J33: {=IFERROR(INDEX(MTIB!$B$3:$B$1000, SMALL( IF((MTIB!$Q$3:$Q$1000<>"")*(MTIB!$Q$3:$Q$1000<>"Not Due"), ROW(MTIB!$Q$3:$Q$1000)-ROW(MTIB!$Q$3)+1), ROWS(A$2:A33))),"")} | K33: {=IFERROR(INDEX(MTIB!$D$3:$D$1000, SMALL( IF((MTIB!$Q$3:$Q$1000<>"")*(MTIB!$Q$3:$Q$1000<>"Not Due"), ROW(MTIB!$Q$3:$Q$1000)-ROW(MTIB!$Q$3)+1), ROWS(A$2:A33))),"")} | L33: {=IFERROR(INDEX(MTIB!$G$3:$G$1000, SMALL( IF((MTIB!$Q$3:$Q$1000<>"")*(MTIB!$Q$3:$Q$1000<>"Not Due"), ROW(MTIB!$Q$3:$Q$1000)-ROW(MTIB!$Q$3)+1), ROWS(A$2:A33))),"")} | M33: {=IFERROR(INDEX(MTIB!$Q$3:$Q$1000, SMALL( IF((MTIB!$Q$3:$Q$1000<>"")*(MTIB!$Q$3:$Q$1000<>"Not Due"), ROW(MTIB!$Q$3:$Q$1000)-ROW(MTIB!$Q$3)+1), ROWS(A$2:A33)) ),"")} | O33: 32 | P33: {=IFERROR(INDEX(MPOB!$E$3:$E$1000, SMALL( IF((MPOB!$Q$3:$Q$1000<>"")*(MPOB!$Q$3:$Q$1000<>"Not Due"), ROW(MPOB!$Q$3:$Q$1000)-ROW(MPOB!$Q$3)+1), ROWS(A$2:A33))),"")} -> MPOB | Q33: {=IFERROR(INDEX(MPOB!$B$3:$B$1000, SMALL( IF((MPOB!$Q$3:$Q$1000<>"")*(MPOB!$Q$3:$Q$1000<>"Not Due"), ROW(MPOB!$Q$3:$Q$1000)-ROW(MPOB!$Q$3)+1), ROWS(A$2:A33))),"")} -> T/2026/00341 | R33: {=IFERROR(INDEX(MPOB!$D$3:$D$1000, SMALL( IF((MPOB!$Q$3:$Q$1000<>"")*(MPOB!$Q$3:$Q$1000<>"Not Due"), ROW(MPOB!$Q$3:$Q$1000)-ROW(MPOB!$Q$3)+1), ROWS(A$2:A33))),"")} -> MyFinancial | S33: {=IFERROR(INDEX(MPOB!$G$3:$G$1000, SMALL( IF((MPOB!$Q$3:$Q$1000<>"")*(MPOB!$Q$3:$Q$1000<>"Not Due"), ROW(MPOB!$Q$3:$Q$1000)-ROW(MPOB!$Q$3)+1), ROWS(A$2:A33))),"")} -> INPOB/326/05312 perlu dibatalkan tetapi tidak wujud dalam sistem | T33: {=IFERROR(INDEX(MPOB!$Q$3:$Q$1000, SMALL( IF((MPOB!$Q$3:$Q$1000<>"")*(MPOB!$Q$3:$Q$1000<>"Not Due"), ROW(MPOB!$Q$3:$Q$1000)-ROW(MPOB!$Q$3)+1), ROWS(A$2:A33)) ),"")} -> 31-60 Days | V33: 32 | W33: {=IFERROR(INDEX(LKTN!$E$3:$E$1000, SMALL( IF((LKTN!$Q$3:$Q$1000<>"")*(LKTN!$Q$3:$Q$1000<>"Not Due"), ROW(LKTN!$Q$3:$Q$1000)-ROW(LKTN!$Q$3)+1), ROWS(A$2:A33))),"")} | X33: {=IFERROR(INDEX(LKTN!$B$3:$B$1000, SMALL( IF((LKTN!$Q$3:$Q$1000<>"")*(LKTN!$Q$3:$Q$1000<>"Not Due"), ROW(LKTN!$Q$3:$Q$1000)-ROW(LKTN!$Q$3)+1), ROWS(A$2:A33))),"")} | Y33: {=IFERROR(INDEX(LKTN!$D$3:$D$1000, SMALL( IF((LKTN!$Q$3:$Q$1000<>"")*(LKTN!$Q$3:$Q$1000<>"Not Due"), ROW(LKTN!$Q$3:$Q$1000)-ROW(LKTN!$Q$3)+1), ROWS(A$2:A33))),"")} | Z33: {=IFERROR(INDEX(LKTN!$G$3:$G$1000, SMALL( IF((LKTN!$Q$3:$Q$1000<>"")*(LKTN!$Q$3:$Q$1000<>"Not Due"), ROW(LKTN!$Q$3:$Q$1000)-ROW(LKTN!$Q$3)+1), ROWS(A$2:A33))),"")} | AA33: {=IFERROR(INDEX(LKTN!$Q$3:$Q$1000, SMALL( IF((LKTN!$Q$3:$Q$1000<>"")*(LKTN!$Q$3:$Q$1000<>"Not Due"), ROW(LKTN!$Q$3:$Q$1000)-ROW(LKTN!$Q$3)+1), ROWS(A$2:A33)) ),"")} | AJ33: 32 | AK33: {=IFERROR(INDEX(ISN!$E$3:$E$1000, SMALL( IF((ISN!$Q$3:$Q$1000<>"")*(ISN!$Q$3:$Q$1000<>"Not Due"), ROW(ISN!$Q$3:$Q$1000)-ROW(ISN!$Q$3)+1), ROWS(A$2:A33))),"")} | AL33: {=IFERROR(INDEX(ISN!$B$3:$B$1000, SMALL( IF((ISN!$Q$3:$Q$1000<>"")*(ISN!$Q$3:$Q$1000<>"Not Due"), ROW(ISN!$Q$3:$Q$1000)-ROW(ISN!$Q$3)+1), ROWS(A$2:A33))),"")} | AM33: {=IFERROR(INDEX(ISN!$D$3:$D$1000, SMALL( IF((ISN!$Q$3:$Q$1000<>"")*(ISN!$Q$3:$Q$1000<>"Not Due"), ROW(ISN!$Q$3:$Q$1000)-ROW(ISN!$Q$3)+1), ROWS(A$2:A33))),"")} | AN33: {=IFERROR(INDEX(ISN!$G$3:$G$1000, SMALL( IF((ISN!$Q$3:$Q$1000<>"")*(ISN!$Q$3:$Q$1000<>"Not Due"), ROW(ISN!$Q$3:$Q$1000)-ROW(ISN!$Q$3)+1), ROWS(A$2:A33))),"")} | AO33: {=IFERROR(INDEX(ISN!$Q$3:$Q$1000, SMALL( IF((ISN!$Q$3:$Q$1000<>"")*(ISN!$Q$3:$Q$1000<>"Not Due"), ROW(ISN!$Q$3:$Q$1000)-ROW(ISN!$Q$3)+1), ROWS(A$2:A33)) ),"")} | AQ33: 32 | AR33: {=IFERROR(INDEX(MSN!$E$3:$E$1000, SMALL( IF((MSN!$Q$3:$Q$1000<>"")*(MSN!$Q$3:$Q$1000<>"Not Due"), ROW(MSN!$Q$3:$Q$1000)-ROW(MSN!$Q$3)+1), ROWS(A$2:A33))),"")} | AS33: {=IFERROR(INDEX(MSN!$B$3:$B$1000, SMALL( IF((MSN!$Q$3:$Q$1000<>"")*(MSN!$Q$3:$Q$1000<>"Not Due"), ROW(MSN!$Q$3:$Q$1000)-ROW(MSN!$Q$3)+1), ROWS(A$2:A33))),"")} | AT33: {=IFERROR(INDEX(MSN!$D$3:$D$1000, SMALL( IF((MSN!$Q$3:$Q$1000<>"")*(MSN!$Q$3:$Q$1000<>"Not Due"), ROW(MSN!$Q$3:$Q$1000)-ROW(MSN!$Q$3)+1), ROWS(A$2:A33))),"")} | AU33: {=IFERROR(INDEX(MSN!$G$3:$G$1000, SMALL( IF((MSN!$Q$3:$Q$1000<>"")*(MSN!$Q$3:$Q$1000<>"Not Due"), ROW(MSN!$Q$3:$Q$1000)-ROW(MSN!$Q$3)+1), ROWS(A$2:A33))),"")} | AV33: {=IFERROR(INDEX(MSN!$Q$3:$Q$1000, SMALL( IF((MSN!$Q$3:$Q$1000<>"")*(MSN!$Q$3:$Q$1000<>"Not Due"), ROW(MSN!$Q$3:$Q$1000)-ROW(MSN!$Q$3)+1), ROWS(A$2:A33)) ),"")}
A34: 33 | B34: {=IFERROR(INDEX(FRIM!$E$3:$E$1000, SMALL(IF(FRIM!$Q$3:$Q$1000<>"", ROW(FRIM!$Q$3:$Q$1000)-ROW(FRIM!$Q$3)+1), ROWS(A$2:A34))),"")} | C34: {=IFERROR(INDEX(FRIM!$B$3:$B$1000, SMALL(IF(FRIM!$Q$3:$Q$1000<>"", ROW(FRIM!$Q$3:$Q$1000)-ROW(FRIM!$Q$3)+1), ROWS(A$2:A34))),"")} | D34: {=IFERROR(INDEX(FRIM!$D$3:$D$1000, SMALL(IF(FRIM!$Q$3:$Q$1000<>"", ROW(FRIM!$Q$3:$Q$1000)-ROW(FRIM!$Q$3)+1), ROWS(A$2:A34))),"")} | E34: {=IFERROR(INDEX(FRIM!$G$3:$G$1000, SMALL(IF(FRIM!$Q$3:$Q$1000<>"", ROW(FRIM!$Q$3:$Q$1000)-ROW(FRIM!$Q$3)+1), ROWS(A$2:A34))),"")} | F34: {=IFERROR(INDEX(FRIM!$Q$3:$Q$1000, SMALL(IF(FRIM!$Q$3:$Q$1000<>"", ROW(FRIM!$Q$3:$Q$1000)-ROW(FRIM!$Q$3)+1), ROWS(A$2:A34))),"")} | H34: 33 | I34: {=IFERROR(INDEX(MTIB!$E$3:$E$1000, SMALL( IF((MTIB!$Q$3:$Q$1000<>"")*(MTIB!$Q$3:$Q$1000<>"Not Due"), ROW(MTIB!$Q$3:$Q$1000)-ROW(MTIB!$Q$3)+1), ROWS(A$2:A34))),"")} | J34: {=IFERROR(INDEX(MTIB!$B$3:$B$1000, SMALL( IF((MTIB!$Q$3:$Q$1000<>"")*(MTIB!$Q$3:$Q$1000<>"Not Due"), ROW(MTIB!$Q$3:$Q$1000)-ROW(MTIB!$Q$3)+1), ROWS(A$2:A34))),"")} | K34: {=IFERROR(INDEX(MTIB!$D$3:$D$1000, SMALL( IF((MTIB!$Q$3:$Q$1000<>"")*(MTIB!$Q$3:$Q$1000<>"Not Due"), ROW(MTIB!$Q$3:$Q$1000)-ROW(MTIB!$Q$3)+1), ROWS(A$2:A34))),"")} | L34: {=IFERROR(INDEX(MTIB!$G$3:$G$1000, SMALL( IF((MTIB!$Q$3:$Q$1000<>"")*(MTIB!$Q$3:$Q$1000<>"Not Due"), ROW(MTIB!$Q$3:$Q$1000)-ROW(MTIB!$Q$3)+1), ROWS(A$2:A34))),"")} | M34: {=IFERROR(INDEX(MTIB!$Q$3:$Q$1000, SMALL( IF((MTIB!$Q$3:$Q$1000<>"")*(MTIB!$Q$3:$Q$1000<>"Not Due"), ROW(MTIB!$Q$3:$Q$1000)-ROW(MTIB!$Q$3)+1), ROWS(A$2:A34)) ),"")} | O34: 33 | P34: {=IFERROR(INDEX(MPOB!$E$3:$E$1000, SMALL( IF((MPOB!$Q$3:$Q$1000<>"")*(MPOB!$Q$3:$Q$1000<>"Not Due"), ROW(MPOB!$Q$3:$Q$1000)-ROW(MPOB!$Q$3)+1), ROWS(A$2:A34))),"")} -> MPOB | Q34: {=IFERROR(INDEX(MPOB!$B$3:$B$1000, SMALL( IF((MPOB!$Q$3:$Q$1000<>"")*(MPOB!$Q$3:$Q$1000<>"Not Due"), ROW(MPOB!$Q$3:$Q$1000)-ROW(MPOB!$Q$3)+1), ROWS(A$2:A34))),"")} -> T/2026/00352 | R34: {=IFERROR(INDEX(MPOB!$D$3:$D$1000, SMALL( IF((MPOB!$Q$3:$Q$1000<>"")*(MPOB!$Q$3:$Q$1000<>"Not Due"), ROW(MPOB!$Q$3:$Q$1000)-ROW(MPOB!$Q$3)+1), ROWS(A$2:A34))),"")} -> MyFinancial | S34: {=IFERROR(INDEX(MPOB!$G$3:$G$1000, SMALL( IF((MPOB!$Q$3:$Q$1000<>"")*(MPOB!$Q$3:$Q$1000<>"Not Due"), ROW(MPOB!$Q$3:$Q$1000)-ROW(MPOB!$Q$3)+1), ROWS(A$2:A34))),"")} -> ADA 2 NAMA, PENOLONG AKAUNTAN DAN PENOLONG PEGAWAI TADBIR | T34: {=IFERROR(INDEX(MPOB!$Q$3:$Q$1000, SMALL( IF((MPOB!$Q$3:$Q$1000<>"")*(MPOB!$Q$3:$Q$1000<>"Not Due"), ROW(MPOB!$Q$3:$Q$1000)-ROW(MPOB!$Q$3)+1), ROWS(A$2:A34)) ),"")} -> 31-60 Days | V34: 33 | W34: {=IFERROR(INDEX(LKTN!$E$3:$E$1000, SMALL( IF((LKTN!$Q$3:$Q$1000<>"")*(LKTN!$Q$3:$Q$1000<>"Not Due"), ROW(LKTN!$Q$3:$Q$1000)-ROW(LKTN!$Q$3)+1), ROWS(A$2:A34))),"")} | X34: {=IFERROR(INDEX(LKTN!$B$3:$B$1000, SMALL( IF((LKTN!$Q$3:$Q$1000<>"")*(LKTN!$Q$3:$Q$1000<>"Not Due"), ROW(LKTN!$Q$3:$Q$1000)-ROW(LKTN!$Q$3)+1), ROWS(A$2:A34))),"")} | Y34: {=IFERROR(INDEX(LKTN!$D$3:$D$1000, SMALL( IF((LKTN!$Q$3:$Q$1000<>"")*(LKTN!$Q$3:$Q$1000<>"Not Due"), ROW(LKTN!$Q$3:$Q$1000)-ROW(LKTN!$Q$3)+1), ROWS(A$2:A34))),"")} | Z34: {=IFERROR(INDEX(LKTN!$G$3:$G$1000, SMALL( IF((LKTN!$Q$3:$Q$1000<>"")*(LKTN!$Q$3:$Q$1000<>"Not Due"), ROW(LKTN!$Q$3:$Q$1000)-ROW(LKTN!$Q$3)+1), ROWS(A$2:A34))),"")} | AA34: {=IFERROR(INDEX(LKTN!$Q$3:$Q$1000, SMALL( IF((LKTN!$Q$3:$Q$1000<>"")*(LKTN!$Q$3:$Q$1000<>"Not Due"), ROW(LKTN!$Q$3:$Q$1000)-ROW(LKTN!$Q$3)+1), ROWS(A$2:A34)) ),"")} | AJ34: 33 | AK34: {=IFERROR(INDEX(ISN!$E$3:$E$1000, SMALL( IF((ISN!$Q$3:$Q$1000<>"")*(ISN!$Q$3:$Q$1000<>"Not Due"), ROW(ISN!$Q$3:$Q$1000)-ROW(ISN!$Q$3)+1), ROWS(A$2:A34))),"")} | AL34: {=IFERROR(INDEX(ISN!$B$3:$B$1000, SMALL( IF((ISN!$Q$3:$Q$1000<>"")*(ISN!$Q$3:$Q$1000<>"Not Due"), ROW(ISN!$Q$3:$Q$1000)-ROW(ISN!$Q$3)+1), ROWS(A$2:A34))),"")} | AM34: {=IFERROR(INDEX(ISN!$D$3:$D$1000, SMALL( IF((ISN!$Q$3:$Q$1000<>"")*(ISN!$Q$3:$Q$1000<>"Not Due"), ROW(ISN!$Q$3:$Q$1000)-ROW(ISN!$Q$3)+1), ROWS(A$2:A34))),"")} | AN34: {=IFERROR(INDEX(ISN!$G$3:$G$1000, SMALL( IF((ISN!$Q$3:$Q$1000<>"")*(ISN!$Q$3:$Q$1000<>"Not Due"), ROW(ISN!$Q$3:$Q$1000)-ROW(ISN!$Q$3)+1), ROWS(A$2:A34))),"")} | AO34: {=IFERROR(INDEX(ISN!$Q$3:$Q$1000, SMALL( IF((ISN!$Q$3:$Q$1000<>"")*(ISN!$Q$3:$Q$1000<>"Not Due"), ROW(ISN!$Q$3:$Q$1000)-ROW(ISN!$Q$3)+1), ROWS(A$2:A34)) ),"")} | AQ34: 33 | AR34: {=IFERROR(INDEX(MSN!$E$3:$E$1000, SMALL( IF((MSN!$Q$3:$Q$1000<>"")*(MSN!$Q$3:$Q$1000<>"Not Due"), ROW(MSN!$Q$3:$Q$1000)-ROW(MSN!$Q$3)+1), ROWS(A$2:A34))),"")} | AS34: {=IFERROR(INDEX(MSN!$B$3:$B$1000, SMALL( IF((MSN!$Q$3:$Q$1000<>"")*(MSN!$Q$3:$Q$1000<>"Not Due"), ROW(MSN!$Q$3:$Q$1000)-ROW(MSN!$Q$3)+1), ROWS(A$2:A34))),"")} | AT34: {=IFERROR(INDEX(MSN!$D$3:$D$1000, SMALL( IF((MSN!$Q$3:$Q$1000<>"")*(MSN!$Q$3:$Q$1000<>"Not Due"), ROW(MSN!$Q$3:$Q$1000)-ROW(MSN!$Q$3)+1), ROWS(A$2:A34))),"")} | AU34: {=IFERROR(INDEX(MSN!$G$3:$G$1000, SMALL( IF((MSN!$Q$3:$Q$1000<>"")*(MSN!$Q$3:$Q$1000<>"Not Due"), ROW(MSN!$Q$3:$Q$1000)-ROW(MSN!$Q$3)+1), ROWS(A$2:A34))),"")} | AV34: {=IFERROR(INDEX(MSN!$Q$3:$Q$1000, SMALL( IF((MSN!$Q$3:$Q$1000<>"")*(MSN!$Q$3:$Q$1000<>"Not Due"), ROW(MSN!$Q$3:$Q$1000)-ROW(MSN!$Q$3)+1), ROWS(A$2:A34)) ),"")}
A35: 34 | B35: {=IFERROR(INDEX(FRIM!$E$3:$E$1000, SMALL(IF(FRIM!$Q$3:$Q$1000<>"", ROW(FRIM!$Q$3:$Q$1000)-ROW(FRIM!$Q$3)+1), ROWS(A$2:A35))),"")} | C35: {=IFERROR(INDEX(FRIM!$B$3:$B$1000, SMALL(IF(FRIM!$Q$3:$Q$1000<>"", ROW(FRIM!$Q$3:$Q$1000)-ROW(FRIM!$Q$3)+1), ROWS(A$2:A35))),"")} | D35: {=IFERROR(INDEX(FRIM!$D$3:$D$1000, SMALL(IF(FRIM!$Q$3:$Q$1000<>"", ROW(FRIM!$Q$3:$Q$1000)-ROW(FRIM!$Q$3)+1), ROWS(A$2:A35))),"")} | E35: {=IFERROR(INDEX(FRIM!$G$3:$G$1000, SMALL(IF(FRIM!$Q$3:$Q$1000<>"", ROW(FRIM!$Q$3:$Q$1000)-ROW(FRIM!$Q$3)+1), ROWS(A$2:A35))),"")} | F35: {=IFERROR(INDEX(FRIM!$Q$3:$Q$1000, SMALL(IF(FRIM!$Q$3:$Q$1000<>"", ROW(FRIM!$Q$3:$Q$1000)-ROW(FRIM!$Q$3)+1), ROWS(A$2:A35))),"")} | H35: 34 | I35: {=IFERROR(INDEX(MTIB!$E$3:$E$1000, SMALL( IF((MTIB!$Q$3:$Q$1000<>"")*(MTIB!$Q$3:$Q$1000<>"Not Due"), ROW(MTIB!$Q$3:$Q$1000)-ROW(MTIB!$Q$3)+1), ROWS(A$2:A35))),"")} | J35: {=IFERROR(INDEX(MTIB!$B$3:$B$1000, SMALL( IF((MTIB!$Q$3:$Q$1000<>"")*(MTIB!$Q$3:$Q$1000<>"Not Due"), ROW(MTIB!$Q$3:$Q$1000)-ROW(MTIB!$Q$3)+1), ROWS(A$2:A35))),"")} | K35: {=IFERROR(INDEX(MTIB!$D$3:$D$1000, SMALL( IF((MTIB!$Q$3:$Q$1000<>"")*(MTIB!$Q$3:$Q$1000<>"Not Due"), ROW(MTIB!$Q$3:$Q$1000)-ROW(MTIB!$Q$3)+1), ROWS(A$2:A35))),"")} | L35: {=IFERROR(INDEX(MTIB!$G$3:$G$1000, SMALL( IF((MTIB!$Q$3:$Q$1000<>"")*(MTIB!$Q$3:$Q$1000<>"Not Due"), ROW(MTIB!$Q$3:$Q$1000)-ROW(MTIB!$Q$3)+1), ROWS(A$2:A35))),"")} | M35: {=IFERROR(INDEX(MTIB!$Q$3:$Q$1000, SMALL( IF((MTIB!$Q$3:$Q$1000<>"")*(MTIB!$Q$3:$Q$1000<>"Not Due"), ROW(MTIB!$Q$3:$Q$1000)-ROW(MTIB!$Q$3)+1), ROWS(A$2:A35)) ),"")} | O35: 34 | P35: {=IFERROR(INDEX(MPOB!$E$3:$E$1000, SMALL( IF((MPOB!$Q$3:$Q$1000<>"")*(MPOB!$Q$3:$Q$1000<>"Not Due"), ROW(MPOB!$Q$3:$Q$1000)-ROW(MPOB!$Q$3)+1), ROWS(A$2:A35))),"")} -> MPOB | Q35: {=IFERROR(INDEX(MPOB!$B$3:$B$1000, SMALL( IF((MPOB!$Q$3:$Q$1000<>"")*(MPOB!$Q$3:$Q$1000<>"Not Due"), ROW(MPOB!$Q$3:$Q$1000)-ROW(MPOB!$Q$3)+1), ROWS(A$2:A35))),"")} -> T/2026/00357 | R35: {=IFERROR(INDEX(MPOB!$D$3:$D$1000, SMALL( IF((MPOB!$Q$3:$Q$1000<>"")*(MPOB!$Q$3:$Q$1000<>"Not Due"), ROW(MPOB!$Q$3:$Q$1000)-ROW(MPOB!$Q$3)+1), ROWS(A$2:A35))),"")} -> MyStor | S35: {=IFERROR(INDEX(MPOB!$G$3:$G$1000, SMALL( IF((MPOB!$Q$3:$Q$1000<>"")*(MPOB!$Q$3:$Q$1000<>"Not Due"), ROW(MPOB!$Q$3:$Q$1000)-ROW(MPOB!$Q$3)+1), ROWS(A$2:A35))),"")} -> 1. item butiran hilang bila disimpan 2. pengesan dan pegawai lulus tidak terima 3. mintak semak semuala flow modul pengeluaran stok antara stor | T35: {=IFERROR(INDEX(MPOB!$Q$3:$Q$1000, SMALL( IF((MPOB!$Q$3:$Q$1000<>"")*(MPOB!$Q$3:$Q$1000<>"Not Due"), ROW(MPOB!$Q$3:$Q$1000)-ROW(MPOB!$Q$3)+1), ROWS(A$2:A35)) ),"")} -> 31-60 Days | V35: 34 | W35: {=IFERROR(INDEX(LKTN!$E$3:$E$1000, SMALL( IF((LKTN!$Q$3:$Q$1000<>"")*(LKTN!$Q$3:$Q$1000<>"Not Due"), ROW(LKTN!$Q$3:$Q$1000)-ROW(LKTN!$Q$3)+1), ROWS(A$2:A35))),"")} | X35: {=IFERROR(INDEX(LKTN!$B$3:$B$1000, SMALL( IF((LKTN!$Q$3:$Q$1000<>"")*(LKTN!$Q$3:$Q$1000<>"Not Due"), ROW(LKTN!$Q$3:$Q$1000)-ROW(LKTN!$Q$3)+1), ROWS(A$2:A35))),"")} | Y35: {=IFERROR(INDEX(LKTN!$D$3:$D$1000, SMALL( IF((LKTN!$Q$3:$Q$1000<>"")*(LKTN!$Q$3:$Q$1000<>"Not Due"), ROW(LKTN!$Q$3:$Q$1000)-ROW(LKTN!$Q$3)+1), ROWS(A$2:A35))),"")} | Z35: {=IFERROR(INDEX(LKTN!$G$3:$G$1000, SMALL( IF((LKTN!$Q$3:$Q$1000<>"")*(LKTN!$Q$3:$Q$1000<>"Not Due"), ROW(LKTN!$Q$3:$Q$1000)-ROW(LKTN!$Q$3)+1), ROWS(A$2:A35))),"")} | AA35: {=IFERROR(INDEX(LKTN!$Q$3:$Q$1000, SMALL( IF((LKTN!$Q$3:$Q$1000<>"")*(LKTN!$Q$3:$Q$1000<>"Not Due"), ROW(LKTN!$Q$3:$Q$1000)-ROW(LKTN!$Q$3)+1), ROWS(A$2:A35)) ),"")} | AJ35: 34 | AK35: {=IFERROR(INDEX(ISN!$E$3:$E$1000, SMALL( IF((ISN!$Q$3:$Q$1000<>"")*(ISN!$Q$3:$Q$1000<>"Not Due"), ROW(ISN!$Q$3:$Q$1000)-ROW(ISN!$Q$3)+1), ROWS(A$2:A35))),"")} | AL35: {=IFERROR(INDEX(ISN!$B$3:$B$1000, SMALL( IF((ISN!$Q$3:$Q$1000<>"")*(ISN!$Q$3:$Q$1000<>"Not Due"), ROW(ISN!$Q$3:$Q$1000)-ROW(ISN!$Q$3)+1), ROWS(A$2:A35))),"")} | AM35: {=IFERROR(INDEX(ISN!$D$3:$D$1000, SMALL( IF((ISN!$Q$3:$Q$1000<>"")*(ISN!$Q$3:$Q$1000<>"Not Due"), ROW(ISN!$Q$3:$Q$1000)-ROW(ISN!$Q$3)+1), ROWS(A$2:A35))),"")} | AN35: {=IFERROR(INDEX(ISN!$G$3:$G$1000, SMALL( IF((ISN!$Q$3:$Q$1000<>"")*(ISN!$Q$3:$Q$1000<>"Not Due"), ROW(ISN!$Q$3:$Q$1000)-ROW(ISN!$Q$3)+1), ROWS(A$2:A35))),"")} | AO35: {=IFERROR(INDEX(ISN!$Q$3:$Q$1000, SMALL( IF((ISN!$Q$3:$Q$1000<>"")*(ISN!$Q$3:$Q$1000<>"Not Due"), ROW(ISN!$Q$3:$Q$1000)-ROW(ISN!$Q$3)+1), ROWS(A$2:A35)) ),"")} | AQ35: 34 | AR35: {=IFERROR(INDEX(MSN!$E$3:$E$1000, SMALL( IF((MSN!$Q$3:$Q$1000<>"")*(MSN!$Q$3:$Q$1000<>"Not Due"), ROW(MSN!$Q$3:$Q$1000)-ROW(MSN!$Q$3)+1), ROWS(A$2:A35))),"")} | AS35: {=IFERROR(INDEX(MSN!$B$3:$B$1000, SMALL( IF((MSN!$Q$3:$Q$1000<>"")*(MSN!$Q$3:$Q$1000<>"Not Due"), ROW(MSN!$Q$3:$Q$1000)-ROW(MSN!$Q$3)+1), ROWS(A$2:A35))),"")} | AT35: {=IFERROR(INDEX(MSN!$D$3:$D$1000, SMALL( IF((MSN!$Q$3:$Q$1000<>"")*(MSN!$Q$3:$Q$1000<>"Not Due"), ROW(MSN!$Q$3:$Q$1000)-ROW(MSN!$Q$3)+1), ROWS(A$2:A35))),"")} | AU35: {=IFERROR(INDEX(MSN!$G$3:$G$1000, SMALL( IF((MSN!$Q$3:$Q$1000<>"")*(MSN!$Q$3:$Q$1000<>"Not Due"), ROW(MSN!$Q$3:$Q$1000)-ROW(MSN!$Q$3)+1), ROWS(A$2:A35))),"")} | AV35: {=IFERROR(INDEX(MSN!$Q$3:$Q$1000, SMALL( IF((MSN!$Q$3:$Q$1000<>"")*(MSN!$Q$3:$Q$1000<>"Not Due"), ROW(MSN!$Q$3:$Q$1000)-ROW(MSN!$Q$3)+1), ROWS(A$2:A35)) ),"")}
A36: 35 | B36: {=IFERROR(INDEX(FRIM!$E$3:$E$1000, SMALL(IF(FRIM!$Q$3:$Q$1000<>"", ROW(FRIM!$Q$3:$Q$1000)-ROW(FRIM!$Q$3)+1), ROWS(A$2:A36))),"")} | C36: {=IFERROR(INDEX(FRIM!$B$3:$B$1000, SMALL(IF(FRIM!$Q$3:$Q$1000<>"", ROW(FRIM!$Q$3:$Q$1000)-ROW(FRIM!$Q$3)+1), ROWS(A$2:A36))),"")} | D36: {=IFERROR(INDEX(FRIM!$D$3:$D$1000, SMALL(IF(FRIM!$Q$3:$Q$1000<>"", ROW(FRIM!$Q$3:$Q$1000)-ROW(FRIM!$Q$3)+1), ROWS(A$2:A36))),"")} | E36: {=IFERROR(INDEX(FRIM!$G$3:$G$1000, SMALL(IF(FRIM!$Q$3:$Q$1000<>"", ROW(FRIM!$Q$3:$Q$1000)-ROW(FRIM!$Q$3)+1), ROWS(A$2:A36))),"")} | F36: {=IFERROR(INDEX(FRIM!$Q$3:$Q$1000, SMALL(IF(FRIM!$Q$3:$Q$1000<>"", ROW(FRIM!$Q$3:$Q$1000)-ROW(FRIM!$Q$3)+1), ROWS(A$2:A36))),"")} | H36: 35 | I36: {=IFERROR(INDEX(MTIB!$E$3:$E$1000, SMALL( IF((MTIB!$Q$3:$Q$1000<>"")*(MTIB!$Q$3:$Q$1000<>"Not Due"), ROW(MTIB!$Q$3:$Q$1000)-ROW(MTIB!$Q$3)+1), ROWS(A$2:A36))),"")} | J36: {=IFERROR(INDEX(MTIB!$B$3:$B$1000, SMALL( IF((MTIB!$Q$3:$Q$1000<>"")*(MTIB!$Q$3:$Q$1000<>"Not Due"), ROW(MTIB!$Q$3:$Q$1000)-ROW(MTIB!$Q$3)+1), ROWS(A$2:A36))),"")} | K36: {=IFERROR(INDEX(MTIB!$D$3:$D$1000, SMALL( IF((MTIB!$Q$3:$Q$1000<>"")*(MTIB!$Q$3:$Q$1000<>"Not Due"), ROW(MTIB!$Q$3:$Q$1000)-ROW(MTIB!$Q$3)+1), ROWS(A$2:A36))),"")} | L36: {=IFERROR(INDEX(MTIB!$G$3:$G$1000, SMALL( IF((MTIB!$Q$3:$Q$1000<>"")*(MTIB!$Q$3:$Q$1000<>"Not Due"), ROW(MTIB!$Q$3:$Q$1000)-ROW(MTIB!$Q$3)+1), ROWS(A$2:A36))),"")} | M36: {=IFERROR(INDEX(MTIB!$Q$3:$Q$1000, SMALL( IF((MTIB!$Q$3:$Q$1000<>"")*(MTIB!$Q$3:$Q$1000<>"Not Due"), ROW(MTIB!$Q$3:$Q$1000)-ROW(MTIB!$Q$3)+1), ROWS(A$2:A36)) ),"")} | O36: 35 | P36: {=IFERROR(INDEX(MPOB!$E$3:$E$1000, SMALL( IF((MPOB!$Q$3:$Q$1000<>"")*(MPOB!$Q$3:$Q$1000<>"Not Due"), ROW(MPOB!$Q$3:$Q$1000)-ROW(MPOB!$Q$3)+1), ROWS(A$2:A36))),"")} -> MPOB | Q36: {=IFERROR(INDEX(MPOB!$B$3:$B$1000, SMALL( IF((MPOB!$Q$3:$Q$1000<>"")*(MPOB!$Q$3:$Q$1000<>"Not Due"), ROW(MPOB!$Q$3:$Q$1000)-ROW(MPOB!$Q$3)+1), ROWS(A$2:A36))),"")} -> T/2026/00360 | R36: {=IFERROR(INDEX(MPOB!$D$3:$D$1000, SMALL( IF((MPOB!$Q$3:$Q$1000<>"")*(MPOB!$Q$3:$Q$1000<>"Not Due"), ROW(MPOB!$Q$3:$Q$1000)-ROW(MPOB!$Q$3)+1), ROWS(A$2:A36))),"")} -> MyProcurement | S36: {=IFERROR(INDEX(MPOB!$G$3:$G$1000, SMALL( IF((MPOB!$Q$3:$Q$1000<>"")*(MPOB!$Q$3:$Q$1000<>"Not Due"), ROW(MPOB!$Q$3:$Q$1000)-ROW(MPOB!$Q$3)+1), ROWS(A$2:A36))),"")} -> LPO/FMDD0522/0426/00033 - TOONG STAR SDN BHD. NO. PO INI TAK ADA DALAM PENGESAHAN PENERIMAN . | T36: {=IFERROR(INDEX(MPOB!$Q$3:$Q$1000, SMALL( IF((MPOB!$Q$3:$Q$1000<>"")*(MPOB!$Q$3:$Q$1000<>"Not Due"), ROW(MPOB!$Q$3:$Q$1000)-ROW(MPOB!$Q$3)+1), ROWS(A$2:A36)) ),"")} -> 31-60 Days | V36: 35 | W36: {=IFERROR(INDEX(LKTN!$E$3:$E$1000, SMALL( IF((LKTN!$Q$3:$Q$1000<>"")*(LKTN!$Q$3:$Q$1000<>"Not Due"), ROW(LKTN!$Q$3:$Q$1000)-ROW(LKTN!$Q$3)+1), ROWS(A$2:A36))),"")} | X36: {=IFERROR(INDEX(LKTN!$B$3:$B$1000, SMALL( IF((LKTN!$Q$3:$Q$1000<>"")*(LKTN!$Q$3:$Q$1000<>"Not Due"), ROW(LKTN!$Q$3:$Q$1000)-ROW(LKTN!$Q$3)+1), ROWS(A$2:A36))),"")} | Y36: {=IFERROR(INDEX(LKTN!$D$3:$D$1000, SMALL( IF((LKTN!$Q$3:$Q$1000<>"")*(LKTN!$Q$3:$Q$1000<>"Not Due"), ROW(LKTN!$Q$3:$Q$1000)-ROW(LKTN!$Q$3)+1), ROWS(A$2:A36))),"")} | Z36: {=IFERROR(INDEX(LKTN!$G$3:$G$1000, SMALL( IF((LKTN!$Q$3:$Q$1000<>"")*(LKTN!$Q$3:$Q$1000<>"Not Due"), ROW(LKTN!$Q$3:$Q$1000)-ROW(LKTN!$Q$3)+1), ROWS(A$2:A36))),"")} | AA36: {=IFERROR(INDEX(LKTN!$Q$3:$Q$1000, SMALL( IF((LKTN!$Q$3:$Q$1000<>"")*(LKTN!$Q$3:$Q$1000<>"Not Due"), ROW(LKTN!$Q$3:$Q$1000)-ROW(LKTN!$Q$3)+1), ROWS(A$2:A36)) ),"")} | AJ36: 35 | AK36: {=IFERROR(INDEX(ISN!$E$3:$E$1000, SMALL( IF((ISN!$Q$3:$Q$1000<>"")*(ISN!$Q$3:$Q$1000<>"Not Due"), ROW(ISN!$Q$3:$Q$1000)-ROW(ISN!$Q$3)+1), ROWS(A$2:A36))),"")} | AL36: {=IFERROR(INDEX(ISN!$B$3:$B$1000, SMALL( IF((ISN!$Q$3:$Q$1000<>"")*(ISN!$Q$3:$Q$1000<>"Not Due"), ROW(ISN!$Q$3:$Q$1000)-ROW(ISN!$Q$3)+1), ROWS(A$2:A36))),"")} | AM36: {=IFERROR(INDEX(ISN!$D$3:$D$1000, SMALL( IF((ISN!$Q$3:$Q$1000<>"")*(ISN!$Q$3:$Q$1000<>"Not Due"), ROW(ISN!$Q$3:$Q$1000)-ROW(ISN!$Q$3)+1), ROWS(A$2:A36))),"")} | AN36: {=IFERROR(INDEX(ISN!$G$3:$G$1000, SMALL( IF((ISN!$Q$3:$Q$1000<>"")*(ISN!$Q$3:$Q$1000<>"Not Due"), ROW(ISN!$Q$3:$Q$1000)-ROW(ISN!$Q$3)+1), ROWS(A$2:A36))),"")} | AO36: {=IFERROR(INDEX(ISN!$Q$3:$Q$1000, SMALL( IF((ISN!$Q$3:$Q$1000<>"")*(ISN!$Q$3:$Q$1000<>"Not Due"), ROW(ISN!$Q$3:$Q$1000)-ROW(ISN!$Q$3)+1), ROWS(A$2:A36)) ),"")} | AQ36: 35 | AR36: {=IFERROR(INDEX(MSN!$E$3:$E$1000, SMALL( IF((MSN!$Q$3:$Q$1000<>"")*(MSN!$Q$3:$Q$1000<>"Not Due"), ROW(MSN!$Q$3:$Q$1000)-ROW(MSN!$Q$3)+1), ROWS(A$2:A36))),"")} | AS36: {=IFERROR(INDEX(MSN!$B$3:$B$1000, SMALL( IF((MSN!$Q$3:$Q$1000<>"")*(MSN!$Q$3:$Q$1000<>"Not Due"), ROW(MSN!$Q$3:$Q$1000)-ROW(MSN!$Q$3)+1), ROWS(A$2:A36))),"")} | AT36: {=IFERROR(INDEX(MSN!$D$3:$D$1000, SMALL( IF((MSN!$Q$3:$Q$1000<>"")*(MSN!$Q$3:$Q$1000<>"Not Due"), ROW(MSN!$Q$3:$Q$1000)-ROW(MSN!$Q$3)+1), ROWS(A$2:A36))),"")} | AU36: {=IFERROR(INDEX(MSN!$G$3:$G$1000, SMALL( IF((MSN!$Q$3:$Q$1000<>"")*(MSN!$Q$3:$Q$1000<>"Not Due"), ROW(MSN!$Q$3:$Q$1000)-ROW(MSN!$Q$3)+1), ROWS(A$2:A36))),"")} | AV36: {=IFERROR(INDEX(MSN!$Q$3:$Q$1000, SMALL( IF((MSN!$Q$3:$Q$1000<>"")*(MSN!$Q$3:$Q$1000<>"Not Due"), ROW(MSN!$Q$3:$Q$1000)-ROW(MSN!$Q$3)+1), ROWS(A$2:A36)) ),"")}
A37: 36 | B37: {=IFERROR(INDEX(FRIM!$E$3:$E$1000, SMALL(IF(FRIM!$Q$3:$Q$1000<>"", ROW(FRIM!$Q$3:$Q$1000)-ROW(FRIM!$Q$3)+1), ROWS(A$2:A37))),"")} | C37: {=IFERROR(INDEX(FRIM!$B$3:$B$1000, SMALL(IF(FRIM!$Q$3:$Q$1000<>"", ROW(FRIM!$Q$3:$Q$1000)-ROW(FRIM!$Q$3)+1), ROWS(A$2:A37))),"")} | D37: {=IFERROR(INDEX(FRIM!$D$3:$D$1000, SMALL(IF(FRIM!$Q$3:$Q$1000<>"", ROW(FRIM!$Q$3:$Q$1000)-ROW(FRIM!$Q$3)+1), ROWS(A$2:A37))),"")} | E37: {=IFERROR(INDEX(FRIM!$G$3:$G$1000, SMALL(IF(FRIM!$Q$3:$Q$1000<>"", ROW(FRIM!$Q$3:$Q$1000)-ROW(FRIM!$Q$3)+1), ROWS(A$2:A37))),"")} | F37: {=IFERROR(INDEX(FRIM!$Q$3:$Q$1000, SMALL(IF(FRIM!$Q$3:$Q$1000<>"", ROW(FRIM!$Q$3:$Q$1000)-ROW(FRIM!$Q$3)+1), ROWS(A$2:A37))),"")} | H37: 36 | I37: {=IFERROR(INDEX(MTIB!$E$3:$E$1000, SMALL( IF((MTIB!$Q$3:$Q$1000<>"")*(MTIB!$Q$3:$Q$1000<>"Not Due"), ROW(MTIB!$Q$3:$Q$1000)-ROW(MTIB!$Q$3)+1), ROWS(A$2:A37))),"")} | J37: {=IFERROR(INDEX(MTIB!$B$3:$B$1000, SMALL( IF((MTIB!$Q$3:$Q$1000<>"")*(MTIB!$Q$3:$Q$1000<>"Not Due"), ROW(MTIB!$Q$3:$Q$1000)-ROW(MTIB!$Q$3)+1), ROWS(A$2:A37))),"")} | K37: {=IFERROR(INDEX(MTIB!$D$3:$D$1000, SMALL( IF((MTIB!$Q$3:$Q$1000<>"")*(MTIB!$Q$3:$Q$1000<>"Not Due"), ROW(MTIB!$Q$3:$Q$1000)-ROW(MTIB!$Q$3)+1), ROWS(A$2:A37))),"")} | L37: {=IFERROR(INDEX(MTIB!$G$3:$G$1000, SMALL( IF((MTIB!$Q$3:$Q$1000<>"")*(MTIB!$Q$3:$Q$1000<>"Not Due"), ROW(MTIB!$Q$3:$Q$1000)-ROW(MTIB!$Q$3)+1), ROWS(A$2:A37))),"")} | M37: {=IFERROR(INDEX(MTIB!$Q$3:$Q$1000, SMALL( IF((MTIB!$Q$3:$Q$1000<>"")*(MTIB!$Q$3:$Q$1000<>"Not Due"), ROW(MTIB!$Q$3:$Q$1000)-ROW(MTIB!$Q$3)+1), ROWS(A$2:A37)) ),"")} | O37: 36 | P37: {=IFERROR(INDEX(MPOB!$E$3:$E$1000, SMALL( IF((MPOB!$Q$3:$Q$1000<>"")*(MPOB!$Q$3:$Q$1000<>"Not Due"), ROW(MPOB!$Q$3:$Q$1000)-ROW(MPOB!$Q$3)+1), ROWS(A$2:A37))),"")} -> MPOB | Q37: {=IFERROR(INDEX(MPOB!$B$3:$B$1000, SMALL( IF((MPOB!$Q$3:$Q$1000<>"")*(MPOB!$Q$3:$Q$1000<>"Not Due"), ROW(MPOB!$Q$3:$Q$1000)-ROW(MPOB!$Q$3)+1), ROWS(A$2:A37))),"")} -> T/2026/00364 | R37: {=IFERROR(INDEX(MPOB!$D$3:$D$1000, SMALL( IF((MPOB!$Q$3:$Q$1000<>"")*(MPOB!$Q$3:$Q$1000<>"Not Due"), ROW(MPOB!$Q$3:$Q$1000)-ROW(MPOB!$Q$3)+1), ROWS(A$2:A37))),"")} -> MyFinancial | S37: {=IFERROR(INDEX(MPOB!$G$3:$G$1000, SMALL( IF((MPOB!$Q$3:$Q$1000<>"")*(MPOB!$Q$3:$Q$1000<>"Not Due"), ROW(MPOB!$Q$3:$Q$1000)-ROW(MPOB!$Q$3)+1), ROWS(A$2:A37))),"")} -> TERDAPAT 2 PO TIDAK KELUAR MAKLUMAT. SEBELUM POST ADA. TAPI BILA DAH POS DAN NAK PRINT MAKLUMAT ITU TAK ADA. kami ada masalah utk print PO. 1)LPO/AOTD0401/0526/00040 - ITEM no.1, kuantiti 0.5. kesilapan jadi 1 selepas kelulusan LPO. 2)LPO/ITCS0501/0526/00011 - Maklumat item, No.LPO & kod bajet hilang selepas kelulusan. | T37: {=IFERROR(INDEX(MPOB!$Q$3:$Q$1000, SMALL( IF((MPOB!$Q$3:$Q$1000<>"")*(MPOB!$Q$3:$Q$1000<>"Not Due"), ROW(MPOB!$Q$3:$Q$1000)-ROW(MPOB!$Q$3)+1), ROWS(A$2:A37)) ),"")} -> 31-60 Days | V37: 36 | W37: {=IFERROR(INDEX(LKTN!$E$3:$E$1000, SMALL( IF((LKTN!$Q$3:$Q$1000<>"")*(LKTN!$Q$3:$Q$1000<>"Not Due"), ROW(LKTN!$Q$3:$Q$1000)-ROW(LKTN!$Q$3)+1), ROWS(A$2:A37))),"")} | X37: {=IFERROR(INDEX(LKTN!$B$3:$B$1000, SMALL( IF((LKTN!$Q$3:$Q$1000<>"")*(LKTN!$Q$3:$Q$1000<>"Not Due"), ROW(LKTN!$Q$3:$Q$1000)-ROW(LKTN!$Q$3)+1), ROWS(A$2:A37))),"")} | Y37: {=IFERROR(INDEX(LKTN!$D$3:$D$1000, SMALL( IF((LKTN!$Q$3:$Q$1000<>"")*(LKTN!$Q$3:$Q$1000<>"Not Due"), ROW(LKTN!$Q$3:$Q$1000)-ROW(LKTN!$Q$3)+1), ROWS(A$2:A37))),"")} | Z37: {=IFERROR(INDEX(LKTN!$G$3:$G$1000, SMALL( IF((LKTN!$Q$3:$Q$1000<>"")*(LKTN!$Q$3:$Q$1000<>"Not Due"), ROW(LKTN!$Q$3:$Q$1000)-ROW(LKTN!$Q$3)+1), ROWS(A$2:A37))),"")} | AA37: {=IFERROR(INDEX(LKTN!$Q$3:$Q$1000, SMALL( IF((LKTN!$Q$3:$Q$1000<>"")*(LKTN!$Q$3:$Q$1000<>"Not Due"), ROW(LKTN!$Q$3:$Q$1000)-ROW(LKTN!$Q$3)+1), ROWS(A$2:A37)) ),"")} | AJ37: 36 | AK37: {=IFERROR(INDEX(ISN!$E$3:$E$1000, SMALL( IF((ISN!$Q$3:$Q$1000<>"")*(ISN!$Q$3:$Q$1000<>"Not Due"), ROW(ISN!$Q$3:$Q$1000)-ROW(ISN!$Q$3)+1), ROWS(A$2:A37))),"")} | AL37: {=IFERROR(INDEX(ISN!$B$3:$B$1000, SMALL( IF((ISN!$Q$3:$Q$1000<>"")*(ISN!$Q$3:$Q$1000<>"Not Due"), ROW(ISN!$Q$3:$Q$1000)-ROW(ISN!$Q$3)+1), ROWS(A$2:A37))),"")} | AM37: {=IFERROR(INDEX(ISN!$D$3:$D$1000, SMALL( IF((ISN!$Q$3:$Q$1000<>"")*(ISN!$Q$3:$Q$1000<>"Not Due"), ROW(ISN!$Q$3:$Q$1000)-ROW(ISN!$Q$3)+1), ROWS(A$2:A37))),"")} | AN37: {=IFERROR(INDEX(ISN!$G$3:$G$1000, SMALL( IF((ISN!$Q$3:$Q$1000<>"")*(ISN!$Q$3:$Q$1000<>"Not Due"), ROW(ISN!$Q$3:$Q$1000)-ROW(ISN!$Q$3)+1), ROWS(A$2:A37))),"")} | AO37: {=IFERROR(INDEX(ISN!$Q$3:$Q$1000, SMALL( IF((ISN!$Q$3:$Q$1000<>"")*(ISN!$Q$3:$Q$1000<>"Not Due"), ROW(ISN!$Q$3:$Q$1000)-ROW(ISN!$Q$3)+1), ROWS(A$2:A37)) ),"")} | AQ37: 36 | AR37: {=IFERROR(INDEX(MSN!$E$3:$E$1000, SMALL( IF((MSN!$Q$3:$Q$1000<>"")*(MSN!$Q$3:$Q$1000<>"Not Due"), ROW(MSN!$Q$3:$Q$1000)-ROW(MSN!$Q$3)+1), ROWS(A$2:A37))),"")} | AS37: {=IFERROR(INDEX(MSN!$B$3:$B$1000, SMALL( IF((MSN!$Q$3:$Q$1000<>"")*(MSN!$Q$3:$Q$1000<>"Not Due"), ROW(MSN!$Q$3:$Q$1000)-ROW(MSN!$Q$3)+1), ROWS(A$2:A37))),"")} | AT37: {=IFERROR(INDEX(MSN!$D$3:$D$1000, SMALL( IF((MSN!$Q$3:$Q$1000<>"")*(MSN!$Q$3:$Q$1000<>"Not Due"), ROW(MSN!$Q$3:$Q$1000)-ROW(MSN!$Q$3)+1), ROWS(A$2:A37))),"")} | AU37: {=IFERROR(INDEX(MSN!$G$3:$G$1000, SMALL( IF((MSN!$Q$3:$Q$1000<>"")*(MSN!$Q$3:$Q$1000<>"Not Due"), ROW(MSN!$Q$3:$Q$1000)-ROW(MSN!$Q$3)+1), ROWS(A$2:A37))),"")} | AV37: {=IFERROR(INDEX(MSN!$Q$3:$Q$1000, SMALL( IF((MSN!$Q$3:$Q$1000<>"")*(MSN!$Q$3:$Q$1000<>"Not Due"), ROW(MSN!$Q$3:$Q$1000)-ROW(MSN!$Q$3)+1), ROWS(A$2:A37)) ),"")}
A38: 37 | B38: {=IFERROR(INDEX(FRIM!$E$3:$E$1000, SMALL(IF(FRIM!$Q$3:$Q$1000<>"", ROW(FRIM!$Q$3:$Q$1000)-ROW(FRIM!$Q$3)+1), ROWS(A$2:A38))),"")} | C38: {=IFERROR(INDEX(FRIM!$B$3:$B$1000, SMALL(IF(FRIM!$Q$3:$Q$1000<>"", ROW(FRIM!$Q$3:$Q$1000)-ROW(FRIM!$Q$3)+1), ROWS(A$2:A38))),"")} | D38: {=IFERROR(INDEX(FRIM!$D$3:$D$1000, SMALL(IF(FRIM!$Q$3:$Q$1000<>"", ROW(FRIM!$Q$3:$Q$1000)-ROW(FRIM!$Q$3)+1), ROWS(A$2:A38))),"")} | E38: {=IFERROR(INDEX(FRIM!$G$3:$G$1000, SMALL(IF(FRIM!$Q$3:$Q$1000<>"", ROW(FRIM!$Q$3:$Q$1000)-ROW(FRIM!$Q$3)+1), ROWS(A$2:A38))),"")} | F38: {=IFERROR(INDEX(FRIM!$Q$3:$Q$1000, SMALL(IF(FRIM!$Q$3:$Q$1000<>"", ROW(FRIM!$Q$3:$Q$1000)-ROW(FRIM!$Q$3)+1), ROWS(A$2:A38))),"")} | H38: 37 | I38: {=IFERROR(INDEX(MTIB!$E$3:$E$1000, SMALL( IF((MTIB!$Q$3:$Q$1000<>"")*(MTIB!$Q$3:$Q$1000<>"Not Due"), ROW(MTIB!$Q$3:$Q$1000)-ROW(MTIB!$Q$3)+1), ROWS(A$2:A38))),"")} | J38: {=IFERROR(INDEX(MTIB!$B$3:$B$1000, SMALL( IF((MTIB!$Q$3:$Q$1000<>"")*(MTIB!$Q$3:$Q$1000<>"Not Due"), ROW(MTIB!$Q$3:$Q$1000)-ROW(MTIB!$Q$3)+1), ROWS(A$2:A38))),"")} | K38: {=IFERROR(INDEX(MTIB!$D$3:$D$1000, SMALL( IF((MTIB!$Q$3:$Q$1000<>"")*(MTIB!$Q$3:$Q$1000<>"Not Due"), ROW(MTIB!$Q$3:$Q$1000)-ROW(MTIB!$Q$3)+1), ROWS(A$2:A38))),"")} | L38: {=IFERROR(INDEX(MTIB!$G$3:$G$1000, SMALL( IF((MTIB!$Q$3:$Q$1000<>"")*(MTIB!$Q$3:$Q$1000<>"Not Due"), ROW(MTIB!$Q$3:$Q$1000)-ROW(MTIB!$Q$3)+1), ROWS(A$2:A38))),"")} | M38: {=IFERROR(INDEX(MTIB!$Q$3:$Q$1000, SMALL( IF((MTIB!$Q$3:$Q$1000<>"")*(MTIB!$Q$3:$Q$1000<>"Not Due"), ROW(MTIB!$Q$3:$Q$1000)-ROW(MTIB!$Q$3)+1), ROWS(A$2:A38)) ),"")} | O38: 37 | P38: {=IFERROR(INDEX(MPOB!$E$3:$E$1000, SMALL( IF((MPOB!$Q$3:$Q$1000<>"")*(MPOB!$Q$3:$Q$1000<>"Not Due"), ROW(MPOB!$Q$3:$Q$1000)-ROW(MPOB!$Q$3)+1), ROWS(A$2:A38))),"")} -> MPOB | Q38: {=IFERROR(INDEX(MPOB!$B$3:$B$1000, SMALL( IF((MPOB!$Q$3:$Q$1000<>"")*(MPOB!$Q$3:$Q$1000<>"Not Due"), ROW(MPOB!$Q$3:$Q$1000)-ROW(MPOB!$Q$3)+1), ROWS(A$2:A38))),"")} -> T/2026/00365 | R38: {=IFERROR(INDEX(MPOB!$D$3:$D$1000, SMALL( IF((MPOB!$Q$3:$Q$1000<>"")*(MPOB!$Q$3:$Q$1000<>"Not Due"), ROW(MPOB!$Q$3:$Q$1000)-ROW(MPOB!$Q$3)+1), ROWS(A$2:A38))),"")} -> MyAsset | S38: {=IFERROR(INDEX(MPOB!$G$3:$G$1000, SMALL( IF((MPOB!$Q$3:$Q$1000<>"")*(MPOB!$Q$3:$Q$1000<>"Not Due"), ROW(MPOB!$Q$3:$Q$1000)-ROW(MPOB!$Q$3)+1), ROWS(A$2:A38))),"")} -> tak boleh nak daftar aset, TERIMAAN ASSET | T38: {=IFERROR(INDEX(MPOB!$Q$3:$Q$1000, SMALL( IF((MPOB!$Q$3:$Q$1000<>"")*(MPOB!$Q$3:$Q$1000<>"Not Due"), ROW(MPOB!$Q$3:$Q$1000)-ROW(MPOB!$Q$3)+1), ROWS(A$2:A38)) ),"")} -> 31-60 Days | V38: 37 | W38: {=IFERROR(INDEX(LKTN!$E$3:$E$1000, SMALL( IF((LKTN!$Q$3:$Q$1000<>"")*(LKTN!$Q$3:$Q$1000<>"Not Due"), ROW(LKTN!$Q$3:$Q$1000)-ROW(LKTN!$Q$3)+1), ROWS(A$2:A38))),"")} | X38: {=IFERROR(INDEX(LKTN!$B$3:$B$1000, SMALL( IF((LKTN!$Q$3:$Q$1000<>"")*(LKTN!$Q$3:$Q$1000<>"Not Due"), ROW(LKTN!$Q$3:$Q$1000)-ROW(LKTN!$Q$3)+1), ROWS(A$2:A38))),"")} | Y38: {=IFERROR(INDEX(LKTN!$D$3:$D$1000, SMALL( IF((LKTN!$Q$3:$Q$1000<>"")*(LKTN!$Q$3:$Q$1000<>"Not Due"), ROW(LKTN!$Q$3:$Q$1000)-ROW(LKTN!$Q$3)+1), ROWS(A$2:A38))),"")} | Z38: {=IFERROR(INDEX(LKTN!$G$3:$G$1000, SMALL( IF((LKTN!$Q$3:$Q$1000<>"")*(LKTN!$Q$3:$Q$1000<>"Not Due"), ROW(LKTN!$Q$3:$Q$1000)-ROW(LKTN!$Q$3)+1), ROWS(A$2:A38))),"")} | AA38: {=IFERROR(INDEX(LKTN!$Q$3:$Q$1000, SMALL( IF((LKTN!$Q$3:$Q$1000<>"")*(LKTN!$Q$3:$Q$1000<>"Not Due"), ROW(LKTN!$Q$3:$Q$1000)-ROW(LKTN!$Q$3)+1), ROWS(A$2:A38)) ),"")} | AJ38: 37 | AK38: {=IFERROR(INDEX(ISN!$E$3:$E$1000, SMALL( IF((ISN!$Q$3:$Q$1000<>"")*(ISN!$Q$3:$Q$1000<>"Not Due"), ROW(ISN!$Q$3:$Q$1000)-ROW(ISN!$Q$3)+1), ROWS(A$2:A38))),"")} | AL38: {=IFERROR(INDEX(ISN!$B$3:$B$1000, SMALL( IF((ISN!$Q$3:$Q$1000<>"")*(ISN!$Q$3:$Q$1000<>"Not Due"), ROW(ISN!$Q$3:$Q$1000)-ROW(ISN!$Q$3)+1), ROWS(A$2:A38))),"")} | AM38: {=IFERROR(INDEX(ISN!$D$3:$D$1000, SMALL( IF((ISN!$Q$3:$Q$1000<>"")*(ISN!$Q$3:$Q$1000<>"Not Due"), ROW(ISN!$Q$3:$Q$1000)-ROW(ISN!$Q$3)+1), ROWS(A$2:A38))),"")} | AN38: {=IFERROR(INDEX(ISN!$G$3:$G$1000, SMALL( IF((ISN!$Q$3:$Q$1000<>"")*(ISN!$Q$3:$Q$1000<>"Not Due"), ROW(ISN!$Q$3:$Q$1000)-ROW(ISN!$Q$3)+1), ROWS(A$2:A38))),"")} | AO38: {=IFERROR(INDEX(ISN!$Q$3:$Q$1000, SMALL( IF((ISN!$Q$3:$Q$1000<>"")*(ISN!$Q$3:$Q$1000<>"Not Due"), ROW(ISN!$Q$3:$Q$1000)-ROW(ISN!$Q$3)+1), ROWS(A$2:A38)) ),"")} | AQ38: 37 | AR38: {=IFERROR(INDEX(MSN!$E$3:$E$1000, SMALL( IF((MSN!$Q$3:$Q$1000<>"")*(MSN!$Q$3:$Q$1000<>"Not Due"), ROW(MSN!$Q$3:$Q$1000)-ROW(MSN!$Q$3)+1), ROWS(A$2:A38))),"")} | AS38: {=IFERROR(INDEX(MSN!$B$3:$B$1000, SMALL( IF((MSN!$Q$3:$Q$1000<>"")*(MSN!$Q$3:$Q$1000<>"Not Due"), ROW(MSN!$Q$3:$Q$1000)-ROW(MSN!$Q$3)+1), ROWS(A$2:A38))),"")} | AT38: {=IFERROR(INDEX(MSN!$D$3:$D$1000, SMALL( IF((MSN!$Q$3:$Q$1000<>"")*(MSN!$Q$3:$Q$1000<>"Not Due"), ROW(MSN!$Q$3:$Q$1000)-ROW(MSN!$Q$3)+1), ROWS(A$2:A38))),"")} | AU38: {=IFERROR(INDEX(MSN!$G$3:$G$1000, SMALL( IF((MSN!$Q$3:$Q$1000<>"")*(MSN!$Q$3:$Q$1000<>"Not Due"), ROW(MSN!$Q$3:$Q$1000)-ROW(MSN!$Q$3)+1), ROWS(A$2:A38))),"")} | AV38: {=IFERROR(INDEX(MSN!$Q$3:$Q$1000, SMALL( IF((MSN!$Q$3:$Q$1000<>"")*(MSN!$Q$3:$Q$1000<>"Not Due"), ROW(MSN!$Q$3:$Q$1000)-ROW(MSN!$Q$3)+1), ROWS(A$2:A38)) ),"")}
A39: 38 | B39: {=IFERROR(INDEX(FRIM!$E$3:$E$1000, SMALL(IF(FRIM!$Q$3:$Q$1000<>"", ROW(FRIM!$Q$3:$Q$1000)-ROW(FRIM!$Q$3)+1), ROWS(A$2:A39))),"")} | C39: {=IFERROR(INDEX(FRIM!$B$3:$B$1000, SMALL(IF(FRIM!$Q$3:$Q$1000<>"", ROW(FRIM!$Q$3:$Q$1000)-ROW(FRIM!$Q$3)+1), ROWS(A$2:A39))),"")} | D39: {=IFERROR(INDEX(FRIM!$D$3:$D$1000, SMALL(IF(FRIM!$Q$3:$Q$1000<>"", ROW(FRIM!$Q$3:$Q$1000)-ROW(FRIM!$Q$3)+1), ROWS(A$2:A39))),"")} | E39: {=IFERROR(INDEX(FRIM!$G$3:$G$1000, SMALL(IF(FRIM!$Q$3:$Q$1000<>"", ROW(FRIM!$Q$3:$Q$1000)-ROW(FRIM!$Q$3)+1), ROWS(A$2:A39))),"")} | F39: {=IFERROR(INDEX(FRIM!$Q$3:$Q$1000, SMALL(IF(FRIM!$Q$3:$Q$1000<>"", ROW(FRIM!$Q$3:$Q$1000)-ROW(FRIM!$Q$3)+1), ROWS(A$2:A39))),"")} | H39: 38 | I39: {=IFERROR(INDEX(MTIB!$E$3:$E$1000, SMALL( IF((MTIB!$Q$3:$Q$1000<>"")*(MTIB!$Q$3:$Q$1000<>"Not Due"), ROW(MTIB!$Q$3:$Q$1000)-ROW(MTIB!$Q$3)+1), ROWS(A$2:A39))),"")} | J39: {=IFERROR(INDEX(MTIB!$B$3:$B$1000, SMALL( IF((MTIB!$Q$3:$Q$1000<>"")*(MTIB!$Q$3:$Q$1000<>"Not Due"), ROW(MTIB!$Q$3:$Q$1000)-ROW(MTIB!$Q$3)+1), ROWS(A$2:A39))),"")} | K39: {=IFERROR(INDEX(MTIB!$D$3:$D$1000, SMALL( IF((MTIB!$Q$3:$Q$1000<>"")*(MTIB!$Q$3:$Q$1000<>"Not Due"), ROW(MTIB!$Q$3:$Q$1000)-ROW(MTIB!$Q$3)+1), ROWS(A$2:A39))),"")} | L39: {=IFERROR(INDEX(MTIB!$G$3:$G$1000, SMALL( IF((MTIB!$Q$3:$Q$1000<>"")*(MTIB!$Q$3:$Q$1000<>"Not Due"), ROW(MTIB!$Q$3:$Q$1000)-ROW(MTIB!$Q$3)+1), ROWS(A$2:A39))),"")} | M39: {=IFERROR(INDEX(MTIB!$Q$3:$Q$1000, SMALL( IF((MTIB!$Q$3:$Q$1000<>"")*(MTIB!$Q$3:$Q$1000<>"Not Due"), ROW(MTIB!$Q$3:$Q$1000)-ROW(MTIB!$Q$3)+1), ROWS(A$2:A39)) ),"")} | O39: 38 | P39: {=IFERROR(INDEX(MPOB!$E$3:$E$1000, SMALL( IF((MPOB!$Q$3:$Q$1000<>"")*(MPOB!$Q$3:$Q$1000<>"Not Due"), ROW(MPOB!$Q$3:$Q$1000)-ROW(MPOB!$Q$3)+1), ROWS(A$2:A39))),"")} | Q39: {=IFERROR(INDEX(MPOB!$B$3:$B$1000, SMALL( IF((MPOB!$Q$3:$Q$1000<>"")*(MPOB!$Q$3:$Q$1000<>"Not Due"), ROW(MPOB!$Q$3:$Q$1000)-ROW(MPOB!$Q$3)+1), ROWS(A$2:A39))),"")} | R39: {=IFERROR(INDEX(MPOB!$D$3:$D$1000, SMALL( IF((MPOB!$Q$3:$Q$1000<>"")*(MPOB!$Q$3:$Q$1000<>"Not Due"), ROW(MPOB!$Q$3:$Q$1000)-ROW(MPOB!$Q$3)+1), ROWS(A$2:A39))),"")} | S39: {=IFERROR(INDEX(MPOB!$G$3:$G$1000, SMALL( IF((MPOB!$Q$3:$Q$1000<>"")*(MPOB!$Q$3:$Q$1000<>"Not Due"), ROW(MPOB!$Q$3:$Q$1000)-ROW(MPOB!$Q$3)+1), ROWS(A$2:A39))),"")} | T39: {=IFERROR(INDEX(MPOB!$Q$3:$Q$1000, SMALL( IF((MPOB!$Q$3:$Q$1000<>"")*(MPOB!$Q$3:$Q$1000<>"Not Due"), ROW(MPOB!$Q$3:$Q$1000)-ROW(MPOB!$Q$3)+1), ROWS(A$2:A39)) ),"")} | V39: 38 | W39: {=IFERROR(INDEX(LKTN!$E$3:$E$1000, SMALL( IF((LKTN!$Q$3:$Q$1000<>"")*(LKTN!$Q$3:$Q$1000<>"Not Due"), ROW(LKTN!$Q$3:$Q$1000)-ROW(LKTN!$Q$3)+1), ROWS(A$2:A39))),"")} | X39: {=IFERROR(INDEX(LKTN!$B$3:$B$1000, SMALL( IF((LKTN!$Q$3:$Q$1000<>"")*(LKTN!$Q$3:$Q$1000<>"Not Due"), ROW(LKTN!$Q$3:$Q$1000)-ROW(LKTN!$Q$3)+1), ROWS(A$2:A39))),"")} | Y39: {=IFERROR(INDEX(LKTN!$D$3:$D$1000, SMALL( IF((LKTN!$Q$3:$Q$1000<>"")*(LKTN!$Q$3:$Q$1000<>"Not Due"), ROW(LKTN!$Q$3:$Q$1000)-ROW(LKTN!$Q$3)+1), ROWS(A$2:A39))),"")} | Z39: {=IFERROR(INDEX(LKTN!$G$3:$G$1000, SMALL( IF((LKTN!$Q$3:$Q$1000<>"")*(LKTN!$Q$3:$Q$1000<>"Not Due"), ROW(LKTN!$Q$3:$Q$1000)-ROW(LKTN!$Q$3)+1), ROWS(A$2:A39))),"")} | AA39: {=IFERROR(INDEX(LKTN!$Q$3:$Q$1000, SMALL( IF((LKTN!$Q$3:$Q$1000<>"")*(LKTN!$Q$3:$Q$1000<>"Not Due"), ROW(LKTN!$Q$3:$Q$1000)-ROW(LKTN!$Q$3)+1), ROWS(A$2:A39)) ),"")} | AJ39: 38 | AK39: {=IFERROR(INDEX(ISN!$E$3:$E$1000, SMALL( IF((ISN!$Q$3:$Q$1000<>"")*(ISN!$Q$3:$Q$1000<>"Not Due"), ROW(ISN!$Q$3:$Q$1000)-ROW(ISN!$Q$3)+1), ROWS(A$2:A39))),"")} | AL39: {=IFERROR(INDEX(ISN!$B$3:$B$1000, SMALL( IF((ISN!$Q$3:$Q$1000<>"")*(ISN!$Q$3:$Q$1000<>"Not Due"), ROW(ISN!$Q$3:$Q$1000)-ROW(ISN!$Q$3)+1), ROWS(A$2:A39))),"")} | AM39: {=IFERROR(INDEX(ISN!$D$3:$D$1000, SMALL( IF((ISN!$Q$3:$Q$1000<>"")*(ISN!$Q$3:$Q$1000<>"Not Due"), ROW(ISN!$Q$3:$Q$1000)-ROW(ISN!$Q$3)+1), ROWS(A$2:A39))),"")} | AN39: {=IFERROR(INDEX(ISN!$G$3:$G$1000, SMALL( IF((ISN!$Q$3:$Q$1000<>"")*(ISN!$Q$3:$Q$1000<>"Not Due"), ROW(ISN!$Q$3:$Q$1000)-ROW(ISN!$Q$3)+1), ROWS(A$2:A39))),"")} | AO39: {=IFERROR(INDEX(ISN!$Q$3:$Q$1000, SMALL( IF((ISN!$Q$3:$Q$1000<>"")*(ISN!$Q$3:$Q$1000<>"Not Due"), ROW(ISN!$Q$3:$Q$1000)-ROW(ISN!$Q$3)+1), ROWS(A$2:A39)) ),"")} | AQ39: 38 | AR39: {=IFERROR(INDEX(MSN!$E$3:$E$1000, SMALL( IF((MSN!$Q$3:$Q$1000<>"")*(MSN!$Q$3:$Q$1000<>"Not Due"), ROW(MSN!$Q$3:$Q$1000)-ROW(MSN!$Q$3)+1), ROWS(A$2:A39))),"")} | AS39: {=IFERROR(INDEX(MSN!$B$3:$B$1000, SMALL( IF((MSN!$Q$3:$Q$1000<>"")*(MSN!$Q$3:$Q$1000<>"Not Due"), ROW(MSN!$Q$3:$Q$1000)-ROW(MSN!$Q$3)+1), ROWS(A$2:A39))),"")} | AT39: {=IFERROR(INDEX(MSN!$D$3:$D$1000, SMALL( IF((MSN!$Q$3:$Q$1000<>"")*(MSN!$Q$3:$Q$1000<>"Not Due"), ROW(MSN!$Q$3:$Q$1000)-ROW(MSN!$Q$3)+1), ROWS(A$2:A39))),"")} | AU39: {=IFERROR(INDEX(MSN!$G$3:$G$1000, SMALL( IF((MSN!$Q$3:$Q$1000<>"")*(MSN!$Q$3:$Q$1000<>"Not Due"), ROW(MSN!$Q$3:$Q$1000)-ROW(MSN!$Q$3)+1), ROWS(A$2:A39))),"")} | AV39: {=IFERROR(INDEX(MSN!$Q$3:$Q$1000, SMALL( IF((MSN!$Q$3:$Q$1000<>"")*(MSN!$Q$3:$Q$1000<>"Not Due"), ROW(MSN!$Q$3:$Q$1000)-ROW(MSN!$Q$3)+1), ROWS(A$2:A39)) ),"")}
A40: 39 | B40: {=IFERROR(INDEX(FRIM!$E$3:$E$1000, SMALL(IF(FRIM!$Q$3:$Q$1000<>"", ROW(FRIM!$Q$3:$Q$1000)-ROW(FRIM!$Q$3)+1), ROWS(A$2:A40))),"")} | C40: {=IFERROR(INDEX(FRIM!$B$3:$B$1000, SMALL(IF(FRIM!$Q$3:$Q$1000<>"", ROW(FRIM!$Q$3:$Q$1000)-ROW(FRIM!$Q$3)+1), ROWS(A$2:A40))),"")} | D40: {=IFERROR(INDEX(FRIM!$D$3:$D$1000, SMALL(IF(FRIM!$Q$3:$Q$1000<>"", ROW(FRIM!$Q$3:$Q$1000)-ROW(FRIM!$Q$3)+1), ROWS(A$2:A40))),"")} | E40: {=IFERROR(INDEX(FRIM!$G$3:$G$1000, SMALL(IF(FRIM!$Q$3:$Q$1000<>"", ROW(FRIM!$Q$3:$Q$1000)-ROW(FRIM!$Q$3)+1), ROWS(A$2:A40))),"")} | F40: {=IFERROR(INDEX(FRIM!$Q$3:$Q$1000, SMALL(IF(FRIM!$Q$3:$Q$1000<>"", ROW(FRIM!$Q$3:$Q$1000)-ROW(FRIM!$Q$3)+1), ROWS(A$2:A40))),"")} | H40: 39 | I40: {=IFERROR(INDEX(MTIB!$E$3:$E$1000, SMALL( IF((MTIB!$Q$3:$Q$1000<>"")*(MTIB!$Q$3:$Q$1000<>"Not Due"), ROW(MTIB!$Q$3:$Q$1000)-ROW(MTIB!$Q$3)+1), ROWS(A$2:A40))),"")} | J40: {=IFERROR(INDEX(MTIB!$B$3:$B$1000, SMALL( IF((MTIB!$Q$3:$Q$1000<>"")*(MTIB!$Q$3:$Q$1000<>"Not Due"), ROW(MTIB!$Q$3:$Q$1000)-ROW(MTIB!$Q$3)+1), ROWS(A$2:A40))),"")} | K40: {=IFERROR(INDEX(MTIB!$D$3:$D$1000, SMALL( IF((MTIB!$Q$3:$Q$1000<>"")*(MTIB!$Q$3:$Q$1000<>"Not Due"), ROW(MTIB!$Q$3:$Q$1000)-ROW(MTIB!$Q$3)+1), ROWS(A$2:A40))),"")} | L40: {=IFERROR(INDEX(MTIB!$G$3:$G$1000, SMALL( IF((MTIB!$Q$3:$Q$1000<>"")*(MTIB!$Q$3:$Q$1000<>"Not Due"), ROW(MTIB!$Q$3:$Q$1000)-ROW(MTIB!$Q$3)+1), ROWS(A$2:A40))),"")} | M40: {=IFERROR(INDEX(MTIB!$Q$3:$Q$1000, SMALL( IF((MTIB!$Q$3:$Q$1000<>"")*(MTIB!$Q$3:$Q$1000<>"Not Due"), ROW(MTIB!$Q$3:$Q$1000)-ROW(MTIB!$Q$3)+1), ROWS(A$2:A40)) ),"")} | O40: 39 | P40: {=IFERROR(INDEX(MPOB!$E$3:$E$1000, SMALL( IF((MPOB!$Q$3:$Q$1000<>"")*(MPOB!$Q$3:$Q$1000<>"Not Due"), ROW(MPOB!$Q$3:$Q$1000)-ROW(MPOB!$Q$3)+1), ROWS(A$2:A40))),"")} | Q40: {=IFERROR(INDEX(MPOB!$B$3:$B$1000, SMALL( IF((MPOB!$Q$3:$Q$1000<>"")*(MPOB!$Q$3:$Q$1000<>"Not Due"), ROW(MPOB!$Q$3:$Q$1000)-ROW(MPOB!$Q$3)+1), ROWS(A$2:A40))),"")} | R40: {=IFERROR(INDEX(MPOB!$D$3:$D$1000, SMALL( IF((MPOB!$Q$3:$Q$1000<>"")*(MPOB!$Q$3:$Q$1000<>"Not Due"), ROW(MPOB!$Q$3:$Q$1000)-ROW(MPOB!$Q$3)+1), ROWS(A$2:A40))),"")} | S40: {=IFERROR(INDEX(MPOB!$G$3:$G$1000, SMALL( IF((MPOB!$Q$3:$Q$1000<>"")*(MPOB!$Q$3:$Q$1000<>"Not Due"), ROW(MPOB!$Q$3:$Q$1000)-ROW(MPOB!$Q$3)+1), ROWS(A$2:A40))),"")} | T40: {=IFERROR(INDEX(MPOB!$Q$3:$Q$1000, SMALL( IF((MPOB!$Q$3:$Q$1000<>"")*(MPOB!$Q$3:$Q$1000<>"Not Due"), ROW(MPOB!$Q$3:$Q$1000)-ROW(MPOB!$Q$3)+1), ROWS(A$2:A40)) ),"")} | V40: 39 | W40: {=IFERROR(INDEX(LKTN!$E$3:$E$1000, SMALL( IF((LKTN!$Q$3:$Q$1000<>"")*(LKTN!$Q$3:$Q$1000<>"Not Due"), ROW(LKTN!$Q$3:$Q$1000)-ROW(LKTN!$Q$3)+1), ROWS(A$2:A40))),"")} | X40: {=IFERROR(INDEX(LKTN!$B$3:$B$1000, SMALL( IF((LKTN!$Q$3:$Q$1000<>"")*(LKTN!$Q$3:$Q$1000<>"Not Due"), ROW(LKTN!$Q$3:$Q$1000)-ROW(LKTN!$Q$3)+1), ROWS(A$2:A40))),"")} | Y40: {=IFERROR(INDEX(LKTN!$D$3:$D$1000, SMALL( IF((LKTN!$Q$3:$Q$1000<>"")*(LKTN!$Q$3:$Q$1000<>"Not Due"), ROW(LKTN!$Q$3:$Q$1000)-ROW(LKTN!$Q$3)+1), ROWS(A$2:A40))),"")} | Z40: {=IFERROR(INDEX(LKTN!$G$3:$G$1000, SMALL( IF((LKTN!$Q$3:$Q$1000<>"")*(LKTN!$Q$3:$Q$1000<>"Not Due"), ROW(LKTN!$Q$3:$Q$1000)-ROW(LKTN!$Q$3)+1), ROWS(A$2:A40))),"")} | AA40: {=IFERROR(INDEX(LKTN!$Q$3:$Q$1000, SMALL( IF((LKTN!$Q$3:$Q$1000<>"")*(LKTN!$Q$3:$Q$1000<>"Not Due"), ROW(LKTN!$Q$3:$Q$1000)-ROW(LKTN!$Q$3)+1), ROWS(A$2:A40)) ),"")} | AJ40: 39 | AK40: {=IFERROR(INDEX(ISN!$E$3:$E$1000, SMALL( IF((ISN!$Q$3:$Q$1000<>"")*(ISN!$Q$3:$Q$1000<>"Not Due"), ROW(ISN!$Q$3:$Q$1000)-ROW(ISN!$Q$3)+1), ROWS(A$2:A40))),"")} | AL40: {=IFERROR(INDEX(ISN!$B$3:$B$1000, SMALL( IF((ISN!$Q$3:$Q$1000<>"")*(ISN!$Q$3:$Q$1000<>"Not Due"), ROW(ISN!$Q$3:$Q$1000)-ROW(ISN!$Q$3)+1), ROWS(A$2:A40))),"")} | AM40: {=IFERROR(INDEX(ISN!$D$3:$D$1000, SMALL( IF((ISN!$Q$3:$Q$1000<>"")*(ISN!$Q$3:$Q$1000<>"Not Due"), ROW(ISN!$Q$3:$Q$1000)-ROW(ISN!$Q$3)+1), ROWS(A$2:A40))),"")} | AN40: {=IFERROR(INDEX(ISN!$G$3:$G$1000, SMALL( IF((ISN!$Q$3:$Q$1000<>"")*(ISN!$Q$3:$Q$1000<>"Not Due"), ROW(ISN!$Q$3:$Q$1000)-ROW(ISN!$Q$3)+1), ROWS(A$2:A40))),"")} | AO40: {=IFERROR(INDEX(ISN!$Q$3:$Q$1000, SMALL( IF((ISN!$Q$3:$Q$1000<>"")*(ISN!$Q$3:$Q$1000<>"Not Due"), ROW(ISN!$Q$3:$Q$1000)-ROW(ISN!$Q$3)+1), ROWS(A$2:A40)) ),"")} | AQ40: 39 | AR40: {=IFERROR(INDEX(MSN!$E$3:$E$1000, SMALL( IF((MSN!$Q$3:$Q$1000<>"")*(MSN!$Q$3:$Q$1000<>"Not Due"), ROW(MSN!$Q$3:$Q$1000)-ROW(MSN!$Q$3)+1), ROWS(A$2:A40))),"")} | AS40: {=IFERROR(INDEX(MSN!$B$3:$B$1000, SMALL( IF((MSN!$Q$3:$Q$1000<>"")*(MSN!$Q$3:$Q$1000<>"Not Due"), ROW(MSN!$Q$3:$Q$1000)-ROW(MSN!$Q$3)+1), ROWS(A$2:A40))),"")} | AT40: {=IFERROR(INDEX(MSN!$D$3:$D$1000, SMALL( IF((MSN!$Q$3:$Q$1000<>"")*(MSN!$Q$3:$Q$1000<>"Not Due"), ROW(MSN!$Q$3:$Q$1000)-ROW(MSN!$Q$3)+1), ROWS(A$2:A40))),"")} | AU40: {=IFERROR(INDEX(MSN!$G$3:$G$1000, SMALL( IF((MSN!$Q$3:$Q$1000<>"")*(MSN!$Q$3:$Q$1000<>"Not Due"), ROW(MSN!$Q$3:$Q$1000)-ROW(MSN!$Q$3)+1), ROWS(A$2:A40))),"")} | AV40: {=IFERROR(INDEX(MSN!$Q$3:$Q$1000, SMALL( IF((MSN!$Q$3:$Q$1000<>"")*(MSN!$Q$3:$Q$1000<>"Not Due"), ROW(MSN!$Q$3:$Q$1000)-ROW(MSN!$Q$3)+1), ROWS(A$2:A40)) ),"")}
